Workbook

Sheet 仕入先マスタ
A1: 仕入先コード | B1: 仕入先名 | C1: 住所１ | D1: 住所２ | E1: 電話番号 | F1: 担当者 | G1: 支払条件 | H1: 仕入先見積税区分 | I1: 紹介文 | J1: 備考
A2: NKH | B2: NIKI HILLS
A3: NAO | B3: Nao-buns
A4: NNS | B4: にんにく種蔵 | C4: 〒060-0062 | D4: 北海道札幌市中央区南２条西１丁目５−６ 第2広和ビル | E4: 090-2035-0229 | F4: 佐藤 | G4: 月末締翌月末払い | H4: 内税 | I4: 北海道初のにんにく専門セレクトショップ。自社農園のダイヤモンドにんにくをはじめ、全国より厳選したにんにく商品を取り扱うにんにく専門店です。
A5: HNM | B5: ほんま
A6: SZS | B6: サザエ食品
A7: JEN | B7: ジョーエンタープライズ
A8: TKP | B8: トカプコーヒー
A9: HRK | B9: ハリカ
A10: VGW | B10: ベジタブルワークス
A11: MTY | B11: マルトシ吉野商店
A12: IHS | B12: 井原水産
A13: HBJ | B13: 北海道美女物語
A14: HOY | B14: 北王よいち
A15: OKK | B15: 小樽かね丁鍛冶
A16: YSS | B16: 山下水産
... A37: NVP | B37: ニセコビュープラザ
A38: HAK | B38: 北見ハッカ通商 | C38: 〒090-0056 | D38: 北海道北見市卸町1丁目7-3 | E38: 0157-66-5655 | F38: 吉田 | G38: 前金 | I38: 「北のかおり ハッカ油」でおなじみ、北見ハッカ通商です。紀元前から人々の生活に計り知れない役割を果たしてきた「天然ハッカ」は、かつて世界シェアの70％以上を北見地方で生産していた時代がありました。 この古き良き「ハッカ隆盛時代」の後、時代の変化とともに世界に誇った「ホクレン北見薄荷工場」も閉鎖。すっかり影を潜めてしまった「北見の天然ハッカ」を、今私たち北見ハッカ通商が復元しています。
A39: CSG | B39: CHISE GARDEN | C39: 〒048-1542 | D39: 北海道虻田郡ニセコ町字近藤８１７ | E39: 090-1302-4156 | F39: 平手千津子 | G39: 月末締翌月末払い | I39: 北海道ニセコ町にてワインぶどう無農薬、無化学肥料で野菜やベリーを生産加工販売しています 山野草・宿根草を中心としたガーデンづくりに奮闘中です！
A40: HAD | B40: 白亜ダイシン | C40: 〒068-0833 | D40: 北海道岩見沢市志文町292-4 | E40: 0120-70-6003 | I40: ノースファームストックには「北海道のおいしいものを蔵出しで」、という思いが込められています。自分たちの目の届く範囲で産地や生産者とつながり、良質な素材をすべて手づくりするのが基本。原点を守ることで、北海道のぬくもりや、やさしさもお伝えしたいのです。また、その思いから商品名に「北海道」を冠しています。
A41: SKA | B41: シャルキュトリーアカイシ | C41: 〒048-1551 | D41: 北海道虻田郡ニセコ町字里見11-26 | E41: 0136-55-5575 | F41: 赤石 | G41: 月末締翌月末払い | I41: 北海道ニセコならではのシャルキュトリーを生み出すため、 2018年シャルキュトリーアカイシを起業。 素材の持つ美味しさを引き出し、北海道の風土を活かしたものづくりを目指す。
A42: FSS | B42: 藤田水産 | C42: 〒078-3454 | D42: 北海道留萌郡小平町字鬼鹿広富90番地 | E42: 0164-57-1048 | F42: 藤田貢 | G42: 月末締翌月末払い | I42: タコを主に、イカ、鮭の珍味類を生産している。珍味の藤田水産の地名度アップに大きな役割を果たした「一杯だこ」は昭和38年先代のアイデアで製品化された息の長い逸品。当時棒くん（たこ足の丸ごとの燻製品）にならない小さいタコに着目、タコの姿そのまま燻製に仕上げた。
A43: YTS | B43: 谷田製菓 | C43: 〒069-1521 | D43: 北海道夕張郡栗山町錦３丁目１３４ | E43: 0123-72-1234 | F43: 木村 | G43: 月末締翌月末払い | I43: 日本一きびだんご大正１２年創製 令和５年生誕１００年を迎えます。北海道開拓の精神と関東大震災の復興を願い、起備団合の名称で発売
A44: SBR | B44: 北海道食美樂
A45: UST | B45: 上田精肉店
A46: HEF | B46: 北海道エゾシカファクトリー
A47: SEF | B47: 知床エゾシカファーム
A48: NRS | B48: ナチュラルシー
A49: ESF | B49: 東しゃこたん漁協
A50: STF | B50: 佐藤水産
A51: CCL | B51: コットンクラブ
A52: YMT | B52: ヤマト運輸
A53: BTD | B53: ベターデイズ | C53: 〒003-0029 | D53: 北海道札幌市白石区平和通二丁目北３番３０号 | E53: 090-1526-6097 | F53: 飯塚 忠志 | G53: 月末締翌月末払い | I53: 社名の｢ベターデイズ(Betterdays)｣には ”より良い明日”や”より良い未来”という想いを込めました。 北海道の産地・生産者と連携して ”より良い食文化”をご提案します！
A54: GYB | B54: 五洋物産 | D54: 北海道札幌市白石区菊水元町6条１－１－３０ | E54: 011-595-7288 | F54: 吉野 | G54: 月末締翌月末払い | I54: 長年培ってきた知床前浜の魚貝類ファーストのものづくりは、知床の魚貝マイスターが競りにおける目利き力とスタッフによる加工技術によって成しえるものであります。
A55: STK | B55: 知床工房 | D55: WEBで出てこず
A56: AUT | B56: オーセントホテル小樽
A57: KTR | B57: 京樽
A58: OTS | B58: 小樽水産加工業協同組合
A59: YAS | B59: 湯浅醤油
A60: FJK | B60: 藤岡 睦夫
A61: JKS | B61: 直商
A62: DNB | B62: DENBA JAPAN
A63: APK | B63: あぷかの森
A64: YUK | B64: ユック | D64: 根室市花園町９丁目１０番地 | E64: 0153-24-8111 | F64: 西尾裕司 | G64: 月末締翌月末払い
A65: SDH | B65: ソバージュド函館
A66: KDK | B66: 狩人の蔵
A67: KYS | B67: 協栄製茶 壱之庄
A68: SFD | B68: エスフーズ
A69: YMN | B69: ヤマニ野口水産
A70: SSK | B70: 佐々木酒造
A71: HMR | B71: ほまれ酒造
A72: YMG | B72: 大和川酒造
A73: EIS | B73: 榮川酒造
A74: NGY | B74: 名倉山酒造
A75: KND | B75: 近藤酒造
A76: UMG | B76: 梅ヶ枝酒造
... A83: KNT | B83: 紀の司酒造
A84: SMK | B84: サンマルコ食品（株） | C84: 〒542-0061 | D84: 大阪市中央区安堂寺町２－１－１０ 第１７松屋ビル9階 | E84: 06-7711-3050 | F84: 山本 | I84: サンマルコは「これ以上ない」に心からこだわり、 「北海道からもっとおいしく健康に」を掲げ、 胸を張って紹介できる商品をお届けします。
A85: OUJ | B85: 王子サーモン（株） | C85: 〒143-0013 | D85: 東京都大田区大森南１－１６－２０ | E85: 03-6423-2963 | F85: 武山 | I85: 私たちのスモークサーモンの美味しさの秘訣は、手間ひまかけた、長時間の燻煙にあります。 燻煙に使うチップは、その魚種に最適なものを選び、旨味や風味を最大限引き出すために研究を重ねました。 こだわりの素材を使い、しっかりと燻煙をかけ、可能な限り手作業で丁寧に加工するため、表面に上質なスモークスキンが出来上がります。 王子サーモンの歴史が生み出したこの飴色に光るスモークスキンが、私たちが自信を持ってお届けするスモークサーモンの美味しさの秘訣です。
A86: TSF | B86: (有)十勝しんむら牧場 | C86: 〒080-1407 | D86: 北海道河東郡上士幌町字上音更西１－２６１ | E86: 01564-2-3923 | F86: 新村浩隆 | G86: 月末締翌月末払い
A87: KGS | B87: 川口水産株式会社 | D87: 和歌山県有田市宮原町滝川原 212 | E87: 0737-88-5118
A88: FJT | B88: 株式会社フジタコーポレーション | C88: 〒048-0125 | D88: 北海道寿都郡黒松内町字目名１５２番地４ | E88: 0136-72-4416 | F88: 熊谷 一功 | G88: 月末締翌月末払い
A89: AKS | B89: （株）旭川食品 | D89: 旭川市工業団地５条３－７９８－１３ | E89: 0166-36-7700 | F89: 谷口威裕 | G89: 月末締め翌月末払い | I89: 旭川食品は北海道のど真ん中、大雪山のふもとで育った健康な黒豆を使ってふっくら美味しいお豆のスイーツを作り続けてきました。 地元食材にこだわり、お豆は近隣の契約農家さんから厳選したものを使用しています。 食材はすべて北海道産のもので まかなっていますので、新鮮で安心ですよ。 黒豆には豊富な栄養が凝縮されておりますが、カロリーは低く、健康の元がいっぱい詰まっています。黒豆の効能は様々ですが、そんなお豆を使って皆さまに「美味しい」って言っていただけるお菓子を真心込めて作っています。
A90: MIO | B90: 丸一大西食品（ベル食品） | C90: 〒063-0802 | D90: 札幌市西区二十四軒2条2丁目2番2号 | E90: 011-641-8180 | G90: 月末締め翌月末払い | I90: 北海道とともに歩んで、創業７５年。調味料で培った技術を生かし、北海道の食材を気軽に味わえるレトルト食品や、北海道の新鮮な原料にこだわったスイーツやスプレッドの販売。「北海道のソウルフードメイカー」北海道の安全・安心で、美味しい食品作りに取り組み続ける。
A91: MTS | B91: 有限会社水戸青果 | C91: 〒060-0008 | D91: 北海道札幌市中央区北8条西19丁目35−69 | E91: 011-213-9625
A92: KBY | B92: 有限会社小林食品

Sheet 商品マスタ
A1: ※灰色セルは自動入力
A2: 大分類 | B2: 小分類 | C2: 仕入先 | D2: 商品連番 | E2: 商品名 | F2: 初出フラグ | G2: シリアル | H2: 単位 | I2: 容量 | J2: 発注ロット | K2: 荷姿 | L2: 仕入 単価 | M2: 仕入価格更新日 | N2: 参考上代 （税込) | O2: 販売先利益率 （上代加味） | P2: 標準国内送料率 | Q2: 標準国内送料 | R2: 実績 国内送料 | S2: 国内送料 | T2: 仕入単価+国内送料 | U2: 海外定価 （20％） | V2: 海外定価 粗利 | W2: 国内定価 （15％） | X2: 国内定価 粗利 | Y2: 税率 | Z2: 賞味期限 | AA2: 温度帯 | AB2: 発注リードタイム | AC2: JANコード | AD2: 商品特徴 | AE2: 画像名 | AF2: EEZO 掲載可否 | AG2: 申し送り事項 在庫、支払い条件、税率、送料条件など
A3: その他 | B3: 調味料 | C3: 北見ハッカ通商 | D3: ="PRD_SNJ_"& _xlfn.XLOOKUP(商品マスタ[[#This Row],[仕入先]],テーブル1[仕入先名],テーブル1[仕入先コード],"XXX",0,1)& "_"& 商品マスタ[[#This Row],[シリアル]]& "_"& TEXT(COUNTIFS(商品マスタ!$C$3:C3,商品マスタ[[#This Row],[仕入先]],商品マスタ!$E$3:E3,商品マスタ[[#This Row],[商品名]]), "00") | E3: ハッカ油スプレー | F3: =IF(COUNTIFS($C$3:C3,商品マスタ[[#This Row],[仕入先]],$E$3:E3,商品マスタ[[#This Row],[商品名]]) = 1, 1,0) | G3: =TEXT(SUMIF($C$3:C3,商品マスタ[[#This Row],[仕入先]],$F$3:F3), "0000") | H3: 本 | I3: 11.5ml | J3: 100 | L3: 715 | M3: 45950 | N3: 1188 | O3: =IF(COUNT(商品マスタ[[#This Row],[参考上代 （税込)]]) > 0, (商品マスタ[[#This Row],[参考上代 （税込)]]-商品マスタ[[#This Row],[国内定価 （15％）]])/(商品マスタ[[#This Row],[参考上代 （税込)]]/1.08), "") | P3: 0.1 | Q3: =商品マスタ[[#This Row],[仕入 単価]]*商品マスタ[[#This Row],[標準国内送料率]] | S3: =IF(ISBLANK(商品マスタ[[#This Row],[実績 国内送料]]),商品マスタ[[#This Row],[標準国内送料]],) | T3: =商品マスタ[[#This Row],[仕入 単価]]+商品マスタ[[#This Row],[国内送料]] | U3: =ROUNDUP(商品マスタ[[#This Row],[仕入単価+国内送料]]/0.8,-1) | V3: =商品マスタ[[#This Row],[海外定価 （20％）]]-商品マスタ[[#This Row],[仕入単価+国内送料]] | W3: =ROUNDUP(商品マスタ[[#This Row],[仕入単価+国内送料]]/0.85,-1) | X3: =商品マスタ[[#This Row],[国内定価 （15％）]]-商品マスタ[[#This Row],[仕入単価+国内送料]] | Y3: 0.08 | Z3: 3年 | AA3: 常温 | AB3: 7日 | AC3: 4985146001639 | AD3: 北のかおり ハッカ油、人気のスプレータイプです。天然ミントの瓶詰です。安心の食品無添加です。 | AF3: 〇 | AG3: 前金。振込後発送。ハッカ油は軽減税率8％対象。販売の際は「定価厳守」契約書交わし済み
A4: その他 | B4: 調味料 | C4: 北見ハッカ通商 | D4: ="PRD_SNJ_"& _xlfn.XLOOKUP(商品マスタ[[#This Row],[仕入先]],テーブル1[仕入先名],テーブル1[仕入先コード],"XXX",0,1)& "_"& 商品マスタ[[#This Row],[シリアル]]& "_"& TEXT(COUNTIFS(商品マスタ!$C$3:C4,商品マスタ[[#This Row],[仕入先]],商品マスタ!$E$3:E4,商品マスタ[[#This Row],[商品名]]), "00") | E4: ハッカ油スプレーR | F4: =IF(COUNTIFS($C$3:C4,商品マスタ[[#This Row],[仕入先]],$E$3:E4,商品マスタ[[#This Row],[商品名]]) = 1, 1,0) | G4: =TEXT(SUMIF($C$3:C4,商品マスタ[[#This Row],[仕入先]],$F$3:F4), "0000") | H4: 本 | I4: 10ml | J4: 100 | L4: 650 | M4: 45950 | N4: 1080 | O4: =IF(COUNT(商品マスタ[[#This Row],[参考上代 （税込)]]) > 0, (商品マスタ[[#This Row],[参考上代 （税込)]]-商品マスタ[[#This Row],[国内定価 （15％）]])/(商品マスタ[[#This Row],[参考上代 （税込)]]/1.08), "") | P4: 0.1 | Q4: =商品マスタ[[#This Row],[仕入 単価]]*商品マスタ[[#This Row],[標準国内送料率]] | S4: =IF(ISBLANK(商品マスタ[[#This Row],[実績 国内送料]]),商品マスタ[[#This Row],[標準国内送料]],) | T4: =商品マスタ[[#This Row],[仕入 単価]]+商品マスタ[[#This Row],[国内送料]] | U4: =ROUNDUP(商品マスタ[[#This Row],[仕入単価+国内送料]]/0.8,-1) | V4: =商品マスタ[[#This Row],[海外定価 （20％）]]-商品マスタ[[#This Row],[仕入単価+国内送料]] | W4: =ROUNDUP(商品マスタ[[#This Row],[仕入単価+国内送料]]/0.85,-1) | X4: =商品マスタ[[#This Row],[国内定価 （15％）]]-商品マスタ[[#This Row],[仕入単価+国内送料]] | Y4: 0.08 | Z4: 3年 | AA4: 常温 | AB4: 7日 | AC4: 4985146001042 | AD4: 少量ずつ塗るのに便利なロールオンタイプ。お好きな場所にクルクルと塗り込んでください。天然ミントで、安心の食品無添加です。 | AF4: 〇 | AG4: 前金。振込後発送。ハッカ油は軽減税率8％対象。販売の際は「定価厳守」契約書交わし済み
A5: 菓子 | B5: 和菓子 | C5: 北見ハッカ通商 | D5: ="PRD_SNJ_"& _xlfn.XLOOKUP(商品マスタ[[#This Row],[仕入先]],テーブル1[仕入先名],テーブル1[仕入先コード],"XXX",0,1)& "_"& 商品マスタ[[#This Row],[シリアル]]& "_"& TEXT(COUNTIFS(商品マスタ!$C$3:C5,商品マスタ[[#This Row],[仕入先]],商品マスタ!$E$3:E5,商品マスタ[[#This Row],[商品名]]), "00") | E5: ハッカ飴 | F5: =IF(COUNTIFS($C$3:C5,商品マスタ[[#This Row],[仕入先]],$E$3:E5,商品マスタ[[#This Row],[商品名]]) = 1, 1,0) | G5: =TEXT(SUMIF($C$3:C5,商品マスタ[[#This Row],[仕入先]],$F$3:F5), "0000") | H5: 袋 | I5: 240g | J5: 200 | L5: 287 | M5: 45950 | N5: 443 | O5: =IF(COUNT(商品マスタ[[#This Row],[参考上代 （税込)]]) > 0, (商品マスタ[[#This Row],[参考上代 （税込)]]-商品マスタ[[#This Row],[国内定価 （15％）]])/(商品マスタ[[#This Row],[参考上代 （税込)]]/1.08), "") | P5: 0.1 | Q5: =商品マスタ[[#This Row],[仕入 単価]]*商品マスタ[[#This Row],[標準国内送料率]] | S5: =IF(ISBLANK(商品マスタ[[#This Row],[実績 国内送料]]),商品マスタ[[#This Row],[標準国内送料]],) | T5: =商品マスタ[[#This Row],[仕入 単価]]+商品マスタ[[#This Row],[国内送料]] | U5: =ROUNDUP(商品マスタ[[#This Row],[仕入単価+国内送料]]/0.8,-1) | V5: =商品マスタ[[#This Row],[海外定価 （20％）]]-商品マスタ[[#This Row],[仕入単価+国内送料]] | W5: =ROUNDUP(商品マスタ[[#This Row],[仕入単価+国内送料]]/0.85,-1) | X5: =商品マスタ[[#This Row],[国内定価 （15％）]]-商品マスタ[[#This Row],[仕入単価+国内送料]] | Y5: 0.08 | Z5: 13か月 | AA5: 常温 | AB5: 7日 | AC5: 4985146000649 | AD5: ロングセラー商品、ハッカ飴です。 | AF5: 〇 | AG5: 前金。振込後発送。販売の際は「定価厳守」契約書交わし済み
A6: 菓子 | B6: 和菓子 | C6: 北見ハッカ通商 | D6: ="PRD_SNJ_"& _xlfn.XLOOKUP(商品マスタ[[#This Row],[仕入先]],テーブル1[仕入先名],テーブル1[仕入先コード],"XXX",0,1)& "_"& 商品マスタ[[#This Row],[シリアル]]& "_"& TEXT(COUNTIFS(商品マスタ!$C$3:C6,商品マスタ[[#This Row],[仕入先]],商品マスタ!$E$3:E6,商品マスタ[[#This Row],[商品名]]), "00") | E6: CHOCOMINT CANDY | F6: =IF(COUNTIFS($C$3:C6,商品マスタ[[#This Row],[仕入先]],$E$3:E6,商品マスタ[[#This Row],[商品名]]) = 1, 1,0) | G6: =TEXT(SUMIF($C$3:C6,商品マスタ[[#This Row],[仕入先]],$F$3:F6), "0000") | H6: 袋 | I6: 170g | J6: 200 | L6: 287 | M6: 45950 | N6: 442 | O6: =IF(COUNT(商品マスタ[[#This Row],[参考上代 （税込)]]) > 0, (商品マスタ[[#This Row],[参考上代 （税込)]]-商品マスタ[[#This Row],[国内定価 （15％）]])/(商品マスタ[[#This Row],[参考上代 （税込)]]/1.08), "") | P6: 0.1 | Q6: =商品マスタ[[#This Row],[仕入 単価]]*商品マスタ[[#This Row],[標準国内送料率]] | S6: =IF(ISBLANK(商品マスタ[[#This Row],[実績 国内送料]]),商品マスタ[[#This Row],[標準国内送料]],) | T6: =商品マスタ[[#This Row],[仕入 単価]]+商品マスタ[[#This Row],[国内送料]] | U6: =ROUNDUP(商品マスタ[[#This Row],[仕入単価+国内送料]]/0.8,-1) | V6: =商品マスタ[[#This Row],[海外定価 （20％）]]-商品マスタ[[#This Row],[仕入単価+国内送料]] | W6: =ROUNDUP(商品マスタ[[#This Row],[仕入単価+国内送料]]/0.85,-1) | X6: =商品マスタ[[#This Row],[国内定価 （15％）]]-商品マスタ[[#This Row],[仕入単価+国内送料]] | Y6: 0.08 | Z6: 13か月 | AA6: 常温 | AB6: 7日 | AC6: 4985146000908 | AD6: 和種ハッカと香ばしいカカオニブが混ざり合う、チョコミント風味のキャンディーです。 | AF6: 〇 | AG6: 前金。振込後発送。販売の際は「定価厳守」契約書交わし済み
A7: 菓子 | B7: 和菓子 | C7: 北見ハッカ通商 | D7: ="PRD_SNJ_"& _xlfn.XLOOKUP(商品マスタ[[#This Row],[仕入先]],テーブル1[仕入先名],テーブル1[仕入先コード],"XXX",0,1)& "_"& 商品マスタ[[#This Row],[シリアル]]& "_"& TEXT(COUNTIFS(商品マスタ!$C$3:C7,商品マスタ[[#This Row],[仕入先]],商品マスタ!$E$3:E7,商品マスタ[[#This Row],[商品名]]), "00") | E7: フルーツミントキャンデー・パイナップル味 | F7: =IF(COUNTIFS($C$3:C7,商品マスタ[[#This Row],[仕入先]],$E$3:E7,商品マスタ[[#This Row],[商品名]]) = 1, 1,0) | G7: =TEXT(SUMIF($C$3:C7,商品マスタ[[#This Row],[仕入先]],$F$3:F7), "0000") | H7: 袋 | I7: 170g | J7: 24 | K7: 24袋/箱 | L7: 287 | M7: 45950 | N7: 442 | O7: =IF(COUNT(商品マスタ[[#This Row],[参考上代 （税込)]]) > 0, (商品マスタ[[#This Row],[参考上代 （税込)]]-商品マスタ[[#This Row],[国内定価 （15％）]])/(商品マスタ[[#This Row],[参考上代 （税込)]]/1.08), "") | P7: 0.1 | Q7: =商品マスタ[[#This Row],[仕入 単価]]*商品マスタ[[#This Row],[標準国内送料率]] | S7: =IF(ISBLANK(商品マスタ[[#This Row],[実績 国内送料]]),商品マスタ[[#This Row],[標準国内送料]],) | T7: =商品マスタ[[#This Row],[仕入 単価]]+商品マスタ[[#This Row],[国内送料]] | U7: =ROUNDUP(商品マスタ[[#This Row],[仕入単価+国内送料]]/0.8,-1) | V7: =商品マスタ[[#This Row],[海外定価 （20％）]]-商品マスタ[[#This Row],[仕入単価+国内送料]] | W7: =ROUNDUP(商品マスタ[[#This Row],[仕入単価+国内送料]]/0.85,-1) | X7: =商品マスタ[[#This Row],[国内定価 （15％）]]-商品マスタ[[#This Row],[仕入単価+国内送料]] | Y7: 0.08 | Z7: 13か月 | AA7: 常温 | AB7: 7日 | AC7: 4985146000953 | AD7: ミントの仲間「パイナップルミント」をイメージしたキャンディー。 南国を想わせる甘く芳醇なパイナップルの風味とミントの清涼感をミックスして、爽やかな甘さのある味に仕上げました。 | AF7: 〇 | AG7: 前金。振込後発送。販売の際は「定価厳守」契約書交わし済み
A8: 菓子 | B8: 和菓子 | C8: 北見ハッカ通商 | D8: ="PRD_SNJ_"& _xlfn.XLOOKUP(商品マスタ[[#This Row],[仕入先]],テーブル1[仕入先名],テーブル1[仕入先コード],"XXX",0,1)& "_"& 商品マスタ[[#This Row],[シリアル]]& "_"& TEXT(COUNTIFS(商品マスタ!$C$3:C8,商品マスタ[[#This Row],[仕入先]],商品マスタ!$E$3:E8,商品マスタ[[#This Row],[商品名]]), "00") | E8: フルーツミントキャンデー・アップル味 | F8: =IF(COUNTIFS($C$3:C8,商品マスタ[[#This Row],[仕入先]],$E$3:E8,商品マスタ[[#This Row],[商品名]]) = 1, 1,0) | G8: =TEXT(SUMIF($C$3:C8,商品マスタ[[#This Row],[仕入先]],$F$3:F8), "0000") | H8: 袋 | I8: 170g | J8: 24 | K8: 24袋/箱 | L8: 287 | M8: 45950 | N8: 442 | O8: =IF(COUNT(商品マスタ[[#This Row],[参考上代 （税込)]]) > 0, (商品マスタ[[#This Row],[参考上代 （税込)]]-商品マスタ[[#This Row],[国内定価 （15％）]])/(商品マスタ[[#This Row],[参考上代 （税込)]]/1.08), "") | P8: 0.1 | Q8: =商品マスタ[[#This Row],[仕入 単価]]*商品マスタ[[#This Row],[標準国内送料率]] | S8: =IF(ISBLANK(商品マスタ[[#This Row],[実績 国内送料]]),商品マスタ[[#This Row],[標準国内送料]],) | T8: =商品マスタ[[#This Row],[仕入 単価]]+商品マスタ[[#This Row],[国内送料]] | U8: =ROUNDUP(商品マスタ[[#This Row],[仕入単価+国内送料]]/0.8,-1) | V8: =商品マスタ[[#This Row],[海外定価 （20％）]]-商品マスタ[[#This Row],[仕入単価+国内送料]] | W8: =ROUNDUP(商品マスタ[[#This Row],[仕入単価+国内送料]]/0.85,-1) | X8: =商品マスタ[[#This Row],[国内定価 （15％）]]-商品マスタ[[#This Row],[仕入単価+国内送料]] | Y8: 0.08 | Z8: 13か月 | AA8: 常温 | AB8: 7日 | AC8: 4985146000960 | AD8: ミントの仲間「アップルミント」をイメージしたミントキャンディー。アップルの後味さっぱりとした甘さとミントの清涼感を合わせて、軽やかなスッキリとした味に仕上げました。 | AF8: 〇 | AG8: 前金。振込後発送。販売の際は「定価厳守」契約書交わし済み
A9: 菓子 | B9: 和菓子 | C9: 北見ハッカ通商 | D9: ="PRD_SNJ_"& _xlfn.XLOOKUP(商品マスタ[[#This Row],[仕入先]],テーブル1[仕入先名],テーブル1[仕入先コード],"XXX",0,1)& "_"& 商品マスタ[[#This Row],[シリアル]]& "_"& TEXT(COUNTIFS(商品マスタ!$C$3:C9,商品マスタ[[#This Row],[仕入先]],商品マスタ!$E$3:E9,商品マスタ[[#This Row],[商品名]]), "00") | E9: フルーツミントキャンデー・レモン味 | F9: =IF(COUNTIFS($C$3:C9,商品マスタ[[#This Row],[仕入先]],$E$3:E9,商品マスタ[[#This Row],[商品名]]) = 1, 1,0) | G9: =TEXT(SUMIF($C$3:C9,商品マスタ[[#This Row],[仕入先]],$F$3:F9), "0000") | H9: 袋 | I9: 170g | J9: 24 | K9: 24袋/箱 | L9: 287 | M9: 45950 | N9: 442 | O9: =IF(COUNT(商品マスタ[[#This Row],[参考上代 （税込)]]) > 0, (商品マスタ[[#This Row],[参考上代 （税込)]]-商品マスタ[[#This Row],[国内定価 （15％）]])/(商品マスタ[[#This Row],[参考上代 （税込)]]/1.08), "") | P9: 0.1 | Q9: =商品マスタ[[#This Row],[仕入 単価]]*商品マスタ[[#This Row],[標準国内送料率]] | S9: =IF(ISBLANK(商品マスタ[[#This Row],[実績 国内送料]]),商品マスタ[[#This Row],[標準国内送料]],) | T9: =商品マスタ[[#This Row],[仕入 単価]]+商品マスタ[[#This Row],[国内送料]] | U9: =ROUNDUP(商品マスタ[[#This Row],[仕入単価+国内送料]]/0.8,-1) | V9: =商品マスタ[[#This Row],[海外定価 （20％）]]-商品マスタ[[#This Row],[仕入単価+国内送料]] | W9: =ROUNDUP(商品マスタ[[#This Row],[仕入単価+国内送料]]/0.85,-1) | X9: =商品マスタ[[#This Row],[国内定価 （15％）]]-商品マスタ[[#This Row],[仕入単価+国内送料]] | Y9: 0.08 | Z9: 13か月 | AA9: 常温 | AB9: 7日 | AC9: 4985146000922 | AD9: ミントの仲間「レモンバーム、レモンミント」をイメージしたキャンディー。レモンのしっかりとした酸味とミントの清涼感をミックスして、爽やかなキレのある味に仕上げました。 | AF9: 〇 | AG9: 前金。振込後発送。販売の際は「定価厳守」契約書交わし済み
A10: 菓子 | B10: 和菓子 | C10: 北見ハッカ通商 | D10: ="PRD_SNJ_"& _xlfn.XLOOKUP(商品マスタ[[#This Row],[仕入先]],テーブル1[仕入先名],テーブル1[仕入先コード],"XXX",0,1)& "_"& 商品マスタ[[#This Row],[シリアル]]& "_"& TEXT(COUNTIFS(商品マスタ!$C$3:C10,商品マスタ[[#This Row],[仕入先]],商品マスタ!$E$3:E10,商品マスタ[[#This Row],[商品名]]), "00") | E10: フルーツミントキャンデー・オレンジ味 | F10: =IF(COUNTIFS($C$3:C10,商品マスタ[[#This Row],[仕入先]],$E$3:E10,商品マスタ[[#This Row],[商品名]]) = 1, 1,0) | G10: =TEXT(SUMIF($C$3:C10,商品マスタ[[#This Row],[仕入先]],$F$3:F10), "0000") | H10: 袋 | I10: 170g | J10: 24 | K10: 24袋/箱 | L10: 287 | M10: 45950 | N10: 442 | O10: =IF(COUNT(商品マスタ[[#This Row],[参考上代 （税込)]]) > 0, (商品マスタ[[#This Row],[参考上代 （税込)]]-商品マスタ[[#This Row],[国内定価 （15％）]])/(商品マスタ[[#This Row],[参考上代 （税込)]]/1.08), "") | P10: 0.1 | Q10: =商品マスタ[[#This Row],[仕入 単価]]*商品マスタ[[#This Row],[標準国内送料率]] | S10: =IF(ISBLANK(商品マスタ[[#This Row],[実績 国内送料]]),商品マスタ[[#This Row],[標準国内送料]],) | T10: =商品マスタ[[#This Row],[仕入 単価]]+商品マスタ[[#This Row],[国内送料]] | U10: =ROUNDUP(商品マスタ[[#This Row],[仕入単価+国内送料]]/0.8,-1) | V10: =商品マスタ[[#This Row],[海外定価 （20％）]]-商品マスタ[[#This Row],[仕入単価+国内送料]] | W10: =ROUNDUP(商品マスタ[[#This Row],[仕入単価+国内送料]]/0.85,-1) | X10: =商品マスタ[[#This Row],[国内定価 （15％）]]-商品マスタ[[#This Row],[仕入単価+国内送料]] | Y10: 0.08 | Z10: 13か月 | AA10: 常温 | AB10: 7日 | AC10: 4985146000946 | AD10: ミントの仲間「オレンジミント」をイメージしたキャンディー。 濃厚なオレンジの風味とミントを合わせて、ジューシーな甘さと香りの広がる味に仕上げました。 | AF10: 〇 | AG10: 前金。振込後発送。販売の際は「定価厳守」契約書交わし済み
A11: 菓子 | B11: 和菓子 | C11: 北見ハッカ通商 | D11: ="PRD_SNJ_"& _xlfn.XLOOKUP(商品マスタ[[#This Row],[仕入先]],テーブル1[仕入先名],テーブル1[仕入先コード],"XXX",0,1)& "_"& 商品マスタ[[#This Row],[シリアル]]& "_"& TEXT(COUNTIFS(商品マスタ!$C$3:C11,商品マスタ[[#This Row],[仕入先]],商品マスタ!$E$3:E11,商品マスタ[[#This Row],[商品名]]), "00") | E11: フルーツミントキャンデー・グレープフルーツ味 | F11: =IF(COUNTIFS($C$3:C11,商品マスタ[[#This Row],[仕入先]],$E$3:E11,商品マスタ[[#This Row],[商品名]]) = 1, 1,0) | G11: =TEXT(SUMIF($C$3:C11,商品マスタ[[#This Row],[仕入先]],$F$3:F11), "0000") | H11: 袋 | I11: 170g | J11: 24 | K11: 24袋/箱 | L11: 287 | M11: 45950 | N11: 442 | O11: =IF(COUNT(商品マスタ[[#This Row],[参考上代 （税込)]]) > 0, (商品マスタ[[#This Row],[参考上代 （税込)]]-商品マスタ[[#This Row],[国内定価 （15％）]])/(商品マスタ[[#This Row],[参考上代 （税込)]]/1.08), "") | P11: 0.1 | Q11: =商品マスタ[[#This Row],[仕入 単価]]*商品マスタ[[#This Row],[標準国内送料率]] | S11: =IF(ISBLANK(商品マスタ[[#This Row],[実績 国内送料]]),商品マスタ[[#This Row],[標準国内送料]],) | T11: =商品マスタ[[#This Row],[仕入 単価]]+商品マスタ[[#This Row],[国内送料]] | U11: =ROUNDUP(商品マスタ[[#This Row],[仕入単価+国内送料]]/0.8,-1) | V11: =商品マスタ[[#This Row],[海外定価 （20％）]]-商品マスタ[[#This Row],[仕入単価+国内送料]] | W11: =ROUNDUP(商品マスタ[[#This Row],[仕入単価+国内送料]]/0.85,-1) | X11: =商品マスタ[[#This Row],[国内定価 （15％）]]-商品マスタ[[#This Row],[仕入単価+国内送料]] | Y11: 0.08 | Z11: 13か月 | AA11: 常温 | AB11: 7日 | AC11: 4985146000984 | AD11: ミントの仲間「グレープフルーツミント」をイメージしたキャンディー。グレープフルーツが持つ柑橘系のさっぱりとした爽やかさにミントの清涼感をミックス。後味スッキリ爽快な味に仕上げました。 | AF11: 〇 | AG11: 前金。振込後発送。販売の際は「定価厳守」契約書交わし済み
A12: 菓子 | B12: 和菓子 | C12: 北見ハッカ通商 | D12: ="PRD_SNJ_"& _xlfn.XLOOKUP(商品マスタ[[#This Row],[仕入先]],テーブル1[仕入先名],テーブル1[仕入先コード],"XXX",0,1)& "_"& 商品マスタ[[#This Row],[シリアル]]& "_"& TEXT(COUNTIFS(商品マスタ!$C$3:C12,商品マスタ[[#This Row],[仕入先]],商品マスタ!$E$3:E12,商品マスタ[[#This Row],[商品名]]), "00") | E12: フルーツミントキャンデー・グレープ味 | F12: =IF(COUNTIFS($C$3:C12,商品マスタ[[#This Row],[仕入先]],$E$3:E12,商品マスタ[[#This Row],[商品名]]) = 1, 1,0) | G12: =TEXT(SUMIF($C$3:C12,商品マスタ[[#This Row],[仕入先]],$F$3:F12), "0000") | H12: 袋 | I12: 180g | J12: 24 | K12: 24袋/箱 | L12: 287 | M12: 45950 | N12: 442 | O12: =IF(COUNT(商品マスタ[[#This Row],[参考上代 （税込)]]) > 0, (商品マスタ[[#This Row],[参考上代 （税込)]]-商品マスタ[[#This Row],[国内定価 （15％）]])/(商品マスタ[[#This Row],[参考上代 （税込)]]/1.08), "") | P12: 0.1 | Q12: =商品マスタ[[#This Row],[仕入 単価]]*商品マスタ[[#This Row],[標準国内送料率]] | S12: =IF(ISBLANK(商品マスタ[[#This Row],[実績 国内送料]]),商品マスタ[[#This Row],[標準国内送料]],) | T12: =商品マスタ[[#This Row],[仕入 単価]]+商品マスタ[[#This Row],[国内送料]] | U12: =ROUNDUP(商品マスタ[[#This Row],[仕入単価+国内送料]]/0.8,-1) | V12: =商品マスタ[[#This Row],[海外定価 （20％）]]-商品マスタ[[#This Row],[仕入単価+国内送料]] | W12: =ROUNDUP(商品マスタ[[#This Row],[仕入単価+国内送料]]/0.85,-1) | X12: =商品マスタ[[#This Row],[国内定価 （15％）]]-商品マスタ[[#This Row],[仕入単価+国内送料]] | Y12: 0.08 | Z12: 13か月 | AA12: 常温 | AB12: 7日 | AC12: 4985146000939 | AD12: グレープのジューシーな甘さと香りにミントの清涼感を合わせて、フルーティーな香り広がる爽やかな味に仕上げました。 | AF12: 〇 | AG12: 前金。振込後発送。販売の際は「定価厳守」契約書交わし済み。税抜仕入額6万以上で無料
A13: 菓子 | B13: 和菓子 | C13: 北見ハッカ通商 | D13: ="PRD_SNJ_"& _xlfn.XLOOKUP(商品マスタ[[#This Row],[仕入先]],テーブル1[仕入先名],テーブル1[仕入先コード],"XXX",0,1)& "_"& 商品マスタ[[#This Row],[シリアル]]& "_"& TEXT(COUNTIFS(商品マスタ!$C$3:C13,商品マスタ[[#This Row],[仕入先]],商品マスタ!$E$3:E13,商品マスタ[[#This Row],[商品名]]), "00") | E13: フルーツミントキャンデー・ピーチ味 | F13: =IF(COUNTIFS($C$3:C13,商品マスタ[[#This Row],[仕入先]],$E$3:E13,商品マスタ[[#This Row],[商品名]]) = 1, 1,0) | G13: =TEXT(SUMIF($C$3:C13,商品マスタ[[#This Row],[仕入先]],$F$3:F13), "0000") | H13: 袋 | I13: 180g | J13: 24 | K13: 24袋/箱 | L13: 287 | M13: 45950 | N13: 442 | O13: =IF(COUNT(商品マスタ[[#This Row],[参考上代 （税込)]]) > 0, (商品マスタ[[#This Row],[参考上代 （税込)]]-商品マスタ[[#This Row],[国内定価 （15％）]])/(商品マスタ[[#This Row],[参考上代 （税込)]]/1.08), "") | P13: 0.1 | Q13: =商品マスタ[[#This Row],[仕入 単価]]*商品マスタ[[#This Row],[標準国内送料率]] | S13: =IF(ISBLANK(商品マスタ[[#This Row],[実績 国内送料]]),商品マスタ[[#This Row],[標準国内送料]],) | T13: =商品マスタ[[#This Row],[仕入 単価]]+商品マスタ[[#This Row],[国内送料]] | U13: =ROUNDUP(商品マスタ[[#This Row],[仕入単価+国内送料]]/0.8,-1) | V13: =商品マスタ[[#This Row],[海外定価 （20％）]]-商品マスタ[[#This Row],[仕入単価+国内送料]] | W13: =ROUNDUP(商品マスタ[[#This Row],[仕入単価+国内送料]]/0.85,-1) | X13: =商品マスタ[[#This Row],[国内定価 （15％）]]-商品マスタ[[#This Row],[仕入単価+国内送料]] | Y13: 0.08 | Z13: 13か月 | AA13: 常温 | AB13: 7日 | AC13: 4985146000977 | AD13: 口の中でジューシーに広がる甘い豊かなピーチの風味とミントの清涼感をマッチさせ、やさしく甘いスッキリした味に仕上げました。 | AF13: 〇 | AG13: 前金。振込後発送。販売の際は「定価厳守」契約書交わし済み。税抜仕入額6万以上で無料
A14: 菓子 | B14: 和菓子 | C14: 北見ハッカ通商 | D14: ="PRD_SNJ_"& _xlfn.XLOOKUP(商品マスタ[[#This Row],[仕入先]],テーブル1[仕入先名],テーブル1[仕入先コード],"XXX",0,1)& "_"& 商品マスタ[[#This Row],[シリアル]]& "_"& TEXT(COUNTIFS(商品マスタ!$C$3:C14,商品マスタ[[#This Row],[仕入先]],商品マスタ!$E$3:E14,商品マスタ[[#This Row],[商品名]]), "00") | E14: フルーツミントキャンデー・ストロベリー味 | F14: =IF(COUNTIFS($C$3:C14,商品マスタ[[#This Row],[仕入先]],$E$3:E14,商品マスタ[[#This Row],[商品名]]) = 1, 1,0) | G14: =TEXT(SUMIF($C$3:C14,商品マスタ[[#This Row],[仕入先]],$F$3:F14), "0000") | H14: 袋 | I14: 180g | J14: 24 | K14: 24袋/箱 | L14: 287 | M14: 45950 | N14: 442 | O14: =IF(COUNT(商品マスタ[[#This Row],[参考上代 （税込)]]) > 0, (商品マスタ[[#This Row],[参考上代 （税込)]]-商品マスタ[[#This Row],[国内定価 （15％）]])/(商品マスタ[[#This Row],[参考上代 （税込)]]/1.08), "") | P14: 0.1 | Q14: =商品マスタ[[#This Row],[仕入 単価]]*商品マスタ[[#This Row],[標準国内送料率]] | S14: =IF(ISBLANK(商品マスタ[[#This Row],[実績 国内送料]]),商品マスタ[[#This Row],[標準国内送料]],) | T14: =商品マスタ[[#This Row],[仕入 単価]]+商品マスタ[[#This Row],[国内送料]] | U14: =ROUNDUP(商品マスタ[[#This Row],[仕入単価+国内送料]]/0.8,-1) | V14: =商品マスタ[[#This Row],[海外定価 （20％）]]-商品マスタ[[#This Row],[仕入単価+国内送料]] | W14: =ROUNDUP(商品マスタ[[#This Row],[仕入単価+国内送料]]/0.85,-1) | X14: =商品マスタ[[#This Row],[国内定価 （15％）]]-商品マスタ[[#This Row],[仕入単価+国内送料]] | Y14: 0.08 | Z14: 13か月 | AA14: 常温 | AB14: 7日 | AC14: 4985146000915 | AD14: ミントの仲間「ストロベリーミント」をイメージしたミントキャンディー。ストロベリーのしっかりとした甘い香りの風味とミントの清涼感を合わせて、フルーティーな甘さとスッキリとした爽やかな味に仕上げました。 | AF14: 〇 | AG14: 前金。振込後発送。販売の際は「定価厳守」契約書交わし済み。税抜仕入額6万以上で無料
A15: 菓子 | B15: 和菓子 | C15: 北見ハッカ通商 | D15: ="PRD_SNJ_"& _xlfn.XLOOKUP(商品マスタ[[#This Row],[仕入先]],テーブル1[仕入先名],テーブル1[仕入先コード],"XXX",0,1)& "_"& 商品マスタ[[#This Row],[シリアル]]& "_"& TEXT(COUNTIFS(商品マスタ!$C$3:C15,商品マスタ[[#This Row],[仕入先]],商品マスタ!$E$3:E15,商品マスタ[[#This Row],[商品名]]), "00") | E15: フルーツミント Mixキャンディ BOX | F15: =IF(COUNTIFS($C$3:C15,商品マスタ[[#This Row],[仕入先]],$E$3:E15,商品マスタ[[#This Row],[商品名]]) = 1, 1,0) | G15: =TEXT(SUMIF($C$3:C15,商品マスタ[[#This Row],[仕入先]],$F$3:F15), "0000") | H15: 缶 | I15: 360g | J15: 30 | K15: 30缶/箱 | L15: 700 | M15: 45950 | N15: 1080 | O15: =IF(COUNT(商品マスタ[[#This Row],[参考上代 （税込)]]) > 0, (商品マスタ[[#This Row],[参考上代 （税込)]]-商品マスタ[[#This Row],[国内定価 （15％）]])/(商品マスタ[[#This Row],[参考上代 （税込)]]/1.08), "") | P15: 0.1 | Q15: =商品マスタ[[#This Row],[仕入 単価]]*商品マスタ[[#This Row],[標準国内送料率]] | S15: =IF(ISBLANK(商品マスタ[[#This Row],[実績 国内送料]]),商品マスタ[[#This Row],[標準国内送料]],) | T15: =商品マスタ[[#This Row],[仕入 単価]]+商品マスタ[[#This Row],[国内送料]] | U15: =ROUNDUP(商品マスタ[[#This Row],[仕入単価+国内送料]]/0.8,-1) | V15: =商品マスタ[[#This Row],[海外定価 （20％）]]-商品マスタ[[#This Row],[仕入単価+国内送料]] | W15: =ROUNDUP(商品マスタ[[#This Row],[仕入単価+国内送料]]/0.85,-1) | X15: =商品マスタ[[#This Row],[国内定価 （15％）]]-商品マスタ[[#This Row],[仕入単価+国内送料]] | Y15: 0.08 | Z15: 13か月 | AA15: 常温 | AB15: 3週間 | AC15: 4985146001134 | AD15: ※受注生産品 ロングセラーのハッカ飴に、カカオニブを使用したチョコミントキャンディー、8種類のフルーツミントキャンディーを詰め合わせた、10種類の味をお楽しみいただけるキャンディーBOXです。 | AF15: 〇 | AG15: 前金。振込後発送。販売の際は「定価厳守」契約書交わし済み。税抜仕入額6万以上で無料
A16: 菓子 | B16: 和菓子 | C16: 北見ハッカ通商 | D16: ="PRD_SNJ_"& _xlfn.XLOOKUP(商品マスタ[[#This Row],[仕入先]],テーブル1[仕入先名],テーブル1[仕入先コード],"XXX",0,1)& "_"& 商品マスタ[[#This Row],[シリアル]]& "_"& TEXT(COUNTIFS(商品マスタ!$C$3:C16,商品マスタ[[#This Row],[仕入先]],商品マスタ!$E$3:E16,商品マスタ[[#This Row],[商品名]]), "00") | E16: ハッカ飴（メントール増量）缶 | F16: =IF(COUNTIFS($C$3:C16,商品マスタ[[#This Row],[仕入先]],$E$3:E16,商品マスタ[[#This Row],[商品名]]) = 1, 1,0) | G16: =TEXT(SUMIF($C$3:C16,商品マスタ[[#This Row],[仕入先]],$F$3:F16), "0000") | H16: 缶 | I16: 170g | J16: 100 | K16: 100缶/箱 | L16: 385 | M16: 45950 | N16: 594 | O16: =IF(COUNT(商品マスタ[[#This Row],[参考上代 （税込)]]) > 0, (商品マスタ[[#This Row],[参考上代 （税込)]]-商品マスタ[[#This Row],[国内定価 （15％）]])/(商品マスタ[[#This Row],[参考上代 （税込)]]/1.08), "") | P16: 0.1 | Q16: =商品マスタ[[#This Row],[仕入 単価]]*商品マスタ[[#This Row],[標準国内送料率]] | S16: =IF(ISBLANK(商品マスタ[[#This Row],[実績 国内送料]]),商品マスタ[[#This Row],[標準国内送料]],) | T16: =商品マスタ[[#This Row],[仕入 単価]]+商品マスタ[[#This Row],[国内送料]] | U16: =ROUNDUP(商品マスタ[[#This Row],[仕入単価+国内送料]]/0.8,-1) | V16: =商品マスタ[[#This Row],[海外定価 （20％）]]-商品マスタ[[#This Row],[仕入単価+国内送料]] | W16: =ROUNDUP(商品マスタ[[#This Row],[仕入単価+国内送料]]/0.85,-1) | X16: =商品マスタ[[#This Row],[国内定価 （15％）]]-商品マスタ[[#This Row],[仕入単価+国内送料]] | Y16: 0.08 | Z16: 13か月 | AA16: 常温 | AB16: 3週間 | AC16: 4985146000243 | AD16: ※受注生産品 メントール1.5倍増量、スッキリ感が強めのハッカ飴です。 | AF16: 〇 | AG16: 前金。振込後発送。販売の際は「定価厳守」契約書交わし済み。税抜仕入額6万以上で無料
A17: その他 | B17: 調味料 | C17: 北見ハッカ通商 | D17: ="PRD_SNJ_"& _xlfn.XLOOKUP(商品マスタ[[#This Row],[仕入先]],テーブル1[仕入先名],テーブル1[仕入先コード],"XXX",0,1)& "_"& 商品マスタ[[#This Row],[シリアル]]& "_"& TEXT(COUNTIFS(商品マスタ!$C$3:C17,商品マスタ[[#This Row],[仕入先]],商品マスタ!$E$3:E17,商品マスタ[[#This Row],[商品名]]), "00") | E17: Mentab（メンタブ） | F17: =IF(COUNTIFS($C$3:C17,商品マスタ[[#This Row],[仕入先]],$E$3:E17,商品マスタ[[#This Row],[商品名]]) = 1, 1,0) | G17: =TEXT(SUMIF($C$3:C17,商品マスタ[[#This Row],[仕入先]],$F$3:F17), "0000") | H17: 個 | I17: 9g（70粒) | J17: 144 | K17: 144個/箱 | L17: 175 | M17: 45950 | N17: 270 | O17: =IF(COUNT(商品マスタ[[#This Row],[参考上代 （税込)]]) > 0, (商品マスタ[[#This Row],[参考上代 （税込)]]-商品マスタ[[#This Row],[国内定価 （15％）]])/(商品マスタ[[#This Row],[参考上代 （税込)]]/1.08), "") | P17: 0.1 | Q17: =商品マスタ[[#This Row],[仕入 単価]]*商品マスタ[[#This Row],[標準国内送料率]] | S17: =IF(ISBLANK(商品マスタ[[#This Row],[実績 国内送料]]),商品マスタ[[#This Row],[標準国内送料]],) | T17: =商品マスタ[[#This Row],[仕入 単価]]+商品マスタ[[#This Row],[国内送料]] | U17: =ROUNDUP(商品マスタ[[#This Row],[仕入単価+国内送料]]/0.8,-1) | V17: =商品マスタ[[#This Row],[海外定価 （20％）]]-商品マスタ[[#This Row],[仕入単価+国内送料]] | W17: =ROUNDUP(商品マスタ[[#This Row],[仕入単価+国内送料]]/0.85,-1) | X17: =商品マスタ[[#This Row],[国内定価 （15％）]]-商品マスタ[[#This Row],[仕入単価+国内送料]] | Y17: 0.08 | Z17: 1年 | AA17: 常温 | AB17: 3週間 | AC17: 4985146000458 | AD17: ※受注生産品 「北海道産和種ハッカ」配合のタブレット菓子です。 | AF17: 〇 | AG17: 前金。振込後発送。販売の際は「定価厳守」契約書交わし済み。税抜仕入額6万以上で無料
A18: 菓子 | B18: 洋菓子 | C18: 北見ハッカ通商 | D18: ="PRD_SNJ_"& _xlfn.XLOOKUP(商品マスタ[[#This Row],[仕入先]],テーブル1[仕入先名],テーブル1[仕入先コード],"XXX",0,1)& "_"& 商品マスタ[[#This Row],[シリアル]]& "_"& TEXT(COUNTIFS(商品マスタ!$C$3:C18,商品マスタ[[#This Row],[仕入先]],商品マスタ!$E$3:E18,商品マスタ[[#This Row],[商品名]]), "00") | E18: Mentab（メンタブ）チョコミント味 | F18: =IF(COUNTIFS($C$3:C18,商品マスタ[[#This Row],[仕入先]],$E$3:E18,商品マスタ[[#This Row],[商品名]]) = 1, 1,0) | G18: =TEXT(SUMIF($C$3:C18,商品マスタ[[#This Row],[仕入先]],$F$3:F18), "0000") | H18: 個 | I18: 9g（70粒） | J18: 144 | K18: 144個/箱 | L18: 175 | M18: 45950 | N18: 270 | O18: =IF(COUNT(商品マスタ[[#This Row],[参考上代 （税込)]]) > 0, (商品マスタ[[#This Row],[参考上代 （税込)]]-商品マスタ[[#This Row],[国内定価 （15％）]])/(商品マスタ[[#This Row],[参考上代 （税込)]]/1.08), "") | P18: 0.1 | Q18: =商品マスタ[[#This Row],[仕入 単価]]*商品マスタ[[#This Row],[標準国内送料率]] | S18: =IF(ISBLANK(商品マスタ[[#This Row],[実績 国内送料]]),商品マスタ[[#This Row],[標準国内送料]],) | T18: =商品マスタ[[#This Row],[仕入 単価]]+商品マスタ[[#This Row],[国内送料]] | U18: =ROUNDUP(商品マスタ[[#This Row],[仕入単価+国内送料]]/0.8,-1) | V18: =商品マスタ[[#This Row],[海外定価 （20％）]]-商品マスタ[[#This Row],[仕入単価+国内送料]] | W18: =ROUNDUP(商品マスタ[[#This Row],[仕入単価+国内送料]]/0.85,-1) | X18: =商品マスタ[[#This Row],[国内定価 （15％）]]-商品マスタ[[#This Row],[仕入単価+国内送料]] | Y18: 0.08 | Z18: 1年 | AA18: 常温 | AB18: 3週間 | AC18: 4985146000830 | AD18: ※受注生産品 やさしいチョコの風味と爽やかなミントの清涼感が新しいタブレットです。 | AF18: 〇 | AG18: 前金。振込後発送。販売の際は「定価厳守」契約書交わし済み。税抜仕入額6万以上で無料
A19: 菓子 | B19: 洋菓子 | C19: CHISE GARDEN | D19: ="PRD_SNJ_"& _xlfn.XLOOKUP(商品マスタ[[#This Row],[仕入先]],テーブル1[仕入先名],テーブル1[仕入先コード],"XXX",0,1)& "_"& 商品マスタ[[#This Row],[シリアル]]& "_"& TEXT(COUNTIFS(商品マスタ!$C$3:C19,商品マスタ[[#This Row],[仕入先]],商品マスタ!$E$3:E19,商品マスタ[[#This Row],[商品名]]), "00") | E19: 野草番茶 | F19: =IF(COUNTIFS($C$3:C19,商品マスタ[[#This Row],[仕入先]],$E$3:E19,商品マスタ[[#This Row],[商品名]]) = 1, 1,0) | G19: =TEXT(SUMIF($C$3:C19,商品マスタ[[#This Row],[仕入先]],$F$3:F19), "0000") | H19: 袋 | I19: 50g | J19: 50 | L19: 560 | M19: 45951 | N19: 864 | O19: =IF(COUNT(商品マスタ[[#This Row],[参考上代 （税込)]]) > 0, (商品マスタ[[#This Row],[参考上代 （税込)]]-商品マスタ[[#This Row],[国内定価 （15％）]])/(商品マスタ[[#This Row],[参考上代 （税込)]]/1.08), "") | P19: 0.1 | Q19: =商品マスタ[[#This Row],[仕入 単価]]*商品マスタ[[#This Row],[標準国内送料率]] | R19: 1000 | S19: =IF(ISBLANK(商品マスタ[[#This Row],[実績 国内送料]]),商品マスタ[[#This Row],[標準国内送料]],) | T19: =商品マスタ[[#This Row],[仕入 単価]]+商品マスタ[[#This Row],[国内送料]] | U19: =ROUNDUP(商品マスタ[[#This Row],[仕入単価+国内送料]]/0.8,-1) | V19: =商品マスタ[[#This Row],[海外定価 （20％）]]-商品マスタ[[#This Row],[仕入単価+国内送料]] | W19: =ROUNDUP(商品マスタ[[#This Row],[仕入単価+国内送料]]/0.85,-1) | X19: =商品マスタ[[#This Row],[国内定価 （15％）]]-商品マスタ[[#This Row],[仕入単価+国内送料]] | Y19: 0.08 | Z19: 1年 | AA19: 常温 | AB19: 7日 | AC19: 4595430036010 | AD19: 地元の有名ホテルのウェルカムドリンクとしても人気の野草番茶。 材料のほとんどがニセコ町産で、ガーデンで採れたハーブもブレンドしています。 | AF19: 〇 | AG19: ロット50袋割れ送料実費、混載50袋可
A20: 菓子 | B20: 洋菓子 | C20: CHISE GARDEN | D20: ="PRD_SNJ_"& _xlfn.XLOOKUP(商品マスタ[[#This Row],[仕入先]],テーブル1[仕入先名],テーブル1[仕入先コード],"XXX",0,1)& "_"& 商品マスタ[[#This Row],[シリアル]]& "_"& TEXT(COUNTIFS(商品マスタ!$C$3:C20,商品マスタ[[#This Row],[仕入先]],商品マスタ!$E$3:E20,商品マスタ[[#This Row],[商品名]]), "00") | E20: ハーブティ | F20: =IF(COUNTIFS($C$3:C20,商品マスタ[[#This Row],[仕入先]],$E$3:E20,商品マスタ[[#This Row],[商品名]]) = 1, 1,0) | G20: =TEXT(SUMIF($C$3:C20,商品マスタ[[#This Row],[仕入先]],$F$3:F20), "0000") | H20: 袋 | I20: 20g | J20: 50 | L20: 560 | M20: 45951 | N20: 864 | O20: =IF(COUNT(商品マスタ[[#This Row],[参考上代 （税込)]]) > 0, (商品マスタ[[#This Row],[参考上代 （税込)]]-商品マスタ[[#This Row],[国内定価 （15％）]])/(商品マスタ[[#This Row],[参考上代 （税込)]]/1.08), "") | P20: 0.1 | Q20: =商品マスタ[[#This Row],[仕入 単価]]*商品マスタ[[#This Row],[標準国内送料率]] | R20: 1000 | S20: =IF(ISBLANK(商品マスタ[[#This Row],[実績 国内送料]]),商品マスタ[[#This Row],[標準国内送料]],) | T20: =商品マスタ[[#This Row],[仕入 単価]]+商品マスタ[[#This Row],[国内送料]] | U20: =ROUNDUP(商品マスタ[[#This Row],[仕入単価+国内送料]]/0.8,-1) | V20: =商品マスタ[[#This Row],[海外定価 （20％）]]-商品マスタ[[#This Row],[仕入単価+国内送料]] | W20: =ROUNDUP(商品マスタ[[#This Row],[仕入単価+国内送料]]/0.85,-1) | X20: =商品マスタ[[#This Row],[国内定価 （15％）]]-商品マスタ[[#This Row],[仕入単価+国内送料]] | Y20: 0.08 | Z20: 1年 | AA20: 常温 | AB20: 7日 | AC20: 4595430036034 | AD20: チセガーデンで育ったハーブを使ったハーブティーです。紫色のハーブティーですが、そのまま飲めば豊かな香りを楽しめます。レモン果汁を一滴入れるとピンク色に変わり、程よい酸味になります。 | AF20: 〇
A21: 菓子 | B21: 洋菓子 | C21: CHISE GARDEN | D21: ="PRD_SNJ_"& _xlfn.XLOOKUP(商品マスタ[[#This Row],[仕入先]],テーブル1[仕入先名],テーブル1[仕入先コード],"XXX",0,1)& "_"& 商品マスタ[[#This Row],[シリアル]]& "_"& TEXT(COUNTIFS(商品マスタ!$C$3:C21,商品マスタ[[#This Row],[仕入先]],商品マスタ!$E$3:E21,商品マスタ[[#This Row],[商品名]]), "00") | E21: 松葉仙人茶 | F21: =IF(COUNTIFS($C$3:C21,商品マスタ[[#This Row],[仕入先]],$E$3:E21,商品マスタ[[#This Row],[商品名]]) = 1, 1,0) | G21: =TEXT(SUMIF($C$3:C21,商品マスタ[[#This Row],[仕入先]],$F$3:F21), "0000") | H21: 袋 | I21: 8g×４/袋 | J21: 50 | L21: 700 | M21: 45951 | N21: 1080 | O21: =IF(COUNT(商品マスタ[[#This Row],[参考上代 （税込)]]) > 0, (商品マスタ[[#This Row],[参考上代 （税込)]]-商品マスタ[[#This Row],[国内定価 （15％）]])/(商品マスタ[[#This Row],[参考上代 （税込)]]/1.08), "") | P21: 0.1 | Q21: =商品マスタ[[#This Row],[仕入 単価]]*商品マスタ[[#This Row],[標準国内送料率]] | R21: 1000 | S21: =IF(ISBLANK(商品マスタ[[#This Row],[実績 国内送料]]),商品マスタ[[#This Row],[標準国内送料]],) | T21: =商品マスタ[[#This Row],[仕入 単価]]+商品マスタ[[#This Row],[国内送料]] | U21: =ROUNDUP(商品マスタ[[#This Row],[仕入単価+国内送料]]/0.8,-1) | V21: =商品マスタ[[#This Row],[海外定価 （20％）]]-商品マスタ[[#This Row],[仕入単価+国内送料]] | W21: =ROUNDUP(商品マスタ[[#This Row],[仕入単価+国内送料]]/0.85,-1) | X21: =商品マスタ[[#This Row],[国内定価 （15％）]]-商品マスタ[[#This Row],[仕入単価+国内送料]] | Y21: 0.08 | Z21: 1年 | AA21: 常温 | AB21: 7日 | AC21: 4595430036027 | AD21: 松葉仙人茶は、ニセコ産の高品質な松葉と高級なカバノアナタケを使用した贅沢な飲料です。この特別なブレンドには、またたび、松ぼっくり、桑の葉、そして三年番茶が含まれており、風味豊かな味わいを楽しむことができます。松葉仙人茶は健康的でリフレッシュすることができる飲み物です。贈り物や自分へのご褒美としても最適な一品です。 | AF21: 〇
A22: その他 | B22: 調味料 | C22: にんにく種蔵 | D22: ="PRD_SNJ_"& _xlfn.XLOOKUP(商品マスタ[[#This Row],[仕入先]],テーブル1[仕入先名],テーブル1[仕入先コード],"XXX",0,1)& "_"& 商品マスタ[[#This Row],[シリアル]]& "_"& TEXT(COUNTIFS(商品マスタ!$C$3:C22,商品マスタ[[#This Row],[仕入先]],商品マスタ!$E$3:E22,商品マスタ[[#This Row],[商品名]]), "00") | E22: ダイヤモンドにんにくマヨネーズ (瓶) | F22: =IF(COUNTIFS($C$3:C22,商品マスタ[[#This Row],[仕入先]],$E$3:E22,商品マスタ[[#This Row],[商品名]]) = 1, 1,0) | G22: =TEXT(SUMIF($C$3:C22,商品マスタ[[#This Row],[仕入先]],$F$3:F22), "0000") | H22: 瓶 | I22: 90g | J22: 30 | L22: =492/1.08 | M22: 45951 | N22: 850 | O22: =IF(COUNT(商品マスタ[[#This Row],[参考上代 （税込)]]) > 0, (商品マスタ[[#This Row],[参考上代 （税込)]]-商品マスタ[[#This Row],[国内定価 （15％）]])/(商品マスタ[[#This Row],[参考上代 （税込)]]/1.08), "") | P22: 0.1 | Q22: =商品マスタ[[#This Row],[仕入 単価]]*商品マスタ[[#This Row],[標準国内送料率]] | R22: 2050 | S22: =IF(ISBLANK(商品マスタ[[#This Row],[実績 国内送料]]),商品マスタ[[#This Row],[標準国内送料]],) | T22: =商品マスタ[[#This Row],[仕入 単価]]+商品マスタ[[#This Row],[国内送料]] | U22: =ROUNDUP(商品マスタ[[#This Row],[仕入単価+国内送料]]/0.8,-1) | V22: =商品マスタ[[#This Row],[海外定価 （20％）]]-商品マスタ[[#This Row],[仕入単価+国内送料]] | W22: =ROUNDUP(商品マスタ[[#This Row],[仕入単価+国内送料]]/0.85,-1) | X22: =商品マスタ[[#This Row],[国内定価 （15％）]]-商品マスタ[[#This Row],[仕入単価+国内送料]] | Y22: 0.08 | AC22: 4573252030331 | AD22: マツコの知らない世界で紹介。北海道美瑛町の自社農園でオリジナルブランド「北海道のダイヤモンドにんにく」を１００％使用したにんにくマヨネーズです。 | AF22: 〇
A23: その他 | B23: 調味料 | C23: にんにく種蔵 | D23: ="PRD_SNJ_"& _xlfn.XLOOKUP(商品マスタ[[#This Row],[仕入先]],テーブル1[仕入先名],テーブル1[仕入先コード],"XXX",0,1)& "_"& 商品マスタ[[#This Row],[シリアル]]& "_"& TEXT(COUNTIFS(商品マスタ!$C$3:C23,商品マスタ[[#This Row],[仕入先]],商品マスタ!$E$3:E23,商品マスタ[[#This Row],[商品名]]), "00") | E23: ダイヤモンドにんにくマヨネーズ (瓶) | F23: =IF(COUNTIFS($C$3:C23,商品マスタ[[#This Row],[仕入先]],$E$3:E23,商品マスタ[[#This Row],[商品名]]) = 1, 1,0) | G23: =TEXT(SUMIF($C$3:C23,商品マスタ[[#This Row],[仕入先]],$F$3:F23), "0000") | H23: 瓶 | I23: 90g | J23: 60 | L23: =492/1.08 | M23: 45951 | N23: 850 | O23: =IF(COUNT(商品マスタ[[#This Row],[参考上代 （税込)]]) > 0, (商品マスタ[[#This Row],[参考上代 （税込)]]-商品マスタ[[#This Row],[国内定価 （15％）]])/(商品マスタ[[#This Row],[参考上代 （税込)]]/1.08), "") | P23: 0.1 | Q23: =商品マスタ[[#This Row],[仕入 単価]]*商品マスタ[[#This Row],[標準国内送料率]] | R23: 2300 | S23: =IF(ISBLANK(商品マスタ[[#This Row],[実績 国内送料]]),商品マスタ[[#This Row],[標準国内送料]],) | T23: =商品マスタ[[#This Row],[仕入 単価]]+商品マスタ[[#This Row],[国内送料]] | U23: =ROUNDUP(商品マスタ[[#This Row],[仕入単価+国内送料]]/0.8,-1) | V23: =商品マスタ[[#This Row],[海外定価 （20％）]]-商品マスタ[[#This Row],[仕入単価+国内送料]] | W23: =ROUNDUP(商品マスタ[[#This Row],[仕入単価+国内送料]]/0.85,-1) | X23: =商品マスタ[[#This Row],[国内定価 （15％）]]-商品マスタ[[#This Row],[仕入単価+国内送料]] | Y23: 0.08 | AC23: 4573252030331 | AD23: マツコの知らない世界で紹介。北海道美瑛町の自社農園でオリジナルブランド「北海道のダイヤモンドにんにく」を１００％使用したにんにくマヨネーズです。 | AF23: 〇
A24: その他 | B24: 調味料 | C24: にんにく種蔵 | D24: ="PRD_SNJ_"& _xlfn.XLOOKUP(商品マスタ[[#This Row],[仕入先]],テーブル1[仕入先名],テーブル1[仕入先コード],"XXX",0,1)& "_"& 商品マスタ[[#This Row],[シリアル]]& "_"& TEXT(COUNTIFS(商品マスタ!$C$3:C24,商品マスタ[[#This Row],[仕入先]],商品マスタ!$E$3:E24,商品マスタ[[#This Row],[商品名]]), "00") | E24: ダイヤモンドにんにくマヨネーズ (パウチ) | F24: =IF(COUNTIFS($C$3:C24,商品マスタ[[#This Row],[仕入先]],$E$3:E24,商品マスタ[[#This Row],[商品名]]) = 1, 1,0) | G24: =TEXT(SUMIF($C$3:C24,商品マスタ[[#This Row],[仕入先]],$F$3:F24), "0000") | H24: パウチ | I24: 200g | J24: 50 | L24: 925 | M24: 45951 | N24: 1706 | O24: =IF(COUNT(商品マスタ[[#This Row],[参考上代 （税込)]]) > 0, (商品マスタ[[#This Row],[参考上代 （税込)]]-商品マスタ[[#This Row],[国内定価 （15％）]])/(商品マスタ[[#This Row],[参考上代 （税込)]]/1.08), "") | P24: 0.1 | Q24: =商品マスタ[[#This Row],[仕入 単価]]*商品マスタ[[#This Row],[標準国内送料率]] | S24: =IF(ISBLANK(商品マスタ[[#This Row],[実績 国内送料]]),商品マスタ[[#This Row],[標準国内送料]],) | T24: =商品マスタ[[#This Row],[仕入 単価]]+商品マスタ[[#This Row],[国内送料]] | U24: =ROUNDUP(商品マスタ[[#This Row],[仕入単価+国内送料]]/0.8,-1) | V24: =商品マスタ[[#This Row],[海外定価 （20％）]]-商品マスタ[[#This Row],[仕入単価+国内送料]] | W24: =ROUNDUP(商品マスタ[[#This Row],[仕入単価+国内送料]]/0.85,-1) | X24: =商品マスタ[[#This Row],[国内定価 （15％）]]-商品マスタ[[#This Row],[仕入単価+国内送料]] | Y24: 0.08 | AD24: マツコの知らない世界で紹介。北海道美瑛町の自社農園でオリジナルブランド「北海道のダイヤモンドにんにく」を１００％使用したにんにくマヨネーズのお徳用 パウチタイプです。 | AF24: 〇
A25: その他 | B25: 調味料 | C25: にんにく種蔵 | D25: ="PRD_SNJ_"& _xlfn.XLOOKUP(商品マスタ[[#This Row],[仕入先]],テーブル1[仕入先名],テーブル1[仕入先コード],"XXX",0,1)& "_"& 商品マスタ[[#This Row],[シリアル]]& "_"& TEXT(COUNTIFS(商品マスタ!$C$3:C25,商品マスタ[[#This Row],[仕入先]],商品マスタ!$E$3:E25,商品マスタ[[#This Row],[商品名]]), "00") | E25: ダイヤモンドにんにくマヨネーズ (パウチ) | F25: =IF(COUNTIFS($C$3:C25,商品マスタ[[#This Row],[仕入先]],$E$3:E25,商品マスタ[[#This Row],[商品名]]) = 1, 1,0) | G25: =TEXT(SUMIF($C$3:C25,商品マスタ[[#This Row],[仕入先]],$F$3:F25), "0000") | H25: パウチ | I25: 200g | J25: 100 | L25: 925 | M25: 45951 | N25: 1706 | O25: =IF(COUNT(商品マスタ[[#This Row],[参考上代 （税込)]]) > 0, (商品マスタ[[#This Row],[参考上代 （税込)]]-商品マスタ[[#This Row],[国内定価 （15％）]])/(商品マスタ[[#This Row],[参考上代 （税込)]]/1.08), "") | P25: 0.1 | Q25: =商品マスタ[[#This Row],[仕入 単価]]*商品マスタ[[#This Row],[標準国内送料率]] | S25: =IF(ISBLANK(商品マスタ[[#This Row],[実績 国内送料]]),商品マスタ[[#This Row],[標準国内送料]],) | T25: =商品マスタ[[#This Row],[仕入 単価]]+商品マスタ[[#This Row],[国内送料]] | U25: =ROUNDUP(商品マスタ[[#This Row],[仕入単価+国内送料]]/0.8,-1) | V25: =商品マスタ[[#This Row],[海外定価 （20％）]]-商品マスタ[[#This Row],[仕入単価+国内送料]] | W25: =ROUNDUP(商品マスタ[[#This Row],[仕入単価+国内送料]]/0.85,-1) | X25: =商品マスタ[[#This Row],[国内定価 （15％）]]-商品マスタ[[#This Row],[仕入単価+国内送料]] | Y25: 0.08 | AD25: マツコの知らない世界で紹介。北海道美瑛町の自社農園でオリジナルブランド「北海道のダイヤモンドにんにく」を１００％使用したにんにくマヨネーズのお徳用 パウチタイプです。 | AF25: 〇
A26: その他 | B26: 調味料 | C26: にんにく種蔵 | D26: ="PRD_SNJ_"& _xlfn.XLOOKUP(商品マスタ[[#This Row],[仕入先]],テーブル1[仕入先名],テーブル1[仕入先コード],"XXX",0,1)& "_"& 商品マスタ[[#This Row],[シリアル]]& "_"& TEXT(COUNTIFS(商品マスタ!$C$3:C26,商品マスタ[[#This Row],[仕入先]],商品マスタ!$E$3:E26,商品マスタ[[#This Row],[商品名]]), "00") | E26: 【数量限定】ダイヤモンドにんにくオリーブオイル | F26: =IF(COUNTIFS($C$3:C26,商品マスタ[[#This Row],[仕入先]],$E$3:E26,商品マスタ[[#This Row],[商品名]]) = 1, 1,0) | G26: =TEXT(SUMIF($C$3:C26,商品マスタ[[#This Row],[仕入先]],$F$3:F26), "0000") | H26: 瓶 | I26: ml | J26: 48 | K26: 1c/s48本 | L26: 1714 | M26: 45951 | N26: 2678 | O26: =IF(COUNT(商品マスタ[[#This Row],[参考上代 （税込)]]) > 0, (商品マスタ[[#This Row],[参考上代 （税込)]]-商品マスタ[[#This Row],[国内定価 （15％）]])/(商品マスタ[[#This Row],[参考上代 （税込)]]/1.08), "") | P26: 0.1 | Q26: =商品マスタ[[#This Row],[仕入 単価]]*商品マスタ[[#This Row],[標準国内送料率]] | S26: =IF(ISBLANK(商品マスタ[[#This Row],[実績 国内送料]]),商品マスタ[[#This Row],[標準国内送料]],) | T26: =商品マスタ[[#This Row],[仕入 単価]]+商品マスタ[[#This Row],[国内送料]] | U26: =ROUNDUP(商品マスタ[[#This Row],[仕入単価+国内送料]]/0.8,-1) | V26: =商品マスタ[[#This Row],[海外定価 （20％）]]-商品マスタ[[#This Row],[仕入単価+国内送料]] | W26: =ROUNDUP(商品マスタ[[#This Row],[仕入単価+国内送料]]/0.85,-1) | X26: =商品マスタ[[#This Row],[国内定価 （15％）]]-商品マスタ[[#This Row],[仕入単価+国内送料]] | Y26: 0.08 | AC26: 4595318851063 | AD26: 美瑛の自社農園で丁寧に作られた、農薬・化学肥料不使用のダイヤモンドにんにくをオリーブオイルにしました。オリーブオイルは本場イタリア産を使用。えぐみがなく香り高い特徴がこのオリーブオイルとよく馴染んでいます。 | AF26: ✕ | AG26: 要在庫確認。数量限定。発送元が異なるため 別途送料必要
A27: その他 | B27: 調味料 | C27: にんにく種蔵 | D27: ="PRD_SNJ_"& _xlfn.XLOOKUP(商品マスタ[[#This Row],[仕入先]],テーブル1[仕入先名],テーブル1[仕入先コード],"XXX",0,1)& "_"& 商品マスタ[[#This Row],[シリアル]]& "_"& TEXT(COUNTIFS(商品マスタ!$C$3:C27,商品マスタ[[#This Row],[仕入先]],商品マスタ!$E$3:E27,商品マスタ[[#This Row],[商品名]]), "00") | E27: ダイヤモンドにんにく味噌 | F27: =IF(COUNTIFS($C$3:C27,商品マスタ[[#This Row],[仕入先]],$E$3:E27,商品マスタ[[#This Row],[商品名]]) = 1, 1,0) | G27: =TEXT(SUMIF($C$3:C27,商品マスタ[[#This Row],[仕入先]],$F$3:F27), "0000") | H27: 瓶 | I27: 110g | J27: 60 | L27: 456 | M27: 45951 | N27: 850 | O27: =IF(COUNT(商品マスタ[[#This Row],[参考上代 （税込)]]) > 0, (商品マスタ[[#This Row],[参考上代 （税込)]]-商品マスタ[[#This Row],[国内定価 （15％）]])/(商品マスタ[[#This Row],[参考上代 （税込)]]/1.08), "") | P27: 0.1 | Q27: =商品マスタ[[#This Row],[仕入 単価]]*商品マスタ[[#This Row],[標準国内送料率]] | S27: =IF(ISBLANK(商品マスタ[[#This Row],[実績 国内送料]]),商品マスタ[[#This Row],[標準国内送料]],) | T27: =商品マスタ[[#This Row],[仕入 単価]]+商品マスタ[[#This Row],[国内送料]] | U27: =ROUNDUP(商品マスタ[[#This Row],[仕入単価+国内送料]]/0.8,-1) | V27: =商品マスタ[[#This Row],[海外定価 （20％）]]-商品マスタ[[#This Row],[仕入単価+国内送料]] | W27: =ROUNDUP(商品マスタ[[#This Row],[仕入単価+国内送料]]/0.85,-1) | X27: =商品マスタ[[#This Row],[国内定価 （15％）]]-商品マスタ[[#This Row],[仕入単価+国内送料]] | Y27: 0.08 | AD27: 美瑛にある自社農園で農薬・化学肥料不使用で愛情込めて作られたダイヤモンドにんにくを味噌にしました。 | AF27: 〇
A28: その他 | B28: 調味料 | C28: にんにく種蔵 | D28: ="PRD_SNJ_"& _xlfn.XLOOKUP(商品マスタ[[#This Row],[仕入先]],テーブル1[仕入先名],テーブル1[仕入先コード],"XXX",0,1)& "_"& 商品マスタ[[#This Row],[シリアル]]& "_"& TEXT(COUNTIFS(商品マスタ!$C$3:C28,商品マスタ[[#This Row],[仕入先]],商品マスタ!$E$3:E28,商品マスタ[[#This Row],[商品名]]), "00") | E28: ダイヤモンドにんにくバーニャカウダ | F28: =IF(COUNTIFS($C$3:C28,商品マスタ[[#This Row],[仕入先]],$E$3:E28,商品マスタ[[#This Row],[商品名]]) = 1, 1,0) | G28: =TEXT(SUMIF($C$3:C28,商品マスタ[[#This Row],[仕入先]],$F$3:F28), "0000") | H28: 瓶 | I28: 90g | J28: 60 | L28: 456 | M28: 45951 | N28: 850 | O28: =IF(COUNT(商品マスタ[[#This Row],[参考上代 （税込)]]) > 0, (商品マスタ[[#This Row],[参考上代 （税込)]]-商品マスタ[[#This Row],[国内定価 （15％）]])/(商品マスタ[[#This Row],[参考上代 （税込)]]/1.08), "") | P28: 0.1 | Q28: =商品マスタ[[#This Row],[仕入 単価]]*商品マスタ[[#This Row],[標準国内送料率]] | S28: =IF(ISBLANK(商品マスタ[[#This Row],[実績 国内送料]]),商品マスタ[[#This Row],[標準国内送料]],) | T28: =商品マスタ[[#This Row],[仕入 単価]]+商品マスタ[[#This Row],[国内送料]] | U28: =ROUNDUP(商品マスタ[[#This Row],[仕入単価+国内送料]]/0.8,-1) | V28: =商品マスタ[[#This Row],[海外定価 （20％）]]-商品マスタ[[#This Row],[仕入単価+国内送料]] | W28: =ROUNDUP(商品マスタ[[#This Row],[仕入単価+国内送料]]/0.85,-1) | X28: =商品マスタ[[#This Row],[国内定価 （15％）]]-商品マスタ[[#This Row],[仕入単価+国内送料]] | Y28: 0.08 | AD28: アンチョビが効いていて隠し味のココナッツミルクが程よいマイルド感を出してくれます。 ダイヤモンドにんにくの旨みもたっぷり入っています。 | AF28: 〇
A29: その他 | B29: 調味料 | C29: にんにく種蔵 | D29: ="PRD_SNJ_"& _xlfn.XLOOKUP(商品マスタ[[#This Row],[仕入先]],テーブル1[仕入先名],テーブル1[仕入先コード],"XXX",0,1)& "_"& 商品マスタ[[#This Row],[シリアル]]& "_"& TEXT(COUNTIFS(商品マスタ!$C$3:C29,商品マスタ[[#This Row],[仕入先]],商品マスタ!$E$3:E29,商品マスタ[[#This Row],[商品名]]), "00") | E29: 絶望のにんにくトマトソース200g | F29: =IF(COUNTIFS($C$3:C29,商品マスタ[[#This Row],[仕入先]],$E$3:E29,商品マスタ[[#This Row],[商品名]]) = 1, 1,0) | G29: =TEXT(SUMIF($C$3:C29,商品マスタ[[#This Row],[仕入先]],$F$3:F29), "0000") | H29: パウチ | I29: 200g | J29: 100 | K29: 1c/s50個 | L29: 456 | M29: 45951 | N29: 853 | O29: =IF(COUNT(商品マスタ[[#This Row],[参考上代 （税込)]]) > 0, (商品マスタ[[#This Row],[参考上代 （税込)]]-商品マスタ[[#This Row],[国内定価 （15％）]])/(商品マスタ[[#This Row],[参考上代 （税込)]]/1.08), "") | P29: 0.1 | Q29: =商品マスタ[[#This Row],[仕入 単価]]*商品マスタ[[#This Row],[標準国内送料率]] | S29: =IF(ISBLANK(商品マスタ[[#This Row],[実績 国内送料]]),商品マスタ[[#This Row],[標準国内送料]],) | T29: =商品マスタ[[#This Row],[仕入 単価]]+商品マスタ[[#This Row],[国内送料]] | U29: =ROUNDUP(商品マスタ[[#This Row],[仕入単価+国内送料]]/0.8,-1) | V29: =商品マスタ[[#This Row],[海外定価 （20％）]]-商品マスタ[[#This Row],[仕入単価+国内送料]] | W29: =ROUNDUP(商品マスタ[[#This Row],[仕入単価+国内送料]]/0.85,-1) | X29: =商品マスタ[[#This Row],[国内定価 （15％）]]-商品マスタ[[#This Row],[仕入単価+国内送料]] | Y29: 0.08 | AD29: 濃厚なトマトソースに程よいピリ辛＆ガツンと効いたにんにくが最高！茹でたパスタに混ぜるだけで本格トマトパスタが味わえます。 | AF29: 〇
A30: その他 | B30: 調味料 | C30: にんにく種蔵 | D30: ="PRD_SNJ_"& _xlfn.XLOOKUP(商品マスタ[[#This Row],[仕入先]],テーブル1[仕入先名],テーブル1[仕入先コード],"XXX",0,1)& "_"& 商品マスタ[[#This Row],[シリアル]]& "_"& TEXT(COUNTIFS(商品マスタ!$C$3:C30,商品マスタ[[#This Row],[仕入先]],商品マスタ!$E$3:E30,商品マスタ[[#This Row],[商品名]]), "00") | E30: 待望のにんにくペペロンチーノソース200g | F30: =IF(COUNTIFS($C$3:C30,商品マスタ[[#This Row],[仕入先]],$E$3:E30,商品マスタ[[#This Row],[商品名]]) = 1, 1,0) | G30: =TEXT(SUMIF($C$3:C30,商品マスタ[[#This Row],[仕入先]],$F$3:F30), "0000") | H30: パウチ | I30: 200g | J30: 100 | K30: 1c/s50個 | L30: 456 | M30: 45951 | N30: 853 | O30: =IF(COUNT(商品マスタ[[#This Row],[参考上代 （税込)]]) > 0, (商品マスタ[[#This Row],[参考上代 （税込)]]-商品マスタ[[#This Row],[国内定価 （15％）]])/(商品マスタ[[#This Row],[参考上代 （税込)]]/1.08), "") | P30: 0.1 | Q30: =商品マスタ[[#This Row],[仕入 単価]]*商品マスタ[[#This Row],[標準国内送料率]] | S30: =IF(ISBLANK(商品マスタ[[#This Row],[実績 国内送料]]),商品マスタ[[#This Row],[標準国内送料]],) | T30: =商品マスタ[[#This Row],[仕入 単価]]+商品マスタ[[#This Row],[国内送料]] | U30: =ROUNDUP(商品マスタ[[#This Row],[仕入単価+国内送料]]/0.8,-1) | V30: =商品マスタ[[#This Row],[海外定価 （20％）]]-商品マスタ[[#This Row],[仕入単価+国内送料]] | W30: =ROUNDUP(商品マスタ[[#This Row],[仕入単価+国内送料]]/0.85,-1) | X30: =商品マスタ[[#This Row],[国内定価 （15％）]]-商品マスタ[[#This Row],[仕入単価+国内送料]] | Y30: 0.08 | AD30: にんにく満足宣言！！これこそ探し求めていた混ぜるだけで激うまペペロンチーノ！パスタに絡まるガツンとにんにく&ブラックペッパーなどのスパイスが絶妙なバランス。チャーハンの仕上げにもおすすめです！ | AF30: 〇
A31: その他 | B31: 調味料 | C31: 白亜ダイシン | D31: ="PRD_SNJ_"& _xlfn.XLOOKUP(商品マスタ[[#This Row],[仕入先]],テーブル1[仕入先名],テーブル1[仕入先コード],"XXX",0,1)& "_"& 商品マスタ[[#This Row],[シリアル]]& "_"& TEXT(COUNTIFS(商品マスタ!$C$3:C31,商品マスタ[[#This Row],[仕入先]],商品マスタ!$E$3:E31,商品マスタ[[#This Row],[商品名]]), "00") | E31: 北海道アールグレイミルクジャム | F31: =IF(COUNTIFS($C$3:C31,商品マスタ[[#This Row],[仕入先]],$E$3:E31,商品マスタ[[#This Row],[商品名]]) = 1, 1,0) | G31: =TEXT(SUMIF($C$3:C31,商品マスタ[[#This Row],[仕入先]],$F$3:F31), "0000") | H31: 瓶 | I31: 140ｇ | J31: 12 | L31: 450 | M31: 45952 | N31: 750 | O31: =IF(COUNT(商品マスタ[[#This Row],[参考上代 （税込)]]) > 0, (商品マスタ[[#This Row],[参考上代 （税込)]]-商品マスタ[[#This Row],[国内定価 （15％）]])/(商品マスタ[[#This Row],[参考上代 （税込)]]/1.08), "") | P31: 0.1 | Q31: =商品マスタ[[#This Row],[仕入 単価]]*商品マスタ[[#This Row],[標準国内送料率]] | R31: 1280 | S31: =IF(ISBLANK(商品マスタ[[#This Row],[実績 国内送料]]),商品マスタ[[#This Row],[標準国内送料]],) | T31: =商品マスタ[[#This Row],[仕入 単価]]+商品マスタ[[#This Row],[国内送料]] | U31: =ROUNDUP(商品マスタ[[#This Row],[仕入単価+国内送料]]/0.8,-1) | V31: =商品マスタ[[#This Row],[海外定価 （20％）]]-商品マスタ[[#This Row],[仕入単価+国内送料]] | W31: =ROUNDUP(商品マスタ[[#This Row],[仕入単価+国内送料]]/0.85,-1) | X31: =商品マスタ[[#This Row],[国内定価 （15％）]]-商品マスタ[[#This Row],[仕入単価+国内送料]] | Y31: 0.08 | Z31: 8日 | AA31: 常温 | AC31: 4562182193957 | AD31: 北海道産の新鮮なミルクをたっぷりと使用し、なめらかで濃厚な口当たりに仕上げたミルクジャムに、香り高いアールグレイの茶葉を贅沢に加えました。アールグレイ特有の柑橘系の華やかな香りがミルクのコクと絶妙に調和し、紅茶の風味が引き立つ上品な味わいが楽しめます。ミルクの優しい甘さと、アールグレイの爽やかで芳醇な香りが織りなすハーモニーは、一口食べるたびにティータイムのような心地よさを感じさせてくれます。 | AF31: 〇
A32: その他 | B32: 調味料 | C32: 白亜ダイシン | D32: ="PRD_SNJ_"& _xlfn.XLOOKUP(商品マスタ[[#This Row],[仕入先]],テーブル1[仕入先名],テーブル1[仕入先コード],"XXX",0,1)& "_"& 商品マスタ[[#This Row],[シリアル]]& "_"& TEXT(COUNTIFS(商品マスタ!$C$3:C32,商品マスタ[[#This Row],[仕入先]],商品マスタ!$E$3:E32,商品マスタ[[#This Row],[商品名]]), "00") | E32: 北海道ほうじ茶ミルクジャム | F32: =IF(COUNTIFS($C$3:C32,商品マスタ[[#This Row],[仕入先]],$E$3:E32,商品マスタ[[#This Row],[商品名]]) = 1, 1,0) | G32: =TEXT(SUMIF($C$3:C32,商品マスタ[[#This Row],[仕入先]],$F$3:F32), "0000") | H32: 袋 | I32: 140ｇ | J32: 12 | L32: 450 | M32: 45952 | N32: 750 | O32: =IF(COUNT(商品マスタ[[#This Row],[参考上代 （税込)]]) > 0, (商品マスタ[[#This Row],[参考上代 （税込)]]-商品マスタ[[#This Row],[国内定価 （15％）]])/(商品マスタ[[#This Row],[参考上代 （税込)]]/1.08), "") | P32: 0.1 | Q32: =商品マスタ[[#This Row],[仕入 単価]]*商品マスタ[[#This Row],[標準国内送料率]] | R32: 1280 | S32: =IF(ISBLANK(商品マスタ[[#This Row],[実績 国内送料]]),商品マスタ[[#This Row],[標準国内送料]],) | T32: =商品マスタ[[#This Row],[仕入 単価]]+商品マスタ[[#This Row],[国内送料]] | U32: =ROUNDUP(商品マスタ[[#This Row],[仕入単価+国内送料]]/0.8,-1) | V32: =商品マスタ[[#This Row],[海外定価 （20％）]]-商品マスタ[[#This Row],[仕入単価+国内送料]] | W32: =ROUNDUP(商品マスタ[[#This Row],[仕入単価+国内送料]]/0.85,-1) | X32: =商品マスタ[[#This Row],[国内定価 （15％）]]-商品マスタ[[#This Row],[仕入単価+国内送料]] | Y32: 0.08 | Z32: 8日 | AA32: 常温 | AC32: 4562182193940 | AD32: 北海道産の新鮮なミルクをたっぷりと贅沢に使用し、濃厚でなめらかな味わいに仕上げたミルクジャムに、国産のほうじ茶の茶葉を細かく挽いた細粒を加えました。ほうじ茶特有の香ばしく、深みのある風味がミルクのコクと見事に調和し、口に入れた瞬間にふわっと広がる豊かな香りが楽しめます。香ばしいほうじ茶の香りと、優しい甘さのミルクジャムが織りなす絶妙なハーモニーは、まるで和のティータイムを味わっているかのような上品な味わいを演出します。 | AF32: 〇
A33: 菓子 | B33: 和菓子 | C33: 白亜ダイシン | D33: ="PRD_SNJ_"& _xlfn.XLOOKUP(商品マスタ[[#This Row],[仕入先]],テーブル1[仕入先名],テーブル1[仕入先コード],"XXX",0,1)& "_"& 商品マスタ[[#This Row],[シリアル]]& "_"& TEXT(COUNTIFS(商品マスタ!$C$3:C33,商品マスタ[[#This Row],[仕入先]],商品マスタ!$E$3:E33,商品マスタ[[#This Row],[商品名]]), "00") | E33: ミルクキャンディ | F33: =IF(COUNTIFS($C$3:C33,商品マスタ[[#This Row],[仕入先]],$E$3:E33,商品マスタ[[#This Row],[商品名]]) = 1, 1,0) | G33: =TEXT(SUMIF($C$3:C33,商品マスタ[[#This Row],[仕入先]],$F$3:F33), "0000") | H33: 袋 | I33: 60ｇ | J33: 40 | L33: 228 | M33: 45952 | N33: 380 | O33: =IF(COUNT(商品マスタ[[#This Row],[参考上代 （税込)]]) > 0, (商品マスタ[[#This Row],[参考上代 （税込)]]-商品マスタ[[#This Row],[国内定価 （15％）]])/(商品マスタ[[#This Row],[参考上代 （税込)]]/1.08), "") | P33: 0.1 | Q33: =商品マスタ[[#This Row],[仕入 単価]]*商品マスタ[[#This Row],[標準国内送料率]] | R33: 1280 | S33: =IF(ISBLANK(商品マスタ[[#This Row],[実績 国内送料]]),商品マスタ[[#This Row],[標準国内送料]],) | T33: =商品マスタ[[#This Row],[仕入 単価]]+商品マスタ[[#This Row],[国内送料]] | U33: =ROUNDUP(商品マスタ[[#This Row],[仕入単価+国内送料]]/0.8,-1) | V33: =商品マスタ[[#This Row],[海外定価 （20％）]]-商品マスタ[[#This Row],[仕入単価+国内送料]] | W33: =ROUNDUP(商品マスタ[[#This Row],[仕入単価+国内送料]]/0.85,-1) | X33: =商品マスタ[[#This Row],[国内定価 （15％）]]-商品マスタ[[#This Row],[仕入単価+国内送料]] | Y33: 0.08 | Z33: 8日 | AA33: 常温 | AC33: 4562182194787 | AD33: 濃厚なミルクをたっぷりと使用し、なめらかでコクのある味わいに仕上げました。口に入れた瞬間に広がるやさしい甘さと、じんわりと溶けていくミルクの風味が、まるでおとぎ話の世界に迷い込んだかのような心温まるひとときを演出します。 | AF33: 〇
A34: 菓子 | B34: 和菓子 | C34: 白亜ダイシン | D34: ="PRD_SNJ_"& _xlfn.XLOOKUP(商品マスタ[[#This Row],[仕入先]],テーブル1[仕入先名],テーブル1[仕入先コード],"XXX",0,1)& "_"& 商品マスタ[[#This Row],[シリアル]]& "_"& TEXT(COUNTIFS(商品マスタ!$C$3:C34,商品マスタ[[#This Row],[仕入先]],商品マスタ!$E$3:E34,商品マスタ[[#This Row],[商品名]]), "00") | E34: ミントキャンディ | F34: =IF(COUNTIFS($C$3:C34,商品マスタ[[#This Row],[仕入先]],$E$3:E34,商品マスタ[[#This Row],[商品名]]) = 1, 1,0) | G34: =TEXT(SUMIF($C$3:C34,商品マスタ[[#This Row],[仕入先]],$F$3:F34), "0000") | H34: 袋 | I34: 60ｇ | J34: 40 | L34: 228 | M34: 45952 | N34: 380 | O34: =IF(COUNT(商品マスタ[[#This Row],[参考上代 （税込)]]) > 0, (商品マスタ[[#This Row],[参考上代 （税込)]]-商品マスタ[[#This Row],[国内定価 （15％）]])/(商品マスタ[[#This Row],[参考上代 （税込)]]/1.08), "") | P34: 0.1 | Q34: =商品マスタ[[#This Row],[仕入 単価]]*商品マスタ[[#This Row],[標準国内送料率]] | R34: 1280 | S34: =IF(ISBLANK(商品マスタ[[#This Row],[実績 国内送料]]),商品マスタ[[#This Row],[標準国内送料]],) | T34: =商品マスタ[[#This Row],[仕入 単価]]+商品マスタ[[#This Row],[国内送料]] | U34: =ROUNDUP(商品マスタ[[#This Row],[仕入単価+国内送料]]/0.8,-1) | V34: =商品マスタ[[#This Row],[海外定価 （20％）]]-商品マスタ[[#This Row],[仕入単価+国内送料]] | W34: =ROUNDUP(商品マスタ[[#This Row],[仕入単価+国内送料]]/0.85,-1) | X34: =商品マスタ[[#This Row],[国内定価 （15％）]]-商品マスタ[[#This Row],[仕入単価+国内送料]] | Y34: 0.08 | Z34: 8日 | AA34: 常温 | AC34: 4562182194794 | AD34: ひと口食べれば、すっきりとした清涼感が広がり、爽やかな風が吹き抜けるような心地よさを感じられます。口の中に広がるクールな味わいは、気分をリフレッシュしたいときや、ちょっとした息抜きの時間にもぴったり。厳選したミントの風味を活かし、ほどよい甘さと爽快感のバランスを絶妙に仕上げました。 | AF34: 〇
A35: その他 | B35: 備長炭 | C35: 白亜ダイシン | D35: ="PRD_SNJ_"& _xlfn.XLOOKUP(商品マスタ[[#This Row],[仕入先]],テーブル1[仕入先名],テーブル1[仕入先コード],"XXX",0,1)& "_"& 商品マスタ[[#This Row],[シリアル]]& "_"& TEXT(COUNTIFS(商品マスタ!$C$3:C35,商品マスタ[[#This Row],[仕入先]],商品マスタ!$E$3:E35,商品マスタ[[#This Row],[商品名]]), "00") | E35: ミックスベリーソーダ | F35: =IF(COUNTIFS($C$3:C35,商品マスタ[[#This Row],[仕入先]],$E$3:E35,商品マスタ[[#This Row],[商品名]]) = 1, 1,0) | G35: =TEXT(SUMIF($C$3:C35,商品マスタ[[#This Row],[仕入先]],$F$3:F35), "0000") | H35: 瓶 | I35: 200ml | J35: 24 | L35: 228 | M35: 45952 | N35: 380 | O35: =IF(COUNT(商品マスタ[[#This Row],[参考上代 （税込)]]) > 0, (商品マスタ[[#This Row],[参考上代 （税込)]]-商品マスタ[[#This Row],[国内定価 （15％）]])/(商品マスタ[[#This Row],[参考上代 （税込)]]/1.08), "") | P35: 0.1 | Q35: =商品マスタ[[#This Row],[仕入 単価]]*商品マスタ[[#This Row],[標準国内送料率]] | R35: 1280 | S35: =IF(ISBLANK(商品マスタ[[#This Row],[実績 国内送料]]),商品マスタ[[#This Row],[標準国内送料]],) | T35: =商品マスタ[[#This Row],[仕入 単価]]+商品マスタ[[#This Row],[国内送料]] | U35: =ROUNDUP(商品マスタ[[#This Row],[仕入単価+国内送料]]/0.8,-1) | V35: =商品マスタ[[#This Row],[海外定価 （20％）]]-商品マスタ[[#This Row],[仕入単価+国内送料]] | W35: =ROUNDUP(商品マスタ[[#This Row],[仕入単価+国内送料]]/0.85,-1) | X35: =商品マスタ[[#This Row],[国内定価 （15％）]]-商品マスタ[[#This Row],[仕入単価+国内送料]] | Y35: 0.08 | Z35: 8日 | AA35: 常温 | AC35: 4562182191731 | AD35: 北海道産のハスカップとはちみつをベースに、ラズベリーとカシスをバランスよくブレンドした、フルーティーな炭酸ドリンクです。ハスカップのほどよい酸味に、ラズベリーの華やかな香りとカシスの深みのあるコクが加わり、爽やかで飲みやすい味わいに仕上げました。炭酸の心地よい刺激が、口の中でふわっと広がるベリーの香りを引き立て、ほんのり甘くすっきりとした後味が楽しめます。 | AF35: 〇
A36: 菓子 | B36: 洋菓子 | C36: 白亜ダイシン | D36: ="PRD_SNJ_"& _xlfn.XLOOKUP(商品マスタ[[#This Row],[仕入先]],テーブル1[仕入先名],テーブル1[仕入先コード],"XXX",0,1)& "_"& 商品マスタ[[#This Row],[シリアル]]& "_"& TEXT(COUNTIFS(商品マスタ!$C$3:C36,商品マスタ[[#This Row],[仕入先]],商品マスタ!$E$3:E36,商品マスタ[[#This Row],[商品名]]), "00") | E36: 北海道バジルソース | F36: =IF(COUNTIFS($C$3:C36,商品マスタ[[#This Row],[仕入先]],$E$3:E36,商品マスタ[[#This Row],[商品名]]) = 1, 1,0) | G36: =TEXT(SUMIF($C$3:C36,商品マスタ[[#This Row],[仕入先]],$F$3:F36), "0000") | H36: 瓶 | I36: 110ｇ | J36: 12 | L36: 504 | M36: 45952 | N36: 840 | O36: =IF(COUNT(商品マスタ[[#This Row],[参考上代 （税込)]]) > 0, (商品マスタ[[#This Row],[参考上代 （税込)]]-商品マスタ[[#This Row],[国内定価 （15％）]])/(商品マスタ[[#This Row],[参考上代 （税込)]]/1.08), "") | P36: 0.1 | Q36: =商品マスタ[[#This Row],[仕入 単価]]*商品マスタ[[#This Row],[標準国内送料率]] | R36: 1280 | S36: =IF(ISBLANK(商品マスタ[[#This Row],[実績 国内送料]]),商品マスタ[[#This Row],[標準国内送料]],) | T36: =商品マスタ[[#This Row],[仕入 単価]]+商品マスタ[[#This Row],[国内送料]] | U36: =ROUNDUP(商品マスタ[[#This Row],[仕入単価+国内送料]]/0.8,-1) | V36: =商品マスタ[[#This Row],[海外定価 （20％）]]-商品マスタ[[#This Row],[仕入単価+国内送料]] | W36: =ROUNDUP(商品マスタ[[#This Row],[仕入単価+国内送料]]/0.85,-1) | X36: =商品マスタ[[#This Row],[国内定価 （15％）]]-商品マスタ[[#This Row],[仕入単価+国内送料]] | Y36: 0.08 | Z36: 8日 | AA36: 常温 | AC36: 4562182191687 | AD36: 北海道産のバジルだけを贅沢に使用した、シンプルでありながら王道のバジルソースが誕生しました。収穫したばかりの新鮮なバジルをたっぷりと使い、素材本来の風味を存分に引き出しています。そこにカシューナッツと粉チーズを加え、クセがなく、まろやかでコクのある味わいに仕上げました。 | AF36: 〇
A37: 青果 | B37: 野菜 | C37: 白亜ダイシン | D37: ="PRD_SNJ_"& _xlfn.XLOOKUP(商品マスタ[[#This Row],[仕入先]],テーブル1[仕入先名],テーブル1[仕入先コード],"XXX",0,1)& "_"& 商品マスタ[[#This Row],[シリアル]]& "_"& TEXT(COUNTIFS(商品マスタ!$C$3:C37,商品マスタ[[#This Row],[仕入先]],商品マスタ!$E$3:E37,商品マスタ[[#This Row],[商品名]]), "00") | E37: 北海道焼肉ソース | F37: =IF(COUNTIFS($C$3:C37,商品マスタ[[#This Row],[仕入先]],$E$3:E37,商品マスタ[[#This Row],[商品名]]) = 1, 1,0) | G37: =TEXT(SUMIF($C$3:C37,商品マスタ[[#This Row],[仕入先]],$F$3:F37), "0000") | H37: 瓶 | I37: 200ｇ | J37: 12 | L37: 414 | M37: 45952 | N37: 690 | O37: =IF(COUNT(商品マスタ[[#This Row],[参考上代 （税込)]]) > 0, (商品マスタ[[#This Row],[参考上代 （税込)]]-商品マスタ[[#This Row],[国内定価 （15％）]])/(商品マスタ[[#This Row],[参考上代 （税込)]]/1.08), "") | P37: 0.1 | Q37: =商品マスタ[[#This Row],[仕入 単価]]*商品マスタ[[#This Row],[標準国内送料率]] | R37: 1280 | S37: =IF(ISBLANK(商品マスタ[[#This Row],[実績 国内送料]]),商品マスタ[[#This Row],[標準国内送料]],) | T37: =商品マスタ[[#This Row],[仕入 単価]]+商品マスタ[[#This Row],[国内送料]] | U37: =ROUNDUP(商品マスタ[[#This Row],[仕入単価+国内送料]]/0.8,-1) | V37: =商品マスタ[[#This Row],[海外定価 （20％）]]-商品マスタ[[#This Row],[仕入単価+国内送料]] | W37: =ROUNDUP(商品マスタ[[#This Row],[仕入単価+国内送料]]/0.85,-1) | X37: =商品マスタ[[#This Row],[国内定価 （15％）]]-商品マスタ[[#This Row],[仕入単価+国内送料]] | Y37: 0.08 | Z37: 8日 | AA37: 常温 | AC37: 4562182192189 | AD37: 北海道産の風味豊かなしょうがをふんだんに使い、ピリッとした爽やかな辛味と香りが引き立つ焼肉ソースに仕上げました。ベースには、北海道産大豆を使用したまろやかでコクのある醤油を採用し、味に深みと奥行きをプラス。さらに、カットした北海道産玉ねぎをたっぷりと加えることで、甘みと旨みが増し、よりマイルドで後味すっきりとした味わいを実現しました。 | AF37: 〇
A38: 加工品 | B38: 肉加工品 | C38: シャルキュトリーアカイシ | D38: ="PRD_SNJ_"& _xlfn.XLOOKUP(商品マスタ[[#This Row],[仕入先]],テーブル1[仕入先名],テーブル1[仕入先コード],"XXX",0,1)& "_"& 商品マスタ[[#This Row],[シリアル]]& "_"& TEXT(COUNTIFS(商品マスタ!$C$3:C38,商品マスタ[[#This Row],[仕入先]],商品マスタ!$E$3:E38,商品マスタ[[#This Row],[商品名]]), "00") | E38: 豚バラ肉のベーコン（スライス）/ Poitrine fumée | F38: =IF(COUNTIFS($C$3:C38,商品マスタ[[#This Row],[仕入先]],$E$3:E38,商品マスタ[[#This Row],[商品名]]) = 1, 1,0) | G38: =TEXT(SUMIF($C$3:C38,商品マスタ[[#This Row],[仕入先]],$F$3:F38), "0000") | I38: 100ｇ | J38: 5 | L38: 625 | M38: 45952 | N38: 900 | O38: =IF(COUNT(商品マスタ[[#This Row],[参考上代 （税込)]]) > 0, (商品マスタ[[#This Row],[参考上代 （税込)]]-商品マスタ[[#This Row],[国内定価 （15％）]])/(商品マスタ[[#This Row],[参考上代 （税込)]]/1.08), "") | P38: 0.1 | Q38: =商品マスタ[[#This Row],[仕入 単価]]*商品マスタ[[#This Row],[標準国内送料率]] | S38: =IF(ISBLANK(商品マスタ[[#This Row],[実績 国内送料]]),商品マスタ[[#This Row],[標準国内送料]],) | T38: =商品マスタ[[#This Row],[仕入 単価]]+商品マスタ[[#This Row],[国内送料]] | U38: =ROUNDUP(商品マスタ[[#This Row],[仕入単価+国内送料]]/0.8,-1) | V38: =商品マスタ[[#This Row],[海外定価 （20％）]]-商品マスタ[[#This Row],[仕入単価+国内送料]] | W38: =ROUNDUP(商品マスタ[[#This Row],[仕入単価+国内送料]]/0.85,-1) | X38: =商品マスタ[[#This Row],[国内定価 （15％）]]-商品マスタ[[#This Row],[仕入単価+国内送料]] | Y38: 0.08 | Z38: 30日 | AA38: 10℃以下 | AB38: 5日 | AC38: 4580578380149 | AD38: 桜のチップでスモーク。熟成と燻煙で肉のうまみを凝縮したベーコン。そのまま焼いてベーコンエッグやサンドウィッチに。 | AF38: 〇 | AG38: 最優秀賞受賞商品。2万円以上の注文で送料無料。
A39: 加工品 | B39: 肉加工品 | C39: シャルキュトリーアカイシ | D39: ="PRD_SNJ_"& _xlfn.XLOOKUP(商品マスタ[[#This Row],[仕入先]],テーブル1[仕入先名],テーブル1[仕入先コード],"XXX",0,1)& "_"& 商品マスタ[[#This Row],[シリアル]]& "_"& TEXT(COUNTIFS(商品マスタ!$C$3:C39,商品マスタ[[#This Row],[仕入先]],商品マスタ!$E$3:E39,商品マスタ[[#This Row],[商品名]]), "00") | E39: 豚バラ肉のベーコン（ブロック） / Poitrine fumée | F39: =IF(COUNTIFS($C$3:C39,商品マスタ[[#This Row],[仕入先]],$E$3:E39,商品マスタ[[#This Row],[商品名]]) = 1, 1,0) | G39: =TEXT(SUMIF($C$3:C39,商品マスタ[[#This Row],[仕入先]],$F$3:F39), "0000") | I39: 150ｇ | J39: 5 | L39: 833 | M39: 45952 | N39: 1200 | O39: =IF(COUNT(商品マスタ[[#This Row],[参考上代 （税込)]]) > 0, (商品マスタ[[#This Row],[参考上代 （税込)]]-商品マスタ[[#This Row],[国内定価 （15％）]])/(商品マスタ[[#This Row],[参考上代 （税込)]]/1.08), "") | P39: 0.1 | Q39: =商品マスタ[[#This Row],[仕入 単価]]*商品マスタ[[#This Row],[標準国内送料率]] | S39: =IF(ISBLANK(商品マスタ[[#This Row],[実績 国内送料]]),商品マスタ[[#This Row],[標準国内送料]],) | T39: =商品マスタ[[#This Row],[仕入 単価]]+商品マスタ[[#This Row],[国内送料]] | U39: =ROUNDUP(商品マスタ[[#This Row],[仕入単価+国内送料]]/0.8,-1) | V39: =商品マスタ[[#This Row],[海外定価 （20％）]]-商品マスタ[[#This Row],[仕入単価+国内送料]] | W39: =ROUNDUP(商品マスタ[[#This Row],[仕入単価+国内送料]]/0.85,-1) | X39: =商品マスタ[[#This Row],[国内定価 （15％）]]-商品マスタ[[#This Row],[仕入単価+国内送料]] | Y39: 0.08 | Z39: 30日 | AA39: 10℃以下 | AB39: 5日 | AC39: 4580578380156 | AD39: 桜のチップでスモーク。熟成と燻煙で肉のうまみを凝縮したベーコン。パスタや煮込み料理に。 | AF39: 〇 | AG39: 2万円以上の注文で送料無料。
A40: 飲料アルコール | B40: ワイン | C40: シャルキュトリーアカイシ | D40: ="PRD_SNJ_"& _xlfn.XLOOKUP(商品マスタ[[#This Row],[仕入先]],テーブル1[仕入先名],テーブル1[仕入先コード],"XXX",0,1)& "_"& 商品マスタ[[#This Row],[シリアル]]& "_"& TEXT(COUNTIFS(商品マスタ!$C$3:C40,商品マスタ[[#This Row],[仕入先]],商品マスタ!$E$3:E40,商品マスタ[[#This Row],[商品名]]), "00") | E40: 鶏白レバーペースト/ Pâté de foie blond de volaille | F40: =IF(COUNTIFS($C$3:C40,商品マスタ[[#This Row],[仕入先]],$E$3:E40,商品マスタ[[#This Row],[商品名]]) = 1, 1,0) | G40: =TEXT(SUMIF($C$3:C40,商品マスタ[[#This Row],[仕入先]],$F$3:F40), "0000") | I40: 80g | J40: 5 | L40: 625 | M40: 45952 | N40: 900 | O40: =IF(COUNT(商品マスタ[[#This Row],[参考上代 （税込)]]) > 0, (商品マスタ[[#This Row],[参考上代 （税込)]]-商品マスタ[[#This Row],[国内定価 （15％）]])/(商品マスタ[[#This Row],[参考上代 （税込)]]/1.08), "") | P40: 0.1 | Q40: =商品マスタ[[#This Row],[仕入 単価]]*商品マスタ[[#This Row],[標準国内送料率]] | S40: =IF(ISBLANK(商品マスタ[[#This Row],[実績 国内送料]]),商品マスタ[[#This Row],[標準国内送料]],) | T40: =商品マスタ[[#This Row],[仕入 単価]]+商品マスタ[[#This Row],[国内送料]] | U40: =ROUNDUP(商品マスタ[[#This Row],[仕入単価+国内送料]]/0.8,-1) | V40: =商品マスタ[[#This Row],[海外定価 （20％）]]-商品マスタ[[#This Row],[仕入単価+国内送料]] | W40: =ROUNDUP(商品マスタ[[#This Row],[仕入単価+国内送料]]/0.85,-1) | X40: =商品マスタ[[#This Row],[国内定価 （15％）]]-商品マスタ[[#This Row],[仕入単価+国内送料]] | Y40: 0.08 | Z40: 30日 | AA40: 10℃以下 | AB40: 5日 | AC40: 4580578380194 | AD40: 貴重な鶏の〝フォアグラ〟をクリームと合わせてリッチな味わいのペーストの。スライスしたハード系のパンと一緒に。赤ワインによく合う人気の商品。 | AF40: 〇 | AG40: 2万円以上の注文で送料無料。
A41: 加工品 | B41: 肉加工品 | C41: シャルキュトリーアカイシ | D41: ="PRD_SNJ_"& _xlfn.XLOOKUP(商品マスタ[[#This Row],[仕入先]],テーブル1[仕入先名],テーブル1[仕入先コード],"XXX",0,1)& "_"& 商品マスタ[[#This Row],[シリアル]]& "_"& TEXT(COUNTIFS(商品マスタ!$C$3:C41,商品マスタ[[#This Row],[仕入先]],商品マスタ!$E$3:E41,商品マスタ[[#This Row],[商品名]]), "00") | E41: 北海道産 豚モモ肉のハム / Jambon blanc | F41: =IF(COUNTIFS($C$3:C41,商品マスタ[[#This Row],[仕入先]],$E$3:E41,商品マスタ[[#This Row],[商品名]]) = 1, 1,0) | G41: =TEXT(SUMIF($C$3:C41,商品マスタ[[#This Row],[仕入先]],$F$3:F41), "0000") | I41: 100ｇ | J41: 5 | L41: 625 | M41: 45952 | N41: 900 | O41: =IF(COUNT(商品マスタ[[#This Row],[参考上代 （税込)]]) > 0, (商品マスタ[[#This Row],[参考上代 （税込)]]-商品マスタ[[#This Row],[国内定価 （15％）]])/(商品マスタ[[#This Row],[参考上代 （税込)]]/1.08), "") | P41: 0.1 | Q41: =商品マスタ[[#This Row],[仕入 単価]]*商品マスタ[[#This Row],[標準国内送料率]] | S41: =IF(ISBLANK(商品マスタ[[#This Row],[実績 国内送料]]),商品マスタ[[#This Row],[標準国内送料]],) | T41: =商品マスタ[[#This Row],[仕入 単価]]+商品マスタ[[#This Row],[国内送料]] | U41: =ROUNDUP(商品マスタ[[#This Row],[仕入単価+国内送料]]/0.8,-1) | V41: =商品マスタ[[#This Row],[海外定価 （20％）]]-商品マスタ[[#This Row],[仕入単価+国内送料]] | W41: =ROUNDUP(商品マスタ[[#This Row],[仕入単価+国内送料]]/0.85,-1) | X41: =商品マスタ[[#This Row],[国内定価 （15％）]]-商品マスタ[[#This Row],[仕入単価+国内送料]] | Y41: 0.08 | Z41: 25日 | AA41: 10℃以下 | AB41: 5日 | AC41: 4580578380019 | AD41: ノンスモークでしっとりとした食感に仕上げたモモ肉のハム。 | AF41: 〇 | AG41: 2万円以上の注文で送料無料。
A42: 菓子 | B42: 洋菓子 | C42: シャルキュトリーアカイシ | D42: ="PRD_SNJ_"& _xlfn.XLOOKUP(商品マスタ[[#This Row],[仕入先]],テーブル1[仕入先名],テーブル1[仕入先コード],"XXX",0,1)& "_"& 商品マスタ[[#This Row],[シリアル]]& "_"& TEXT(COUNTIFS(商品マスタ!$C$3:C42,商品マスタ[[#This Row],[仕入先]],商品マスタ!$E$3:E42,商品マスタ[[#This Row],[商品名]]), "00") | E42: ビアブルストEZO / Bierwurst EZO | F42: =IF(COUNTIFS($C$3:C42,商品マスタ[[#This Row],[仕入先]],$E$3:E42,商品マスタ[[#This Row],[商品名]]) = 1, 1,0) | G42: =TEXT(SUMIF($C$3:C42,商品マスタ[[#This Row],[仕入先]],$F$3:F42), "0000") | I42: 80ｇ | J42: 5 | L42: 625 | M42: 45952 | N42: 900 | O42: =IF(COUNT(商品マスタ[[#This Row],[参考上代 （税込)]]) > 0, (商品マスタ[[#This Row],[参考上代 （税込)]]-商品マスタ[[#This Row],[国内定価 （15％）]])/(商品マスタ[[#This Row],[参考上代 （税込)]]/1.08), "") | P42: 0.1 | Q42: =商品マスタ[[#This Row],[仕入 単価]]*商品マスタ[[#This Row],[標準国内送料率]] | S42: =IF(ISBLANK(商品マスタ[[#This Row],[実績 国内送料]]),商品マスタ[[#This Row],[標準国内送料]],) | T42: =商品マスタ[[#This Row],[仕入 単価]]+商品マスタ[[#This Row],[国内送料]] | U42: =ROUNDUP(商品マスタ[[#This Row],[仕入単価+国内送料]]/0.8,-1) | V42: =商品マスタ[[#This Row],[海外定価 （20％）]]-商品マスタ[[#This Row],[仕入単価+国内送料]] | W42: =ROUNDUP(商品マスタ[[#This Row],[仕入単価+国内送料]]/0.85,-1) | X42: =商品マスタ[[#This Row],[国内定価 （15％）]]-商品マスタ[[#This Row],[仕入単価+国内送料]] | Y42: 0.08 | Z42: 25日 | AA42: 10℃以下 | AB42: 5日 | AC42: 4580578380071 | AD42: 蝦夷鹿肉と豚肉のスパイシーなボロニアソーセージ。ホットサンドやサラダ等に。 | AF42: 〇 | AG42: 2万円以上の注文で送料無料。
A43: 加工品 | B43: 肉加工品 | C43: シャルキュトリーアカイシ | D43: ="PRD_SNJ_"& _xlfn.XLOOKUP(商品マスタ[[#This Row],[仕入先]],テーブル1[仕入先名],テーブル1[仕入先コード],"XXX",0,1)& "_"& 商品マスタ[[#This Row],[シリアル]]& "_"& TEXT(COUNTIFS(商品マスタ!$C$3:C43,商品マスタ[[#This Row],[仕入先]],商品マスタ!$E$3:E43,商品マスタ[[#This Row],[商品名]]), "00") | E43: パテ・ド・カンパーニュ / Pâté de campagne | F43: =IF(COUNTIFS($C$3:C43,商品マスタ[[#This Row],[仕入先]],$E$3:E43,商品マスタ[[#This Row],[商品名]]) = 1, 1,0) | G43: =TEXT(SUMIF($C$3:C43,商品マスタ[[#This Row],[仕入先]],$F$3:F43), "0000") | I43: 100g | J43: 5 | L43: 556 | M43: 45952 | N43: 800 | O43: =IF(COUNT(商品マスタ[[#This Row],[参考上代 （税込)]]) > 0, (商品マスタ[[#This Row],[参考上代 （税込)]]-商品マスタ[[#This Row],[国内定価 （15％）]])/(商品マスタ[[#This Row],[参考上代 （税込)]]/1.08), "") | P43: 0.1 | Q43: =商品マスタ[[#This Row],[仕入 単価]]*商品マスタ[[#This Row],[標準国内送料率]] | S43: =IF(ISBLANK(商品マスタ[[#This Row],[実績 国内送料]]),商品マスタ[[#This Row],[標準国内送料]],) | T43: =商品マスタ[[#This Row],[仕入 単価]]+商品マスタ[[#This Row],[国内送料]] | U43: =ROUNDUP(商品マスタ[[#This Row],[仕入単価+国内送料]]/0.8,-1) | V43: =商品マスタ[[#This Row],[海外定価 （20％）]]-商品マスタ[[#This Row],[仕入単価+国内送料]] | W43: =ROUNDUP(商品マスタ[[#This Row],[仕入単価+国内送料]]/0.85,-1) | X43: =商品マスタ[[#This Row],[国内定価 （15％）]]-商品マスタ[[#This Row],[仕入単価+国内送料]] | Y43: 0.08 | Z43: 25日 | AA43: 10℃以下 | AB43: 5日 | AC43: 4580578380316 | AD43: 北海道産豚使用。しっとりと焼き上げコクのある味わいに。 | AF43: 〇 | AG43: 2万円以上の注文で送料無料。
A44: 加工品 | B44: 肉加工品 | C44: シャルキュトリーアカイシ | D44: ="PRD_SNJ_"& _xlfn.XLOOKUP(商品マスタ[[#This Row],[仕入先]],テーブル1[仕入先名],テーブル1[仕入先コード],"XXX",0,1)& "_"& 商品マスタ[[#This Row],[シリアル]]& "_"& TEXT(COUNTIFS(商品マスタ!$C$3:C44,商品マスタ[[#This Row],[仕入先]],商品マスタ!$E$3:E44,商品マスタ[[#This Row],[商品名]]), "00") | E44: 蝦夷鹿のパテ / Pâté de chevreuil | F44: =IF(COUNTIFS($C$3:C44,商品マスタ[[#This Row],[仕入先]],$E$3:E44,商品マスタ[[#This Row],[商品名]]) = 1, 1,0) | G44: =TEXT(SUMIF($C$3:C44,商品マスタ[[#This Row],[仕入先]],$F$3:F44), "0000") | I44: 100g | J44: 5 | L44: 625 | M44: 45952 | N44: 900 | O44: =IF(COUNT(商品マスタ[[#This Row],[参考上代 （税込)]]) > 0, (商品マスタ[[#This Row],[参考上代 （税込)]]-商品マスタ[[#This Row],[国内定価 （15％）]])/(商品マスタ[[#This Row],[参考上代 （税込)]]/1.08), "") | P44: 0.1 | Q44: =商品マスタ[[#This Row],[仕入 単価]]*商品マスタ[[#This Row],[標準国内送料率]] | S44: =IF(ISBLANK(商品マスタ[[#This Row],[実績 国内送料]]),商品マスタ[[#This Row],[標準国内送料]],) | T44: =商品マスタ[[#This Row],[仕入 単価]]+商品マスタ[[#This Row],[国内送料]] | U44: =ROUNDUP(商品マスタ[[#This Row],[仕入単価+国内送料]]/0.8,-1) | V44: =商品マスタ[[#This Row],[海外定価 （20％）]]-商品マスタ[[#This Row],[仕入単価+国内送料]] | W44: =ROUNDUP(商品マスタ[[#This Row],[仕入単価+国内送料]]/0.85,-1) | X44: =商品マスタ[[#This Row],[国内定価 （15％）]]-商品マスタ[[#This Row],[仕入単価+国内送料]] | Y44: 0.08 | Z44: 25日 | AA44: 10℃以下 | AB44: 5日 | AC44: 4580578380323 | AD44: 蝦夷鹿と合鴨レバー、自家製ベーコンの濃厚な旨みと香りをまとった上質なパテ。 | AF44: 〇 | AG44: 2万円以上の注文で送料無料。
A45: 加工品 | B45: 肉加工品 | C45: シャルキュトリーアカイシ | D45: ="PRD_SNJ_"& _xlfn.XLOOKUP(商品マスタ[[#This Row],[仕入先]],テーブル1[仕入先名],テーブル1[仕入先コード],"XXX",0,1)& "_"& 商品マスタ[[#This Row],[シリアル]]& "_"& TEXT(COUNTIFS(商品マスタ!$C$3:C45,商品マスタ[[#This Row],[仕入先]],商品マスタ!$E$3:E45,商品マスタ[[#This Row],[商品名]]), "00") | E45: 丸ごと豚のテリーヌ / Fromage de tête | F45: =IF(COUNTIFS($C$3:C45,商品マスタ[[#This Row],[仕入先]],$E$3:E45,商品マスタ[[#This Row],[商品名]]) = 1, 1,0) | G45: =TEXT(SUMIF($C$3:C45,商品マスタ[[#This Row],[仕入先]],$F$3:F45), "0000") | I45: 90ｇ | J45: 5 | L45: 625 | M45: 45952 | N45: 900 | O45: =IF(COUNT(商品マスタ[[#This Row],[参考上代 （税込)]]) > 0, (商品マスタ[[#This Row],[参考上代 （税込)]]-商品マスタ[[#This Row],[国内定価 （15％）]])/(商品マスタ[[#This Row],[参考上代 （税込)]]/1.08), "") | P45: 0.1 | Q45: =商品マスタ[[#This Row],[仕入 単価]]*商品マスタ[[#This Row],[標準国内送料率]] | S45: =IF(ISBLANK(商品マスタ[[#This Row],[実績 国内送料]]),商品マスタ[[#This Row],[標準国内送料]],) | T45: =商品マスタ[[#This Row],[仕入 単価]]+商品マスタ[[#This Row],[国内送料]] | U45: =ROUNDUP(商品マスタ[[#This Row],[仕入単価+国内送料]]/0.8,-1) | V45: =商品マスタ[[#This Row],[海外定価 （20％）]]-商品マスタ[[#This Row],[仕入単価+国内送料]] | W45: =ROUNDUP(商品マスタ[[#This Row],[仕入単価+国内送料]]/0.85,-1) | X45: =商品マスタ[[#This Row],[国内定価 （15％）]]-商品マスタ[[#This Row],[仕入単価+国内送料]] | Y45: 0.08 | Z45: 25日 | AA45: 10℃以下 | AB45: 5日 | AC45: 4580578380330 | AD45: コルニッションピクルスをアクセントにした豚の頭のテリーヌ。冷たいままスライスして。 | AF45: 〇 | AG45: 2万円以上の注文で送料無料。
A46: 加工品 | B46: 肉加工品 | C46: シャルキュトリーアカイシ | D46: ="PRD_SNJ_"& _xlfn.XLOOKUP(商品マスタ[[#This Row],[仕入先]],テーブル1[仕入先名],テーブル1[仕入先コード],"XXX",0,1)& "_"& 商品マスタ[[#This Row],[シリアル]]& "_"& TEXT(COUNTIFS(商品マスタ!$C$3:C46,商品マスタ[[#This Row],[仕入先]],商品マスタ!$E$3:E46,商品マスタ[[#This Row],[商品名]]), "00") | E46: 鶏砂肝のコンフィ / Gégiers de volaille confit | F46: =IF(COUNTIFS($C$3:C46,商品マスタ[[#This Row],[仕入先]],$E$3:E46,商品マスタ[[#This Row],[商品名]]) = 1, 1,0) | G46: =TEXT(SUMIF($C$3:C46,商品マスタ[[#This Row],[仕入先]],$F$3:F46), "0000") | I46: 120ｇ | J46: 5 | L46: 750 | M46: 45952 | N46: 1080 | O46: =IF(COUNT(商品マスタ[[#This Row],[参考上代 （税込)]]) > 0, (商品マスタ[[#This Row],[参考上代 （税込)]]-商品マスタ[[#This Row],[国内定価 （15％）]])/(商品マスタ[[#This Row],[参考上代 （税込)]]/1.08), "") | P46: 0.1 | Q46: =商品マスタ[[#This Row],[仕入 単価]]*商品マスタ[[#This Row],[標準国内送料率]] | S46: =IF(ISBLANK(商品マスタ[[#This Row],[実績 国内送料]]),商品マスタ[[#This Row],[標準国内送料]],) | T46: =商品マスタ[[#This Row],[仕入 単価]]+商品マスタ[[#This Row],[国内送料]] | U46: =ROUNDUP(商品マスタ[[#This Row],[仕入単価+国内送料]]/0.8,-1) | V46: =商品マスタ[[#This Row],[海外定価 （20％）]]-商品マスタ[[#This Row],[仕入単価+国内送料]] | W46: =ROUNDUP(商品マスタ[[#This Row],[仕入単価+国内送料]]/0.85,-1) | X46: =商品マスタ[[#This Row],[国内定価 （15％）]]-商品マスタ[[#This Row],[仕入単価+国内送料]] | Y46: 0.08 | Z46: 25日 | AA46: 10℃以下 | AB46: 5日 | AC46: 4580578380200 | AD46: 砂肝を柔らかなオイル煮に。黒胡椒とガーリックのフレーバー。そのままでも、軽くソテーしても！ | AF46: 〇 | AG46: 2万円以上の注文で送料無料。
A47: 精肉 | B47: 和牛 | C47: シャルキュトリーアカイシ | D47: ="PRD_SNJ_"& _xlfn.XLOOKUP(商品マスタ[[#This Row],[仕入先]],テーブル1[仕入先名],テーブル1[仕入先コード],"XXX",0,1)& "_"& 商品マスタ[[#This Row],[シリアル]]& "_"& TEXT(COUNTIFS(商品マスタ!$C$3:C47,商品マスタ[[#This Row],[仕入先]],商品マスタ!$E$3:E47,商品マスタ[[#This Row],[商品名]]), "00") | E47: ストラスブルグ ソーセージ/ Saucisse de strasbourg | F47: =IF(COUNTIFS($C$3:C47,商品マスタ[[#This Row],[仕入先]],$E$3:E47,商品マスタ[[#This Row],[商品名]]) = 1, 1,0) | G47: =TEXT(SUMIF($C$3:C47,商品マスタ[[#This Row],[仕入先]],$F$3:F47), "0000") | I47: 160ｇ | J47: 5 | L47: 833 | M47: 45952 | N47: 1200 | O47: =IF(COUNT(商品マスタ[[#This Row],[参考上代 （税込)]]) > 0, (商品マスタ[[#This Row],[参考上代 （税込)]]-商品マスタ[[#This Row],[国内定価 （15％）]])/(商品マスタ[[#This Row],[参考上代 （税込)]]/1.08), "") | P47: 0.1 | Q47: =商品マスタ[[#This Row],[仕入 単価]]*商品マスタ[[#This Row],[標準国内送料率]] | S47: =IF(ISBLANK(商品マスタ[[#This Row],[実績 国内送料]]),商品マスタ[[#This Row],[標準国内送料]],) | T47: =商品マスタ[[#This Row],[仕入 単価]]+商品マスタ[[#This Row],[国内送料]] | U47: =ROUNDUP(商品マスタ[[#This Row],[仕入単価+国内送料]]/0.8,-1) | V47: =商品マスタ[[#This Row],[海外定価 （20％）]]-商品マスタ[[#This Row],[仕入単価+国内送料]] | W47: =ROUNDUP(商品マスタ[[#This Row],[仕入単価+国内送料]]/0.85,-1) | X47: =商品マスタ[[#This Row],[国内定価 （15％）]]-商品マスタ[[#This Row],[仕入単価+国内送料]] | Y47: 0.08 | Z47: 25日 | AA47: 10℃以下 | AB47: 5日 | AC47: 4580578380064 | AD47: 北海道産ポークと牛肉で作ったジューシーなウィンナーソーセージ。ホットドックやシュクルートに。 | AF47: 〇 | AG47: 2万円以上の注文で送料無料。
A48: 加工品 | B48: 肉加工品 | C48: シャルキュトリーアカイシ | D48: ="PRD_SNJ_"& _xlfn.XLOOKUP(商品マスタ[[#This Row],[仕入先]],テーブル1[仕入先名],テーブル1[仕入先コード],"XXX",0,1)& "_"& 商品マスタ[[#This Row],[シリアル]]& "_"& TEXT(COUNTIFS(商品マスタ!$C$3:C48,商品マスタ[[#This Row],[仕入先]],商品マスタ!$E$3:E48,商品マスタ[[#This Row],[商品名]]), "00") | E48: ブーダンブラン / Boudin blanc | F48: =IF(COUNTIFS($C$3:C48,商品マスタ[[#This Row],[仕入先]],$E$3:E48,商品マスタ[[#This Row],[商品名]]) = 1, 1,0) | G48: =TEXT(SUMIF($C$3:C48,商品マスタ[[#This Row],[仕入先]],$F$3:F48), "0000") | I48: 160ｇ | J48: 5 | L48: 625 | M48: 45952 | N48: 900 | O48: =IF(COUNT(商品マスタ[[#This Row],[参考上代 （税込)]]) > 0, (商品マスタ[[#This Row],[参考上代 （税込)]]-商品マスタ[[#This Row],[国内定価 （15％）]])/(商品マスタ[[#This Row],[参考上代 （税込)]]/1.08), "") | P48: 0.1 | Q48: =商品マスタ[[#This Row],[仕入 単価]]*商品マスタ[[#This Row],[標準国内送料率]] | S48: =IF(ISBLANK(商品マスタ[[#This Row],[実績 国内送料]]),商品マスタ[[#This Row],[標準国内送料]],) | T48: =商品マスタ[[#This Row],[仕入 単価]]+商品マスタ[[#This Row],[国内送料]] | U48: =ROUNDUP(商品マスタ[[#This Row],[仕入単価+国内送料]]/0.8,-1) | V48: =商品マスタ[[#This Row],[海外定価 （20％）]]-商品マスタ[[#This Row],[仕入単価+国内送料]] | W48: =ROUNDUP(商品マスタ[[#This Row],[仕入単価+国内送料]]/0.85,-1) | X48: =商品マスタ[[#This Row],[国内定価 （15％）]]-商品マスタ[[#This Row],[仕入単価+国内送料]] | Y48: 0.08 | Z48: 15日 | AA48: 10℃以下 | AB48: 5日 | AC48: 4580578380088 | AD48: 豚肉と牛乳、ハーブオレンジピールの滑らかな食感の香豊かなソーセージ。 | AF48: 〇 | AG48: 2万円以上の注文で送料無料。
A49: 飲料アルコール | B49: ワイン | C49: シャルキュトリーアカイシ | D49: ="PRD_SNJ_"& _xlfn.XLOOKUP(商品マスタ[[#This Row],[仕入先]],テーブル1[仕入先名],テーブル1[仕入先コード],"XXX",0,1)& "_"& 商品マスタ[[#This Row],[シリアル]]& "_"& TEXT(COUNTIFS(商品マスタ!$C$3:C49,商品マスタ[[#This Row],[仕入先]],商品マスタ!$E$3:E49,商品マスタ[[#This Row],[商品名]]), "00") | E49: 長期熟成サラミ / Saucisson sec maison | F49: =IF(COUNTIFS($C$3:C49,商品マスタ[[#This Row],[仕入先]],$E$3:E49,商品マスタ[[#This Row],[商品名]]) = 1, 1,0) | G49: =TEXT(SUMIF($C$3:C49,商品マスタ[[#This Row],[仕入先]],$F$3:F49), "0000") | I49: 120ｇ | J49: 5 | L49: 1458 | M49: 45952 | N49: 2100 | O49: =IF(COUNT(商品マスタ[[#This Row],[参考上代 （税込)]]) > 0, (商品マスタ[[#This Row],[参考上代 （税込)]]-商品マスタ[[#This Row],[国内定価 （15％）]])/(商品マスタ[[#This Row],[参考上代 （税込)]]/1.08), "") | P49: 0.1 | Q49: =商品マスタ[[#This Row],[仕入 単価]]*商品マスタ[[#This Row],[標準国内送料率]] | S49: =IF(ISBLANK(商品マスタ[[#This Row],[実績 国内送料]]),商品マスタ[[#This Row],[標準国内送料]],) | T49: =商品マスタ[[#This Row],[仕入 単価]]+商品マスタ[[#This Row],[国内送料]] | U49: =ROUNDUP(商品マスタ[[#This Row],[仕入単価+国内送料]]/0.8,-1) | V49: =商品マスタ[[#This Row],[海外定価 （20％）]]-商品マスタ[[#This Row],[仕入単価+国内送料]] | W49: =ROUNDUP(商品マスタ[[#This Row],[仕入単価+国内送料]]/0.85,-1) | X49: =商品マスタ[[#This Row],[国内定価 （15％）]]-商品マスタ[[#This Row],[仕入単価+国内送料]] | Y49: 0.08 | Z49: 50日 | AA49: 10℃以下 | AB49: 5日 | AC49: 4580578380163 | AD49: 徐々に溢れ出る旨みの熟成サラミ。軽めの赤ワインと。 【※数量限定。要在庫確認】 | AF49: 〇 | AG49: 【※数量限定。要在庫確認】2万円以上の注文で送料無料。
... A51: 加工品 | B51: 肉加工品 | C51: シャルキュトリーアカイシ | D51: ="PRD_SNJ_"& _xlfn.XLOOKUP(商品マスタ[[#This Row],[仕入先]],テーブル1[仕入先名],テーブル1[仕入先コード],"XXX",0,1)& "_"& 商品マスタ[[#This Row],[シリアル]]& "_"& TEXT(COUNTIFS(商品マスタ!$C$3:C51,商品マスタ[[#This Row],[仕入先]],商品マスタ!$E$3:E51,商品マスタ[[#This Row],[商品名]]), "00") | E51: 長期熟成フェンネルのサラミ / Finocchiona | F51: =IF(COUNTIFS($C$3:C51,商品マスタ[[#This Row],[仕入先]],$E$3:E51,商品マスタ[[#This Row],[商品名]]) = 1, 1,0) | G51: =TEXT(SUMIF($C$3:C51,商品マスタ[[#This Row],[仕入先]],$F$3:F51), "0000") | I51: 120ｇ | J51: 5 | L51: 1458 | M51: 45952 | N51: 2100 | O51: =IF(COUNT(商品マスタ[[#This Row],[参考上代 （税込)]]) > 0, (商品マスタ[[#This Row],[参考上代 （税込)]]-商品マスタ[[#This Row],[国内定価 （15％）]])/(商品マスタ[[#This Row],[参考上代 （税込)]]/1.08), "") | P51: 0.1 | Q51: =商品マスタ[[#This Row],[仕入 単価]]*商品マスタ[[#This Row],[標準国内送料率]] | S51: =IF(ISBLANK(商品マスタ[[#This Row],[実績 国内送料]]),商品マスタ[[#This Row],[標準国内送料]],) | T51: =商品マスタ[[#This Row],[仕入 単価]]+商品マスタ[[#This Row],[国内送料]] | U51: =ROUNDUP(商品マスタ[[#This Row],[仕入単価+国内送料]]/0.8,-1) | V51: =商品マスタ[[#This Row],[海外定価 （20％）]]-商品マスタ[[#This Row],[仕入単価+国内送料]] | W51: =ROUNDUP(商品マスタ[[#This Row],[仕入単価+国内送料]]/0.85,-1) | X51: =商品マスタ[[#This Row],[国内定価 （15％）]]-商品マスタ[[#This Row],[仕入単価+国内送料]] | Y51: 0.08 | Z51: 50日 | AA51: 10℃以下 | AB51: 5日 | AC51: 4580578380187 | AD51: 爽やかなフェンネルシードが香るイタリアンタイプ。 【※数量限定。要在庫確認】 | AF51: 〇 | AG51: 【※数量限定。要在庫確認】2万円以上の注文で送料無料。
A52: 菓子 | B52: 和菓子 | C52: 藤田水産 | D52: ="PRD_SNJ_"& _xlfn.XLOOKUP(商品マスタ[[#This Row],[仕入先]],テーブル1[仕入先名],テーブル1[仕入先コード],"XXX",0,1)& "_"& 商品マスタ[[#This Row],[シリアル]]& "_"& TEXT(COUNTIFS(商品マスタ!$C$3:C52,商品マスタ[[#This Row],[仕入先]],商品マスタ!$E$3:E52,商品マスタ[[#This Row],[商品名]]), "00") | E52: 引張たこ（短） | F52: =IF(COUNTIFS($C$3:C52,商品マスタ[[#This Row],[仕入先]],$E$3:E52,商品マスタ[[#This Row],[商品名]]) = 1, 1,0) | G52: =TEXT(SUMIF($C$3:C52,商品マスタ[[#This Row],[仕入先]],$F$3:F52), "0000") | I52: 45g | J52: 15 | L52: 600 | M52: 45953 | N52: 980 | O52: =IF(COUNT(商品マスタ[[#This Row],[参考上代 （税込)]]) > 0, (商品マスタ[[#This Row],[参考上代 （税込)]]-商品マスタ[[#This Row],[国内定価 （15％）]])/(商品マスタ[[#This Row],[参考上代 （税込)]]/1.08), "") | P52: 0.1 | Q52: =商品マスタ[[#This Row],[仕入 単価]]*商品マスタ[[#This Row],[標準国内送料率]] | R52: 1500 | S52: =IF(ISBLANK(商品マスタ[[#This Row],[実績 国内送料]]),商品マスタ[[#This Row],[標準国内送料]],) | T52: =商品マスタ[[#This Row],[仕入 単価]]+商品マスタ[[#This Row],[国内送料]] | U52: =ROUNDUP(商品マスタ[[#This Row],[仕入単価+国内送料]]/0.8,-1) | V52: =商品マスタ[[#This Row],[海外定価 （20％）]]-商品マスタ[[#This Row],[仕入単価+国内送料]] | W52: =ROUNDUP(商品マスタ[[#This Row],[仕入単価+国内送料]]/0.85,-1) | X52: =商品マスタ[[#This Row],[国内定価 （15％）]]-商品マスタ[[#This Row],[仕入単価+国内送料]] | Z52: 180日 | AA52: 常温 | AB52: 5日 | AC52: 4901944000087 | AD52: 原材料のもち米、砂糖、生飴、オブラートは北海道産を使用しています。社内人気NO.1。食べやすい一口サイズです。 | AF52: 〇
A53: 菓子 | B53: 和菓子 | C53: 藤田水産 | D53: ="PRD_SNJ_"& _xlfn.XLOOKUP(商品マスタ[[#This Row],[仕入先]],テーブル1[仕入先名],テーブル1[仕入先コード],"XXX",0,1)& "_"& 商品マスタ[[#This Row],[シリアル]]& "_"& TEXT(COUNTIFS(商品マスタ!$C$3:C53,商品マスタ[[#This Row],[仕入先]],商品マスタ!$E$3:E53,商品マスタ[[#This Row],[商品名]]), "00") | E53: たこ頭ロール | F53: =IF(COUNTIFS($C$3:C53,商品マスタ[[#This Row],[仕入先]],$E$3:E53,商品マスタ[[#This Row],[商品名]]) = 1, 1,0) | G53: =TEXT(SUMIF($C$3:C53,商品マスタ[[#This Row],[仕入先]],$F$3:F53), "0000") | I53: 55g | J53: 15 | L53: 600 | M53: 45953 | N53: 980 | O53: =IF(COUNT(商品マスタ[[#This Row],[参考上代 （税込)]]) > 0, (商品マスタ[[#This Row],[参考上代 （税込)]]-商品マスタ[[#This Row],[国内定価 （15％）]])/(商品マスタ[[#This Row],[参考上代 （税込)]]/1.08), "") | P53: 0.1 | Q53: =商品マスタ[[#This Row],[仕入 単価]]*商品マスタ[[#This Row],[標準国内送料率]] | R53: 1500 | S53: =IF(ISBLANK(商品マスタ[[#This Row],[実績 国内送料]]),商品マスタ[[#This Row],[標準国内送料]],) | T53: =商品マスタ[[#This Row],[仕入 単価]]+商品マスタ[[#This Row],[国内送料]] | U53: =ROUNDUP(商品マスタ[[#This Row],[仕入単価+国内送料]]/0.8,-1) | V53: =商品マスタ[[#This Row],[海外定価 （20％）]]-商品マスタ[[#This Row],[仕入単価+国内送料]] | W53: =ROUNDUP(商品マスタ[[#This Row],[仕入単価+国内送料]]/0.85,-1) | X53: =商品マスタ[[#This Row],[国内定価 （15％）]]-商品マスタ[[#This Row],[仕入単価+国内送料]] | Z53: 150日 | AA53: 常温 | AB53: 5日 | AC53: 4901944000117 | AD53: 原材料のもち米、砂糖、生飴、オブラートは北海道産を使用しています。 | AF53: 〇
A54: 菓子 | B54: 和菓子 | C54: 谷田製菓 | D54: ="PRD_SNJ_"& _xlfn.XLOOKUP(商品マスタ[[#This Row],[仕入先]],テーブル1[仕入先名],テーブル1[仕入先コード],"XXX",0,1)& "_"& 商品マスタ[[#This Row],[シリアル]]& "_"& TEXT(COUNTIFS(商品マスタ!$C$3:C54,商品マスタ[[#This Row],[仕入先]],商品マスタ!$E$3:E54,商品マスタ[[#This Row],[商品名]]), "00") | E54: 一口きびだんご | F54: =IF(COUNTIFS($C$3:C54,商品マスタ[[#This Row],[仕入先]],$E$3:E54,商品マスタ[[#This Row],[商品名]]) = 1, 1,0) | G54: =TEXT(SUMIF($C$3:C54,商品マスタ[[#This Row],[仕入先]],$F$3:F54), "0000") | I54: 10×4 | J54: 40 | L54: 310 | M54: 45953 | N54: 500 | O54: =IF(COUNT(商品マスタ[[#This Row],[参考上代 （税込)]]) > 0, (商品マスタ[[#This Row],[参考上代 （税込)]]-商品マスタ[[#This Row],[国内定価 （15％）]])/(商品マスタ[[#This Row],[参考上代 （税込)]]/1.08), "") | P54: 0.1 | Q54: =商品マスタ[[#This Row],[仕入 単価]]*商品マスタ[[#This Row],[標準国内送料率]] | S54: =IF(ISBLANK(商品マスタ[[#This Row],[実績 国内送料]]),商品マスタ[[#This Row],[標準国内送料]],) | T54: =商品マスタ[[#This Row],[仕入 単価]]+商品マスタ[[#This Row],[国内送料]] | U54: =ROUNDUP(商品マスタ[[#This Row],[仕入単価+国内送料]]/0.8,-1) | V54: =商品マスタ[[#This Row],[海外定価 （20％）]]-商品マスタ[[#This Row],[仕入単価+国内送料]] | W54: =ROUNDUP(商品マスタ[[#This Row],[仕入単価+国内送料]]/0.85,-1) | X54: =商品マスタ[[#This Row],[国内定価 （15％）]]-商品マスタ[[#This Row],[仕入単価+国内送料]] | Z54: 150日 | AA54: 常温 | AB54: 5日 | AC54: 4901944000124 | AD54: 原材料のもち米、砂糖、生飴、オブラートは北海道産を使用しています。 | AF54: 〇
A55: 菓子 | B55: 和菓子 | C55: 谷田製菓 | D55: ="PRD_SNJ_"& _xlfn.XLOOKUP(商品マスタ[[#This Row],[仕入先]],テーブル1[仕入先名],テーブル1[仕入先コード],"XXX",0,1)& "_"& 商品マスタ[[#This Row],[シリアル]]& "_"& TEXT(COUNTIFS(商品マスタ!$C$3:C55,商品マスタ[[#This Row],[仕入先]],商品マスタ!$E$3:E55,商品マスタ[[#This Row],[商品名]]), "00") | E55: 谷田の日本一きびだんご30ｇ | F55: =IF(COUNTIFS($C$3:C55,商品マスタ[[#This Row],[仕入先]],$E$3:E55,商品マスタ[[#This Row],[商品名]]) = 1, 1,0) | G55: =TEXT(SUMIF($C$3:C55,商品マスタ[[#This Row],[仕入先]],$F$3:F55), "0000") | I55: 20×16 | J55: 320 | L55: 40.5 | M55: 45953 | N55: 60 | O55: =IF(COUNT(商品マスタ[[#This Row],[参考上代 （税込)]]) > 0, (商品マスタ[[#This Row],[参考上代 （税込)]]-商品マスタ[[#This Row],[国内定価 （15％）]])/(商品マスタ[[#This Row],[参考上代 （税込)]]/1.08), "") | P55: 0.1 | Q55: =商品マスタ[[#This Row],[仕入 単価]]*商品マスタ[[#This Row],[標準国内送料率]] | S55: =IF(ISBLANK(商品マスタ[[#This Row],[実績 国内送料]]),商品マスタ[[#This Row],[標準国内送料]],) | T55: =商品マスタ[[#This Row],[仕入 単価]]+商品マスタ[[#This Row],[国内送料]] | U55: =ROUNDUP(商品マスタ[[#This Row],[仕入単価+国内送料]]/0.8,-1) | V55: =商品マスタ[[#This Row],[海外定価 （20％）]]-商品マスタ[[#This Row],[仕入単価+国内送料]] | W55: =ROUNDUP(商品マスタ[[#This Row],[仕入単価+国内送料]]/0.85,-1) | X55: =商品マスタ[[#This Row],[国内定価 （15％）]]-商品マスタ[[#This Row],[仕入単価+国内送料]] | Z55: 150日 | AA55: 常温 | AB55: 5日 | AC55: 4901944000018 | AD55: 原材料のもち米、砂糖、生餡、オブラートは北海道産を使用しています。大正１２年創製のロングラン商品です。 | AF55: 〇
A56: 菓子 | B56: 和菓子 | C56: 谷田製菓 | D56: ="PRD_SNJ_"& _xlfn.XLOOKUP(商品マスタ[[#This Row],[仕入先]],テーブル1[仕入先名],テーブル1[仕入先コード],"XXX",0,1)& "_"& 商品マスタ[[#This Row],[シリアル]]& "_"& TEXT(COUNTIFS(商品マスタ!$C$3:C56,商品マスタ[[#This Row],[仕入先]],商品マスタ!$E$3:E56,商品マスタ[[#This Row],[商品名]]), "00") | E56: 谷田の日本一きびだんご30ｇｘ４個入 | F56: =IF(COUNTIFS($C$3:C56,商品マスタ[[#This Row],[仕入先]],$E$3:E56,商品マスタ[[#This Row],[商品名]]) = 1, 1,0) | G56: =TEXT(SUMIF($C$3:C56,商品マスタ[[#This Row],[仕入先]],$F$3:F56), "0000") | I56: 10×８ | J56: 80 | L56: 161 | M56: 45953 | N56: 240 | O56: =IF(COUNT(商品マスタ[[#This Row],[参考上代 （税込)]]) > 0, (商品マスタ[[#This Row],[参考上代 （税込)]]-商品マスタ[[#This Row],[国内定価 （15％）]])/(商品マスタ[[#This Row],[参考上代 （税込)]]/1.08), "") | P56: 0.1 | Q56: =商品マスタ[[#This Row],[仕入 単価]]*商品マスタ[[#This Row],[標準国内送料率]] | S56: =IF(ISBLANK(商品マスタ[[#This Row],[実績 国内送料]]),商品マスタ[[#This Row],[標準国内送料]],) | T56: =商品マスタ[[#This Row],[仕入 単価]]+商品マスタ[[#This Row],[国内送料]] | U56: =ROUNDUP(商品マスタ[[#This Row],[仕入単価+国内送料]]/0.8,-1) | V56: =商品マスタ[[#This Row],[海外定価 （20％）]]-商品マスタ[[#This Row],[仕入単価+国内送料]] | W56: =ROUNDUP(商品マスタ[[#This Row],[仕入単価+国内送料]]/0.85,-1) | X56: =商品マスタ[[#This Row],[国内定価 （15％）]]-商品マスタ[[#This Row],[仕入単価+国内送料]] | Z56: 180日 | AA56: 常温 | AB56: 5日 | AC56: 4901944001886 | AD56: 原材料のもち米、砂糖、生飴、オブラートは北海道産を使用しています。当社ＮＯ１商品とファイターズのコラボ商品! | AF56: 〇
A57: 菓子 | B57: 和菓子 | C57: 谷田製菓 | D57: ="PRD_SNJ_"& _xlfn.XLOOKUP(商品マスタ[[#This Row],[仕入先]],テーブル1[仕入先名],テーブル1[仕入先コード],"XXX",0,1)& "_"& 商品マスタ[[#This Row],[シリアル]]& "_"& TEXT(COUNTIFS(商品マスタ!$C$3:C57,商品マスタ[[#This Row],[仕入先]],商品マスタ!$E$3:E57,商品マスタ[[#This Row],[商品名]]), "00") | E57: 日本一きびだんご70g | F57: =IF(COUNTIFS($C$3:C57,商品マスタ[[#This Row],[仕入先]],$E$3:E57,商品マスタ[[#This Row],[商品名]]) = 1, 1,0) | G57: =TEXT(SUMIF($C$3:C57,商品マスタ[[#This Row],[仕入先]],$F$3:F57), "0000") | I57: 10×16 | J57: 160 | L57: 92.5 | M57: 45953 | N57: 140 | O57: =IF(COUNT(商品マスタ[[#This Row],[参考上代 （税込)]]) > 0, (商品マスタ[[#This Row],[参考上代 （税込)]]-商品マスタ[[#This Row],[国内定価 （15％）]])/(商品マスタ[[#This Row],[参考上代 （税込)]]/1.08), "") | P57: 0.1 | Q57: =商品マスタ[[#This Row],[仕入 単価]]*商品マスタ[[#This Row],[標準国内送料率]] | S57: =IF(ISBLANK(商品マスタ[[#This Row],[実績 国内送料]]),商品マスタ[[#This Row],[標準国内送料]],) | T57: =商品マスタ[[#This Row],[仕入 単価]]+商品マスタ[[#This Row],[国内送料]] | U57: =ROUNDUP(商品マスタ[[#This Row],[仕入単価+国内送料]]/0.8,-1) | V57: =商品マスタ[[#This Row],[海外定価 （20％）]]-商品マスタ[[#This Row],[仕入単価+国内送料]] | W57: =ROUNDUP(商品マスタ[[#This Row],[仕入単価+国内送料]]/0.85,-1) | X57: =商品マスタ[[#This Row],[国内定価 （15％）]]-商品マスタ[[#This Row],[仕入単価+国内送料]] | Z57: 180日 | AA57: 常温 | AB57: 5日 | AC57: 4901944001893 | AD57: 原材料のもち米、砂糖、生飴、オブラートは北海道産を使用しています。ファイターズのコラボ商品! | AF57: 〇
A58: 菓子 | B58: 和菓子 | C58: 谷田製菓 | D58: ="PRD_SNJ_"& _xlfn.XLOOKUP(商品マスタ[[#This Row],[仕入先]],テーブル1[仕入先名],テーブル1[仕入先コード],"XXX",0,1)& "_"& 商品マスタ[[#This Row],[シリアル]]& "_"& TEXT(COUNTIFS(商品マスタ!$C$3:C58,商品マスタ[[#This Row],[仕入先]],商品マスタ!$E$3:E58,商品マスタ[[#This Row],[商品名]]), "00") | E58: ファイターズ一口きびだんご98ｇ | F58: =IF(COUNTIFS($C$3:C58,商品マスタ[[#This Row],[仕入先]],$E$3:E58,商品マスタ[[#This Row],[商品名]]) = 1, 1,0) | G58: =TEXT(SUMIF($C$3:C58,商品マスタ[[#This Row],[仕入先]],$F$3:F58), "0000") | I58: 12×6 | J58: 72 | L58: 163 | M58: 45953 | N58: 260 | O58: =IF(COUNT(商品マスタ[[#This Row],[参考上代 （税込)]]) > 0, (商品マスタ[[#This Row],[参考上代 （税込)]]-商品マスタ[[#This Row],[国内定価 （15％）]])/(商品マスタ[[#This Row],[参考上代 （税込)]]/1.08), "") | P58: 0.1 | Q58: =商品マスタ[[#This Row],[仕入 単価]]*商品マスタ[[#This Row],[標準国内送料率]] | S58: =IF(ISBLANK(商品マスタ[[#This Row],[実績 国内送料]]),商品マスタ[[#This Row],[標準国内送料]],) | T58: =商品マスタ[[#This Row],[仕入 単価]]+商品マスタ[[#This Row],[国内送料]] | U58: =ROUNDUP(商品マスタ[[#This Row],[仕入単価+国内送料]]/0.8,-1) | V58: =商品マスタ[[#This Row],[海外定価 （20％）]]-商品マスタ[[#This Row],[仕入単価+国内送料]] | W58: =ROUNDUP(商品マスタ[[#This Row],[仕入単価+国内送料]]/0.85,-1) | X58: =商品マスタ[[#This Row],[国内定価 （15％）]]-商品マスタ[[#This Row],[仕入単価+国内送料]] | Z58: 180日 | AA58: 常温 | AB58: 5日 | AC58: 4901944007116 | AD58: 原材料のもち米、砂糖、生飴、オブラートは北海道産を使用しています。 | AF58: 〇
A59: 菓子 | B59: 和菓子 | C59: 谷田製菓 | D59: ="PRD_SNJ_"& _xlfn.XLOOKUP(商品マスタ[[#This Row],[仕入先]],テーブル1[仕入先名],テーブル1[仕入先コード],"XXX",0,1)& "_"& 商品マスタ[[#This Row],[シリアル]]& "_"& TEXT(COUNTIFS(商品マスタ!$C$3:C59,商品マスタ[[#This Row],[仕入先]],商品マスタ!$E$3:E59,商品マスタ[[#This Row],[商品名]]), "00") | E59: ファイターズきびだんごミルク味98ｇ | F59: =IF(COUNTIFS($C$3:C59,商品マスタ[[#This Row],[仕入先]],$E$3:E59,商品マスタ[[#This Row],[商品名]]) = 1, 1,0) | G59: =TEXT(SUMIF($C$3:C59,商品マスタ[[#This Row],[仕入先]],$F$3:F59), "0000") | I59: 12×6 | J59: 72 | L59: 163 | M59: 45953 | N59: 260 | O59: =IF(COUNT(商品マスタ[[#This Row],[参考上代 （税込)]]) > 0, (商品マスタ[[#This Row],[参考上代 （税込)]]-商品マスタ[[#This Row],[国内定価 （15％）]])/(商品マスタ[[#This Row],[参考上代 （税込)]]/1.08), "") | P59: 0.1 | Q59: =商品マスタ[[#This Row],[仕入 単価]]*商品マスタ[[#This Row],[標準国内送料率]] | S59: =IF(ISBLANK(商品マスタ[[#This Row],[実績 国内送料]]),商品マスタ[[#This Row],[標準国内送料]],) | T59: =商品マスタ[[#This Row],[仕入 単価]]+商品マスタ[[#This Row],[国内送料]] | U59: =ROUNDUP(商品マスタ[[#This Row],[仕入単価+国内送料]]/0.8,-1) | V59: =商品マスタ[[#This Row],[海外定価 （20％）]]-商品マスタ[[#This Row],[仕入単価+国内送料]] | W59: =ROUNDUP(商品マスタ[[#This Row],[仕入単価+国内送料]]/0.85,-1) | X59: =商品マスタ[[#This Row],[国内定価 （15％）]]-商品マスタ[[#This Row],[仕入単価+国内送料]] | Z59: 180日 | AA59: 常温 | AB59: 5日 | AC59: 4901944001114 | AD59: 原材料のもち米、砂糖、生餡、メロン果汁、オブラートが北海道産を使用しています。 | AF59: 〇
A60: 菓子 | B60: 和菓子 | C60: 谷田製菓 | D60: ="PRD_SNJ_"& _xlfn.XLOOKUP(商品マスタ[[#This Row],[仕入先]],テーブル1[仕入先名],テーブル1[仕入先コード],"XXX",0,1)& "_"& 商品マスタ[[#This Row],[シリアル]]& "_"& TEXT(COUNTIFS(商品マスタ!$C$3:C60,商品マスタ[[#This Row],[仕入先]],商品マスタ!$E$3:E60,商品マスタ[[#This Row],[商品名]]), "00") | E60: とうきび餅98ｇ | F60: =IF(COUNTIFS($C$3:C60,商品マスタ[[#This Row],[仕入先]],$E$3:E60,商品マスタ[[#This Row],[商品名]]) = 1, 1,0) | G60: =TEXT(SUMIF($C$3:C60,商品マスタ[[#This Row],[仕入先]],$F$3:F60), "0000") | I60: 12×6 | J60: 72 | L60: 163 | M60: 45953 | N60: 260 | O60: =IF(COUNT(商品マスタ[[#This Row],[参考上代 （税込)]]) > 0, (商品マスタ[[#This Row],[参考上代 （税込)]]-商品マスタ[[#This Row],[国内定価 （15％）]])/(商品マスタ[[#This Row],[参考上代 （税込)]]/1.08), "") | P60: 0.1 | Q60: =商品マスタ[[#This Row],[仕入 単価]]*商品マスタ[[#This Row],[標準国内送料率]] | S60: =IF(ISBLANK(商品マスタ[[#This Row],[実績 国内送料]]),商品マスタ[[#This Row],[標準国内送料]],) | T60: =商品マスタ[[#This Row],[仕入 単価]]+商品マスタ[[#This Row],[国内送料]] | U60: =ROUNDUP(商品マスタ[[#This Row],[仕入単価+国内送料]]/0.8,-1) | V60: =商品マスタ[[#This Row],[海外定価 （20％）]]-商品マスタ[[#This Row],[仕入単価+国内送料]] | W60: =ROUNDUP(商品マスタ[[#This Row],[仕入単価+国内送料]]/0.85,-1) | X60: =商品マスタ[[#This Row],[国内定価 （15％）]]-商品マスタ[[#This Row],[仕入単価+国内送料]] | Z60: 180日 | AA60: 常温 | AB60: 5日 | AC60: 4901944001213 | AD60: 原材料のもち米、砂糖、生餡、濃縮牛乳、オブラートが北海道産を使用しています。 | AF60: 〇
A61: 菓子 | B61: 和菓子 | C61: 谷田製菓 | D61: ="PRD_SNJ_"& _xlfn.XLOOKUP(商品マスタ[[#This Row],[仕入先]],テーブル1[仕入先名],テーブル1[仕入先コード],"XXX",0,1)& "_"& 商品マスタ[[#This Row],[シリアル]]& "_"& TEXT(COUNTIFS(商品マスタ!$C$3:C61,商品マスタ[[#This Row],[仕入先]],商品マスタ!$E$3:E61,商品マスタ[[#This Row],[商品名]]), "00") | E61: きびだんごメロン味98ｇ | F61: =IF(COUNTIFS($C$3:C61,商品マスタ[[#This Row],[仕入先]],$E$3:E61,商品マスタ[[#This Row],[商品名]]) = 1, 1,0) | G61: =TEXT(SUMIF($C$3:C61,商品マスタ[[#This Row],[仕入先]],$F$3:F61), "0000") | I61: 12×6 | J61: 72 | L61: 163 | M61: 45953 | N61: 260 | O61: =IF(COUNT(商品マスタ[[#This Row],[参考上代 （税込)]]) > 0, (商品マスタ[[#This Row],[参考上代 （税込)]]-商品マスタ[[#This Row],[国内定価 （15％）]])/(商品マスタ[[#This Row],[参考上代 （税込)]]/1.08), "") | P61: 0.1 | Q61: =商品マスタ[[#This Row],[仕入 単価]]*商品マスタ[[#This Row],[標準国内送料率]] | S61: =IF(ISBLANK(商品マスタ[[#This Row],[実績 国内送料]]),商品マスタ[[#This Row],[標準国内送料]],) | T61: =商品マスタ[[#This Row],[仕入 単価]]+商品マスタ[[#This Row],[国内送料]] | U61: =ROUNDUP(商品マスタ[[#This Row],[仕入単価+国内送料]]/0.8,-1) | V61: =商品マスタ[[#This Row],[海外定価 （20％）]]-商品マスタ[[#This Row],[仕入単価+国内送料]] | W61: =ROUNDUP(商品マスタ[[#This Row],[仕入単価+国内送料]]/0.85,-1) | X61: =商品マスタ[[#This Row],[国内定価 （15％）]]-商品マスタ[[#This Row],[仕入単価+国内送料]] | Z61: 150日 | AA61: 常温 | AB61: 5日 | AC61: 4595644160075 | AD61: 原材料のもち米、砂糖、さつまいも、オブラートが北海道産を使用しています。 | AF61: 〇
A62: 菓子 | B62: 和菓子 | C62: 谷田製菓 | D62: ="PRD_SNJ_"& _xlfn.XLOOKUP(商品マスタ[[#This Row],[仕入先]],テーブル1[仕入先名],テーブル1[仕入先コード],"XXX",0,1)& "_"& 商品マスタ[[#This Row],[シリアル]]& "_"& TEXT(COUNTIFS(商品マスタ!$C$3:C62,商品マスタ[[#This Row],[仕入先]],商品マスタ!$E$3:E62,商品マスタ[[#This Row],[商品名]]), "00") | E62: きびだんごミルク味98ｇ | F62: =IF(COUNTIFS($C$3:C62,商品マスタ[[#This Row],[仕入先]],$E$3:E62,商品マスタ[[#This Row],[商品名]]) = 1, 1,0) | G62: =TEXT(SUMIF($C$3:C62,商品マスタ[[#This Row],[仕入先]],$F$3:F62), "0000") | I62: 12×6 | J62: 72 | L62: 163 | M62: 45953 | N62: 260 | O62: =IF(COUNT(商品マスタ[[#This Row],[参考上代 （税込)]]) > 0, (商品マスタ[[#This Row],[参考上代 （税込)]]-商品マスタ[[#This Row],[国内定価 （15％）]])/(商品マスタ[[#This Row],[参考上代 （税込)]]/1.08), "") | P62: 0.1 | Q62: =商品マスタ[[#This Row],[仕入 単価]]*商品マスタ[[#This Row],[標準国内送料率]] | S62: =IF(ISBLANK(商品マスタ[[#This Row],[実績 国内送料]]),商品マスタ[[#This Row],[標準国内送料]],) | T62: =商品マスタ[[#This Row],[仕入 単価]]+商品マスタ[[#This Row],[国内送料]] | U62: =ROUNDUP(商品マスタ[[#This Row],[仕入単価+国内送料]]/0.8,-1) | V62: =商品マスタ[[#This Row],[海外定価 （20％）]]-商品マスタ[[#This Row],[仕入単価+国内送料]] | W62: =ROUNDUP(商品マスタ[[#This Row],[仕入単価+国内送料]]/0.85,-1) | X62: =商品マスタ[[#This Row],[国内定価 （15％）]]-商品マスタ[[#This Row],[仕入単価+国内送料]] | Z62: 150日 | AA62: 常温 | AB62: 5日 | AC62: 4595644160099 | AD62: 原材料のもち米、砂糖、さつまいも、オブラートが北海道産を使用しています。 | AF62: 〇
A63: 菓子 | B63: 和菓子 | C63: 谷田製菓 | D63: ="PRD_SNJ_"& _xlfn.XLOOKUP(商品マスタ[[#This Row],[仕入先]],テーブル1[仕入先名],テーブル1[仕入先コード],"XXX",0,1)& "_"& 商品マスタ[[#This Row],[シリアル]]& "_"& TEXT(COUNTIFS(商品マスタ!$C$3:C63,商品マスタ[[#This Row],[仕入先]],商品マスタ!$E$3:E63,商品マスタ[[#This Row],[商品名]]), "00") | E63: (合)ベジタボ 由栗いも 畑のキャラメル 30g | F63: =IF(COUNTIFS($C$3:C63,商品マスタ[[#This Row],[仕入先]],$E$3:E63,商品マスタ[[#This Row],[商品名]]) = 1, 1,0) | G63: =TEXT(SUMIF($C$3:C63,商品マスタ[[#This Row],[仕入先]],$F$3:F63), "0000") | I63: 20×16 | J63: 320 | L63: 67.5 | M63: 45953 | N63: 130 | O63: =IF(COUNT(商品マスタ[[#This Row],[参考上代 （税込)]]) > 0, (商品マスタ[[#This Row],[参考上代 （税込)]]-商品マスタ[[#This Row],[国内定価 （15％）]])/(商品マスタ[[#This Row],[参考上代 （税込)]]/1.08), "") | P63: 0.1 | Q63: =商品マスタ[[#This Row],[仕入 単価]]*商品マスタ[[#This Row],[標準国内送料率]] | S63: =IF(ISBLANK(商品マスタ[[#This Row],[実績 国内送料]]),商品マスタ[[#This Row],[標準国内送料]],) | T63: =商品マスタ[[#This Row],[仕入 単価]]+商品マスタ[[#This Row],[国内送料]] | U63: =ROUNDUP(商品マスタ[[#This Row],[仕入単価+国内送料]]/0.8,-1) | V63: =商品マスタ[[#This Row],[海外定価 （20％）]]-商品マスタ[[#This Row],[仕入単価+国内送料]] | W63: =ROUNDUP(商品マスタ[[#This Row],[仕入単価+国内送料]]/0.85,-1) | X63: =商品マスタ[[#This Row],[国内定価 （15％）]]-商品マスタ[[#This Row],[仕入単価+国内送料]] | AF63: 〇
A64: 菓子 | B64: 和菓子 | C64: 谷田製菓 | D64: ="PRD_SNJ_"& _xlfn.XLOOKUP(商品マスタ[[#This Row],[仕入先]],テーブル1[仕入先名],テーブル1[仕入先コード],"XXX",0,1)& "_"& 商品マスタ[[#This Row],[シリアル]]& "_"& TEXT(COUNTIFS(商品マスタ!$C$3:C64,商品マスタ[[#This Row],[仕入先]],商品マスタ!$E$3:E64,商品マスタ[[#This Row],[商品名]]), "00") | E64: (合)ベジタボ 由栗いも 畑のキャラメル 30g×８個入 | F64: =IF(COUNTIFS($C$3:C64,商品マスタ[[#This Row],[仕入先]],$E$3:E64,商品マスタ[[#This Row],[商品名]]) = 1, 1,0) | G64: =TEXT(SUMIF($C$3:C64,商品マスタ[[#This Row],[仕入先]],$F$3:F64), "0000") | I64: 24×1 | J64: 24 | L64: 620 | M64: 45953 | N64: 1080 | O64: =IF(COUNT(商品マスタ[[#This Row],[参考上代 （税込)]]) > 0, (商品マスタ[[#This Row],[参考上代 （税込)]]-商品マスタ[[#This Row],[国内定価 （15％）]])/(商品マスタ[[#This Row],[参考上代 （税込)]]/1.08), "") | P64: 0.1 | Q64: =商品マスタ[[#This Row],[仕入 単価]]*商品マスタ[[#This Row],[標準国内送料率]] | S64: =IF(ISBLANK(商品マスタ[[#This Row],[実績 国内送料]]),商品マスタ[[#This Row],[標準国内送料]],) | T64: =商品マスタ[[#This Row],[仕入 単価]]+商品マスタ[[#This Row],[国内送料]] | U64: =ROUNDUP(商品マスタ[[#This Row],[仕入単価+国内送料]]/0.8,-1) | V64: =商品マスタ[[#This Row],[海外定価 （20％）]]-商品マスタ[[#This Row],[仕入単価+国内送料]] | W64: =ROUNDUP(商品マスタ[[#This Row],[仕入単価+国内送料]]/0.85,-1) | X64: =商品マスタ[[#This Row],[国内定価 （15％）]]-商品マスタ[[#This Row],[仕入単価+国内送料]] | Y64: 0.08 | AF64: 〇
A65: 精肉 | B65: 和牛 | C65: 上田精肉店 | D65: ="PRD_SNJ_"& _xlfn.XLOOKUP(商品マスタ[[#This Row],[仕入先]],テーブル1[仕入先名],テーブル1[仕入先コード],"XXX",0,1)& "_"& 商品マスタ[[#This Row],[シリアル]]& "_"& TEXT(COUNTIFS(商品マスタ!$C$3:C65,商品マスタ[[#This Row],[仕入先]],商品マスタ!$E$3:E65,商品マスタ[[#This Row],[商品名]]), "00") | E65: エゾシカ ロース | F65: =IF(COUNTIFS($C$3:C65,商品マスタ[[#This Row],[仕入先]],$E$3:E65,商品マスタ[[#This Row],[商品名]]) = 1, 1,0) | G65: =TEXT(SUMIF($C$3:C65,商品マスタ[[#This Row],[仕入先]],$F$3:F65), "0000") | H65: kg | I65: 約2-3kg/本 | J65: 1本 | K65: ブロック（カット・スライスなし） | L65: 4675 | M65: 45957 | O65: =IF(COUNT(商品マスタ[[#This Row],[参考上代 （税込)]]) > 0, (商品マスタ[[#This Row],[参考上代 （税込)]]-商品マスタ[[#This Row],[国内定価 （15％）]])/(商品マスタ[[#This Row],[参考上代 （税込)]]/1.08), "") | P65: 0.1 | Q65: =商品マスタ[[#This Row],[仕入 単価]]*商品マスタ[[#This Row],[標準国内送料率]] | S65: =IF(ISBLANK(商品マスタ[[#This Row],[実績 国内送料]]),商品マスタ[[#This Row],[標準国内送料]],) | T65: =商品マスタ[[#This Row],[仕入 単価]]+商品マスタ[[#This Row],[国内送料]] | U65: =ROUNDUP(商品マスタ[[#This Row],[仕入単価+国内送料]]/0.8,-1) | V65: =商品マスタ[[#This Row],[海外定価 （20％）]]-商品マスタ[[#This Row],[仕入単価+国内送料]] | W65: =ROUNDUP(商品マスタ[[#This Row],[仕入単価+国内送料]]/0.85,-1) | X65: =商品マスタ[[#This Row],[国内定価 （15％）]]-商品マスタ[[#This Row],[仕入単価+国内送料]] | Y65: 0.08 | Z65: 別途お見積 | AA65: 冷凍 | AB65: ７日
A66: 精肉 | B66: 和牛 | C66: 上田精肉店 | D66: ="PRD_SNJ_"& _xlfn.XLOOKUP(商品マスタ[[#This Row],[仕入先]],テーブル1[仕入先名],テーブル1[仕入先コード],"XXX",0,1)& "_"& 商品マスタ[[#This Row],[シリアル]]& "_"& TEXT(COUNTIFS(商品マスタ!$C$3:C66,商品マスタ[[#This Row],[仕入先]],商品マスタ!$E$3:E66,商品マスタ[[#This Row],[商品名]]), "00") | E66: エゾシカ ヒレ | F66: =IF(COUNTIFS($C$3:C66,商品マスタ[[#This Row],[仕入先]],$E$3:E66,商品マスタ[[#This Row],[商品名]]) = 1, 1,0) | G66: =TEXT(SUMIF($C$3:C66,商品マスタ[[#This Row],[仕入先]],$F$3:F66), "0000") | H66: kg | I66: 約0.2-0.7kg/本 | J66: 1本 | K66: ブロック（カット・スライスなし） | L66: 5500 | M66: 45957 | O66: =IF(COUNT(商品マスタ[[#This Row],[参考上代 （税込)]]) > 0, (商品マスタ[[#This Row],[参考上代 （税込)]]-商品マスタ[[#This Row],[国内定価 （15％）]])/(商品マスタ[[#This Row],[参考上代 （税込)]]/1.08), "") | P66: 0.1 | Q66: =商品マスタ[[#This Row],[仕入 単価]]*商品マスタ[[#This Row],[標準国内送料率]] | S66: =IF(ISBLANK(商品マスタ[[#This Row],[実績 国内送料]]),商品マスタ[[#This Row],[標準国内送料]],) | T66: =商品マスタ[[#This Row],[仕入 単価]]+商品マスタ[[#This Row],[国内送料]] | U66: =ROUNDUP(商品マスタ[[#This Row],[仕入単価+国内送料]]/0.8,-1) | V66: =商品マスタ[[#This Row],[海外定価 （20％）]]-商品マスタ[[#This Row],[仕入単価+国内送料]] | W66: =ROUNDUP(商品マスタ[[#This Row],[仕入単価+国内送料]]/0.85,-1) | X66: =商品マスタ[[#This Row],[国内定価 （15％）]]-商品マスタ[[#This Row],[仕入単価+国内送料]] | Y66: 0.08 | Z66: 別途お見積 | AA66: 冷凍 | AB66: ７日
A67: 精肉 | B67: 和牛 | C67: 上田精肉店 | D67: ="PRD_SNJ_"& _xlfn.XLOOKUP(商品マスタ[[#This Row],[仕入先]],テーブル1[仕入先名],テーブル1[仕入先コード],"XXX",0,1)& "_"& 商品マスタ[[#This Row],[シリアル]]& "_"& TEXT(COUNTIFS(商品マスタ!$C$3:C67,商品マスタ[[#This Row],[仕入先]],商品マスタ!$E$3:E67,商品マスタ[[#This Row],[商品名]]), "00") | E67: エゾシカ 肩ロース | F67: =IF(COUNTIFS($C$3:C67,商品マスタ[[#This Row],[仕入先]],$E$3:E67,商品マスタ[[#This Row],[商品名]]) = 1, 1,0) | G67: =TEXT(SUMIF($C$3:C67,商品マスタ[[#This Row],[仕入先]],$F$3:F67), "0000") | H67: kg | I67: 約0.5-1.5kg/個 | J67: 1個 | K67: ブロック（カット・スライスなし） | L67: 3600 | M67: 45957 | O67: =IF(COUNT(商品マスタ[[#This Row],[参考上代 （税込)]]) > 0, (商品マスタ[[#This Row],[参考上代 （税込)]]-商品マスタ[[#This Row],[国内定価 （15％）]])/(商品マスタ[[#This Row],[参考上代 （税込)]]/1.08), "") | P67: 0.1 | Q67: =商品マスタ[[#This Row],[仕入 単価]]*商品マスタ[[#This Row],[標準国内送料率]] | S67: =IF(ISBLANK(商品マスタ[[#This Row],[実績 国内送料]]),商品マスタ[[#This Row],[標準国内送料]],) | T67: =商品マスタ[[#This Row],[仕入 単価]]+商品マスタ[[#This Row],[国内送料]] | U67: =ROUNDUP(商品マスタ[[#This Row],[仕入単価+国内送料]]/0.8,-1) | V67: =商品マスタ[[#This Row],[海外定価 （20％）]]-商品マスタ[[#This Row],[仕入単価+国内送料]] | W67: =ROUNDUP(商品マスタ[[#This Row],[仕入単価+国内送料]]/0.85,-1) | X67: =商品マスタ[[#This Row],[国内定価 （15％）]]-商品マスタ[[#This Row],[仕入単価+国内送料]] | Y67: 0.08 | Z67: 別途お見積 | AA67: 冷凍 | AB67: ７日
A68: 精肉 | B68: 和牛 | C68: 上田精肉店 | D68: ="PRD_SNJ_"& _xlfn.XLOOKUP(商品マスタ[[#This Row],[仕入先]],テーブル1[仕入先名],テーブル1[仕入先コード],"XXX",0,1)& "_"& 商品マスタ[[#This Row],[シリアル]]& "_"& TEXT(COUNTIFS(商品マスタ!$C$3:C68,商品マスタ[[#This Row],[仕入先]],商品マスタ!$E$3:E68,商品マスタ[[#This Row],[商品名]]), "00") | E68: エゾシカ 内モモ | F68: =IF(COUNTIFS($C$3:C68,商品マスタ[[#This Row],[仕入先]],$E$3:E68,商品マスタ[[#This Row],[商品名]]) = 1, 1,0) | G68: =TEXT(SUMIF($C$3:C68,商品マスタ[[#This Row],[仕入先]],$F$3:F68), "0000") | H68: kg | I68: 約1.2-2kg/個 | J68: 1個 | K68: ブロック（カット・スライスなし） | L68: 2900 | M68: 45957 | O68: =IF(COUNT(商品マスタ[[#This Row],[参考上代 （税込)]]) > 0, (商品マスタ[[#This Row],[参考上代 （税込)]]-商品マスタ[[#This Row],[国内定価 （15％）]])/(商品マスタ[[#This Row],[参考上代 （税込)]]/1.08), "") | P68: 0.1 | Q68: =商品マスタ[[#This Row],[仕入 単価]]*商品マスタ[[#This Row],[標準国内送料率]] | S68: =IF(ISBLANK(商品マスタ[[#This Row],[実績 国内送料]]),商品マスタ[[#This Row],[標準国内送料]],) | T68: =商品マスタ[[#This Row],[仕入 単価]]+商品マスタ[[#This Row],[国内送料]] | U68: =ROUNDUP(商品マスタ[[#This Row],[仕入単価+国内送料]]/0.8,-1) | V68: =商品マスタ[[#This Row],[海外定価 （20％）]]-商品マスタ[[#This Row],[仕入単価+国内送料]] | W68: =ROUNDUP(商品マスタ[[#This Row],[仕入単価+国内送料]]/0.85,-1) | X68: =商品マスタ[[#This Row],[国内定価 （15％）]]-商品マスタ[[#This Row],[仕入単価+国内送料]] | Y68: 0.08 | Z68: 別途お見積 | AA68: 冷凍 | AB68: ７日
A69: 精肉 | B69: 和牛 | C69: 上田精肉店 | D69: ="PRD_SNJ_"& _xlfn.XLOOKUP(商品マスタ[[#This Row],[仕入先]],テーブル1[仕入先名],テーブル1[仕入先コード],"XXX",0,1)& "_"& 商品マスタ[[#This Row],[シリアル]]& "_"& TEXT(COUNTIFS(商品マスタ!$C$3:C69,商品マスタ[[#This Row],[仕入先]],商品マスタ!$E$3:E69,商品マスタ[[#This Row],[商品名]]), "00") | E69: エゾシカ 外モモ | F69: =IF(COUNTIFS($C$3:C69,商品マスタ[[#This Row],[仕入先]],$E$3:E69,商品マスタ[[#This Row],[商品名]]) = 1, 1,0) | G69: =TEXT(SUMIF($C$3:C69,商品マスタ[[#This Row],[仕入先]],$F$3:F69), "0000") | H69: kg | I69: 約1-2kg/個 | J69: 1個 | K69: ブロック（カット・スライスなし） | L69: 2800 | M69: 45957 | O69: =IF(COUNT(商品マスタ[[#This Row],[参考上代 （税込)]]) > 0, (商品マスタ[[#This Row],[参考上代 （税込)]]-商品マスタ[[#This Row],[国内定価 （15％）]])/(商品マスタ[[#This Row],[参考上代 （税込)]]/1.08), "") | P69: 0.1 | Q69: =商品マスタ[[#This Row],[仕入 単価]]*商品マスタ[[#This Row],[標準国内送料率]] | S69: =IF(ISBLANK(商品マスタ[[#This Row],[実績 国内送料]]),商品マスタ[[#This Row],[標準国内送料]],) | T69: =商品マスタ[[#This Row],[仕入 単価]]+商品マスタ[[#This Row],[国内送料]] | U69: =ROUNDUP(商品マスタ[[#This Row],[仕入単価+国内送料]]/0.8,-1) | V69: =商品マスタ[[#This Row],[海外定価 （20％）]]-商品マスタ[[#This Row],[仕入単価+国内送料]] | W69: =ROUNDUP(商品マスタ[[#This Row],[仕入単価+国内送料]]/0.85,-1) | X69: =商品マスタ[[#This Row],[国内定価 （15％）]]-商品マスタ[[#This Row],[仕入単価+国内送料]] | Y69: 0.08 | Z69: 別途お見積 | AA69: 冷凍 | AB69: ７日
A70: 精肉 | B70: 和牛 | C70: 上田精肉店 | D70: ="PRD_SNJ_"& _xlfn.XLOOKUP(商品マスタ[[#This Row],[仕入先]],テーブル1[仕入先名],テーブル1[仕入先コード],"XXX",0,1)& "_"& 商品マスタ[[#This Row],[シリアル]]& "_"& TEXT(COUNTIFS(商品マスタ!$C$3:C70,商品マスタ[[#This Row],[仕入先]],商品マスタ!$E$3:E70,商品マスタ[[#This Row],[商品名]]), "00") | E70: エゾシカ シンタマ | F70: =IF(COUNTIFS($C$3:C70,商品マスタ[[#This Row],[仕入先]],$E$3:E70,商品マスタ[[#This Row],[商品名]]) = 1, 1,0) | G70: =TEXT(SUMIF($C$3:C70,商品マスタ[[#This Row],[仕入先]],$F$3:F70), "0000") | H70: kg | I70: 約1.3-1.8kg/個 | J70: 1個 | K70: ブロック（カット・スライスなし） | L70: 2800 | M70: 45957 | O70: =IF(COUNT(商品マスタ[[#This Row],[参考上代 （税込)]]) > 0, (商品マスタ[[#This Row],[参考上代 （税込)]]-商品マスタ[[#This Row],[国内定価 （15％）]])/(商品マスタ[[#This Row],[参考上代 （税込)]]/1.08), "") | P70: 0.1 | Q70: =商品マスタ[[#This Row],[仕入 単価]]*商品マスタ[[#This Row],[標準国内送料率]] | S70: =IF(ISBLANK(商品マスタ[[#This Row],[実績 国内送料]]),商品マスタ[[#This Row],[標準国内送料]],) | T70: =商品マスタ[[#This Row],[仕入 単価]]+商品マスタ[[#This Row],[国内送料]] | U70: =ROUNDUP(商品マスタ[[#This Row],[仕入単価+国内送料]]/0.8,-1) | V70: =商品マスタ[[#This Row],[海外定価 （20％）]]-商品マスタ[[#This Row],[仕入単価+国内送料]] | W70: =ROUNDUP(商品マスタ[[#This Row],[仕入単価+国内送料]]/0.85,-1) | X70: =商品マスタ[[#This Row],[国内定価 （15％）]]-商品マスタ[[#This Row],[仕入単価+国内送料]] | Y70: 0.08 | Z70: 別途お見積 | AA70: 冷凍 | AB70: ７日
A71: 精肉 | B71: 和牛 | C71: 上田精肉店 | D71: ="PRD_SNJ_"& _xlfn.XLOOKUP(商品マスタ[[#This Row],[仕入先]],テーブル1[仕入先名],テーブル1[仕入先コード],"XXX",0,1)& "_"& 商品マスタ[[#This Row],[シリアル]]& "_"& TEXT(COUNTIFS(商品マスタ!$C$3:C71,商品マスタ[[#This Row],[仕入先]],商品マスタ!$E$3:E71,商品マスタ[[#This Row],[商品名]]), "00") | E71: エゾシカ ランイチ | F71: =IF(COUNTIFS($C$3:C71,商品マスタ[[#This Row],[仕入先]],$E$3:E71,商品マスタ[[#This Row],[商品名]]) = 1, 1,0) | G71: =TEXT(SUMIF($C$3:C71,商品マスタ[[#This Row],[仕入先]],$F$3:F71), "0000") | H71: kg | I71: 約0.7-1.5kg/個 | J71: 1個 | K71: ブロック（カット・スライスなし） | L71: 2700 | M71: 45957 | O71: =IF(COUNT(商品マスタ[[#This Row],[参考上代 （税込)]]) > 0, (商品マスタ[[#This Row],[参考上代 （税込)]]-商品マスタ[[#This Row],[国内定価 （15％）]])/(商品マスタ[[#This Row],[参考上代 （税込)]]/1.08), "") | P71: 0.1 | Q71: =商品マスタ[[#This Row],[仕入 単価]]*商品マスタ[[#This Row],[標準国内送料率]] | S71: =IF(ISBLANK(商品マスタ[[#This Row],[実績 国内送料]]),商品マスタ[[#This Row],[標準国内送料]],) | T71: =商品マスタ[[#This Row],[仕入 単価]]+商品マスタ[[#This Row],[国内送料]] | U71: =ROUNDUP(商品マスタ[[#This Row],[仕入単価+国内送料]]/0.8,-1) | V71: =商品マスタ[[#This Row],[海外定価 （20％）]]-商品マスタ[[#This Row],[仕入単価+国内送料]] | W71: =ROUNDUP(商品マスタ[[#This Row],[仕入単価+国内送料]]/0.85,-1) | X71: =商品マスタ[[#This Row],[国内定価 （15％）]]-商品マスタ[[#This Row],[仕入単価+国内送料]] | Y71: 0.08 | Z71: 別途お見積 | AA71: 冷凍 | AB71: ７日
A72: 精肉 | B72: 和牛 | C72: 上田精肉店 | D72: ="PRD_SNJ_"& _xlfn.XLOOKUP(商品マスタ[[#This Row],[仕入先]],テーブル1[仕入先名],テーブル1[仕入先コード],"XXX",0,1)& "_"& 商品マスタ[[#This Row],[シリアル]]& "_"& TEXT(COUNTIFS(商品マスタ!$C$3:C72,商品マスタ[[#This Row],[仕入先]],商品マスタ!$E$3:E72,商品マスタ[[#This Row],[商品名]]), "00") | E72: エゾシカ モモ 4パーツセット | F72: =IF(COUNTIFS($C$3:C72,商品マスタ[[#This Row],[仕入先]],$E$3:E72,商品マスタ[[#This Row],[商品名]]) = 1, 1,0) | G72: =TEXT(SUMIF($C$3:C72,商品マスタ[[#This Row],[仕入先]],$F$3:F72), "0000") | H72: kg | I72: 約4-6kg/セット | J72: 1セット | K72: ブロック（カット・スライスなし） | L72: 2700 | M72: 45957 | O72: =IF(COUNT(商品マスタ[[#This Row],[参考上代 （税込)]]) > 0, (商品マスタ[[#This Row],[参考上代 （税込)]]-商品マスタ[[#This Row],[国内定価 （15％）]])/(商品マスタ[[#This Row],[参考上代 （税込)]]/1.08), "") | P72: 0.1 | Q72: =商品マスタ[[#This Row],[仕入 単価]]*商品マスタ[[#This Row],[標準国内送料率]] | S72: =IF(ISBLANK(商品マスタ[[#This Row],[実績 国内送料]]),商品マスタ[[#This Row],[標準国内送料]],) | T72: =商品マスタ[[#This Row],[仕入 単価]]+商品マスタ[[#This Row],[国内送料]] | U72: =ROUNDUP(商品マスタ[[#This Row],[仕入単価+国内送料]]/0.8,-1) | V72: =商品マスタ[[#This Row],[海外定価 （20％）]]-商品マスタ[[#This Row],[仕入単価+国内送料]] | W72: =ROUNDUP(商品マスタ[[#This Row],[仕入単価+国内送料]]/0.85,-1) | X72: =商品マスタ[[#This Row],[国内定価 （15％）]]-商品マスタ[[#This Row],[仕入単価+国内送料]] | Y72: 0.08 | Z72: 別途お見積 | AA72: 冷凍 | AB72: ７日
A73: 精肉 | B73: 和牛 | C73: 上田精肉店 | D73: ="PRD_SNJ_"& _xlfn.XLOOKUP(商品マスタ[[#This Row],[仕入先]],テーブル1[仕入先名],テーブル1[仕入先コード],"XXX",0,1)& "_"& 商品マスタ[[#This Row],[シリアル]]& "_"& TEXT(COUNTIFS(商品マスタ!$C$3:C73,商品マスタ[[#This Row],[仕入先]],商品マスタ!$E$3:E73,商品マスタ[[#This Row],[商品名]]), "00") | E73: エゾシカ スペアリブ | F73: =IF(COUNTIFS($C$3:C73,商品マスタ[[#This Row],[仕入先]],$E$3:E73,商品マスタ[[#This Row],[商品名]]) = 1, 1,0) | G73: =TEXT(SUMIF($C$3:C73,商品マスタ[[#This Row],[仕入先]],$F$3:F73), "0000") | H73: kg | I73: 500g/パック | J73: 1パック | K73: ブロック（カット・スライスなし） | L73: 2000 | M73: 45957 | O73: =IF(COUNT(商品マスタ[[#This Row],[参考上代 （税込)]]) > 0, (商品マスタ[[#This Row],[参考上代 （税込)]]-商品マスタ[[#This Row],[国内定価 （15％）]])/(商品マスタ[[#This Row],[参考上代 （税込)]]/1.08), "") | P73: 0.1 | Q73: =商品マスタ[[#This Row],[仕入 単価]]*商品マスタ[[#This Row],[標準国内送料率]] | S73: =IF(ISBLANK(商品マスタ[[#This Row],[実績 国内送料]]),商品マスタ[[#This Row],[標準国内送料]],) | T73: =商品マスタ[[#This Row],[仕入 単価]]+商品マスタ[[#This Row],[国内送料]] | U73: =ROUNDUP(商品マスタ[[#This Row],[仕入単価+国内送料]]/0.8,-1) | V73: =商品マスタ[[#This Row],[海外定価 （20％）]]-商品マスタ[[#This Row],[仕入単価+国内送料]] | W73: =ROUNDUP(商品マスタ[[#This Row],[仕入単価+国内送料]]/0.85,-1) | X73: =商品マスタ[[#This Row],[国内定価 （15％）]]-商品マスタ[[#This Row],[仕入単価+国内送料]] | Y73: 0.08 | Z73: 別途お見積 | AA73: 冷凍 | AB73: ７日
A74: 精肉 | B74: 和牛 | C74: 上田精肉店 | D74: ="PRD_SNJ_"& _xlfn.XLOOKUP(商品マスタ[[#This Row],[仕入先]],テーブル1[仕入先名],テーブル1[仕入先コード],"XXX",0,1)& "_"& 商品マスタ[[#This Row],[シリアル]]& "_"& TEXT(COUNTIFS(商品マスタ!$C$3:C74,商品マスタ[[#This Row],[仕入先]],商品マスタ!$E$3:E74,商品マスタ[[#This Row],[商品名]]), "00") | E74: エゾシカ バラ | F74: =IF(COUNTIFS($C$3:C74,商品マスタ[[#This Row],[仕入先]],$E$3:E74,商品マスタ[[#This Row],[商品名]]) = 1, 1,0) | G74: =TEXT(SUMIF($C$3:C74,商品マスタ[[#This Row],[仕入先]],$F$3:F74), "0000") | H74: kg | I74: 約1.5-2.5kg/枚 | J74: 1枚 | K74: ブロック（カット・スライスなし） | L74: 2400 | M74: 45957 | O74: =IF(COUNT(商品マスタ[[#This Row],[参考上代 （税込)]]) > 0, (商品マスタ[[#This Row],[参考上代 （税込)]]-商品マスタ[[#This Row],[国内定価 （15％）]])/(商品マスタ[[#This Row],[参考上代 （税込)]]/1.08), "") | P74: 0.1 | Q74: =商品マスタ[[#This Row],[仕入 単価]]*商品マスタ[[#This Row],[標準国内送料率]] | S74: =IF(ISBLANK(商品マスタ[[#This Row],[実績 国内送料]]),商品マスタ[[#This Row],[標準国内送料]],) | T74: =商品マスタ[[#This Row],[仕入 単価]]+商品マスタ[[#This Row],[国内送料]] | U74: =ROUNDUP(商品マスタ[[#This Row],[仕入単価+国内送料]]/0.8,-1) | V74: =商品マスタ[[#This Row],[海外定価 （20％）]]-商品マスタ[[#This Row],[仕入単価+国内送料]] | W74: =ROUNDUP(商品マスタ[[#This Row],[仕入単価+国内送料]]/0.85,-1) | X74: =商品マスタ[[#This Row],[国内定価 （15％）]]-商品マスタ[[#This Row],[仕入単価+国内送料]] | Y74: 0.08 | Z74: 別途お見積 | AA74: 冷凍 | AB74: ７日
A75: 精肉 | B75: 和牛 | C75: 上田精肉店 | D75: ="PRD_SNJ_"& _xlfn.XLOOKUP(商品マスタ[[#This Row],[仕入先]],テーブル1[仕入先名],テーブル1[仕入先コード],"XXX",0,1)& "_"& 商品マスタ[[#This Row],[シリアル]]& "_"& TEXT(COUNTIFS(商品マスタ!$C$3:C75,商品マスタ[[#This Row],[仕入先]],商品マスタ!$E$3:E75,商品マスタ[[#This Row],[商品名]]), "00") | E75: エゾシカ ウデ肉 | F75: =IF(COUNTIFS($C$3:C75,商品マスタ[[#This Row],[仕入先]],$E$3:E75,商品マスタ[[#This Row],[商品名]]) = 1, 1,0) | G75: =TEXT(SUMIF($C$3:C75,商品マスタ[[#This Row],[仕入先]],$F$3:F75), "0000") | H75: kg | I75: 約1-2kg/本 | J75: 1本 | K75: ブロック（カット・スライスなし） | L75: 2000 | M75: 45957 | O75: =IF(COUNT(商品マスタ[[#This Row],[参考上代 （税込)]]) > 0, (商品マスタ[[#This Row],[参考上代 （税込)]]-商品マスタ[[#This Row],[国内定価 （15％）]])/(商品マスタ[[#This Row],[参考上代 （税込)]]/1.08), "") | P75: 0.1 | Q75: =商品マスタ[[#This Row],[仕入 単価]]*商品マスタ[[#This Row],[標準国内送料率]] | S75: =IF(ISBLANK(商品マスタ[[#This Row],[実績 国内送料]]),商品マスタ[[#This Row],[標準国内送料]],) | T75: =商品マスタ[[#This Row],[仕入 単価]]+商品マスタ[[#This Row],[国内送料]] | U75: =ROUNDUP(商品マスタ[[#This Row],[仕入単価+国内送料]]/0.8,-1) | V75: =商品マスタ[[#This Row],[海外定価 （20％）]]-商品マスタ[[#This Row],[仕入単価+国内送料]] | W75: =ROUNDUP(商品マスタ[[#This Row],[仕入単価+国内送料]]/0.85,-1) | X75: =商品マスタ[[#This Row],[国内定価 （15％）]]-商品マスタ[[#This Row],[仕入単価+国内送料]] | Y75: 0.08 | Z75: 別途お見積 | AA75: 冷凍 | AB75: ７日
A76: 精肉 | B76: 和牛 | C76: 上田精肉店 | D76: ="PRD_SNJ_"& _xlfn.XLOOKUP(商品マスタ[[#This Row],[仕入先]],テーブル1[仕入先名],テーブル1[仕入先コード],"XXX",0,1)& "_"& 商品マスタ[[#This Row],[シリアル]]& "_"& TEXT(COUNTIFS(商品マスタ!$C$3:C76,商品マスタ[[#This Row],[仕入先]],商品マスタ!$E$3:E76,商品マスタ[[#This Row],[商品名]]), "00") | E76: エゾシカ 挽き肉 | F76: =IF(COUNTIFS($C$3:C76,商品マスタ[[#This Row],[仕入先]],$E$3:E76,商品マスタ[[#This Row],[商品名]]) = 1, 1,0) | G76: =TEXT(SUMIF($C$3:C76,商品マスタ[[#This Row],[仕入先]],$F$3:F76), "0000") | H76: kg | I76: 500g/パック | J76: 1パック | K76: ブロック（カット・スライスなし） | L76: 2000 | M76: 45957 | O76: =IF(COUNT(商品マスタ[[#This Row],[参考上代 （税込)]]) > 0, (商品マスタ[[#This Row],[参考上代 （税込)]]-商品マスタ[[#This Row],[国内定価 （15％）]])/(商品マスタ[[#This Row],[参考上代 （税込)]]/1.08), "") | P76: 0.1 | Q76: =商品マスタ[[#This Row],[仕入 単価]]*商品マスタ[[#This Row],[標準国内送料率]] | S76: =IF(ISBLANK(商品マスタ[[#This Row],[実績 国内送料]]),商品マスタ[[#This Row],[標準国内送料]],) | T76: =商品マスタ[[#This Row],[仕入 単価]]+商品マスタ[[#This Row],[国内送料]] | U76: =ROUNDUP(商品マスタ[[#This Row],[仕入単価+国内送料]]/0.8,-1) | V76: =商品マスタ[[#This Row],[海外定価 （20％）]]-商品マスタ[[#This Row],[仕入単価+国内送料]] | W76: =ROUNDUP(商品マスタ[[#This Row],[仕入単価+国内送料]]/0.85,-1) | X76: =商品マスタ[[#This Row],[国内定価 （15％）]]-商品マスタ[[#This Row],[仕入単価+国内送料]] | Y76: 0.08 | Z76: 別途お見積 | AA76: 冷凍 | AB76: ７日
... A79: 精肉 | B79: 和牛 | C79: 上田精肉店 | D79: ="PRD_SNJ_"& _xlfn.XLOOKUP(商品マスタ[[#This Row],[仕入先]],テーブル1[仕入先名],テーブル1[仕入先コード],"XXX",0,1)& "_"& 商品マスタ[[#This Row],[シリアル]]& "_"& TEXT(COUNTIFS(商品マスタ!$C$3:C79,商品マスタ[[#This Row],[仕入先]],商品マスタ!$E$3:E79,商品マスタ[[#This Row],[商品名]]), "00") | E79: エゾシカ 骨付きモモ | F79: =IF(COUNTIFS($C$3:C79,商品マスタ[[#This Row],[仕入先]],$E$3:E79,商品マスタ[[#This Row],[商品名]]) = 1, 1,0) | G79: =TEXT(SUMIF($C$3:C79,商品マスタ[[#This Row],[仕入先]],$F$3:F79), "0000") | H79: kg | I79: 約6-10kg/本 | J79: 1本 | K79: ブロック（カット・スライスなし） | L79: 2000 | M79: 45957 | O79: =IF(COUNT(商品マスタ[[#This Row],[参考上代 （税込)]]) > 0, (商品マスタ[[#This Row],[参考上代 （税込)]]-商品マスタ[[#This Row],[国内定価 （15％）]])/(商品マスタ[[#This Row],[参考上代 （税込)]]/1.08), "") | P79: 0.1 | Q79: =商品マスタ[[#This Row],[仕入 単価]]*商品マスタ[[#This Row],[標準国内送料率]] | S79: =IF(ISBLANK(商品マスタ[[#This Row],[実績 国内送料]]),商品マスタ[[#This Row],[標準国内送料]],) | T79: =商品マスタ[[#This Row],[仕入 単価]]+商品マスタ[[#This Row],[国内送料]] | U79: =ROUNDUP(商品マスタ[[#This Row],[仕入単価+国内送料]]/0.8,-1) | V79: =商品マスタ[[#This Row],[海外定価 （20％）]]-商品マスタ[[#This Row],[仕入単価+国内送料]] | W79: =ROUNDUP(商品マスタ[[#This Row],[仕入単価+国内送料]]/0.85,-1) | X79: =商品マスタ[[#This Row],[国内定価 （15％）]]-商品マスタ[[#This Row],[仕入単価+国内送料]] | Y79: 0.08 | Z79: 別途お見積 | AA79: 冷蔵 | AB79: ７日
A80: 精肉 | B80: 和牛 | C80: 上田精肉店 | D80: ="PRD_SNJ_"& _xlfn.XLOOKUP(商品マスタ[[#This Row],[仕入先]],テーブル1[仕入先名],テーブル1[仕入先コード],"XXX",0,1)& "_"& 商品マスタ[[#This Row],[シリアル]]& "_"& TEXT(COUNTIFS(商品マスタ!$C$3:C80,商品マスタ[[#This Row],[仕入先]],商品マスタ!$E$3:E80,商品マスタ[[#This Row],[商品名]]), "00") | E80: エゾシカ 骨付きウデ | F80: =IF(COUNTIFS($C$3:C80,商品マスタ[[#This Row],[仕入先]],$E$3:E80,商品マスタ[[#This Row],[商品名]]) = 1, 1,0) | G80: =TEXT(SUMIF($C$3:C80,商品マスタ[[#This Row],[仕入先]],$F$3:F80), "0000") | H80: kg | I80: 約3-5kg/本 | J80: 1本 | K80: ブロック（カット・スライスなし） | L80: 1700 | M80: 45957 | O80: =IF(COUNT(商品マスタ[[#This Row],[参考上代 （税込)]]) > 0, (商品マスタ[[#This Row],[参考上代 （税込)]]-商品マスタ[[#This Row],[国内定価 （15％）]])/(商品マスタ[[#This Row],[参考上代 （税込)]]/1.08), "") | P80: 0.1 | Q80: =商品マスタ[[#This Row],[仕入 単価]]*商品マスタ[[#This Row],[標準国内送料率]] | S80: =IF(ISBLANK(商品マスタ[[#This Row],[実績 国内送料]]),商品マスタ[[#This Row],[標準国内送料]],) | T80: =商品マスタ[[#This Row],[仕入 単価]]+商品マスタ[[#This Row],[国内送料]] | U80: =ROUNDUP(商品マスタ[[#This Row],[仕入単価+国内送料]]/0.8,-1) | V80: =商品マスタ[[#This Row],[海外定価 （20％）]]-商品マスタ[[#This Row],[仕入単価+国内送料]] | W80: =ROUNDUP(商品マスタ[[#This Row],[仕入単価+国内送料]]/0.85,-1) | X80: =商品マスタ[[#This Row],[国内定価 （15％）]]-商品マスタ[[#This Row],[仕入単価+国内送料]] | Y80: 0.08
A81: 精肉 | B81: 和牛 | C81: 上田精肉店 | D81: ="PRD_SNJ_"& _xlfn.XLOOKUP(商品マスタ[[#This Row],[仕入先]],テーブル1[仕入先名],テーブル1[仕入先コード],"XXX",0,1)& "_"& 商品マスタ[[#This Row],[シリアル]]& "_"& TEXT(COUNTIFS(商品マスタ!$C$3:C81,商品マスタ[[#This Row],[仕入先]],商品マスタ!$E$3:E81,商品マスタ[[#This Row],[商品名]]), "00") | E81: エゾシカ 骨付きバラ | F81: =IF(COUNTIFS($C$3:C81,商品マスタ[[#This Row],[仕入先]],$E$3:E81,商品マスタ[[#This Row],[商品名]]) = 1, 1,0) | G81: =TEXT(SUMIF($C$3:C81,商品マスタ[[#This Row],[仕入先]],$F$3:F81), "0000") | H81: kg | I81: 約2-3kg/枚 | J81: 1枚 | K81: ブロック（カット・スライスなし） | L81: 1800 | M81: 45957 | O81: =IF(COUNT(商品マスタ[[#This Row],[参考上代 （税込)]]) > 0, (商品マスタ[[#This Row],[参考上代 （税込)]]-商品マスタ[[#This Row],[国内定価 （15％）]])/(商品マスタ[[#This Row],[参考上代 （税込)]]/1.08), "") | P81: 0.1 | Q81: =商品マスタ[[#This Row],[仕入 単価]]*商品マスタ[[#This Row],[標準国内送料率]] | S81: =IF(ISBLANK(商品マスタ[[#This Row],[実績 国内送料]]),商品マスタ[[#This Row],[標準国内送料]],) | T81: =商品マスタ[[#This Row],[仕入 単価]]+商品マスタ[[#This Row],[国内送料]] | U81: =ROUNDUP(商品マスタ[[#This Row],[仕入単価+国内送料]]/0.8,-1) | V81: =商品マスタ[[#This Row],[海外定価 （20％）]]-商品マスタ[[#This Row],[仕入単価+国内送料]] | W81: =ROUNDUP(商品マスタ[[#This Row],[仕入単価+国内送料]]/0.85,-1) | X81: =商品マスタ[[#This Row],[国内定価 （15％）]]-商品マスタ[[#This Row],[仕入単価+国内送料]] | Y81: 0.08
A82: 精肉 | B82: 和牛 | C82: 上田精肉店 | D82: ="PRD_SNJ_"& _xlfn.XLOOKUP(商品マスタ[[#This Row],[仕入先]],テーブル1[仕入先名],テーブル1[仕入先コード],"XXX",0,1)& "_"& 商品マスタ[[#This Row],[シリアル]]& "_"& TEXT(COUNTIFS(商品マスタ!$C$3:C82,商品マスタ[[#This Row],[仕入先]],商品マスタ!$E$3:E82,商品マスタ[[#This Row],[商品名]]), "00") | E82: エゾシカ バラ付きサドル | F82: =IF(COUNTIFS($C$3:C82,商品マスタ[[#This Row],[仕入先]],$E$3:E82,商品マスタ[[#This Row],[商品名]]) = 1, 1,0) | G82: =TEXT(SUMIF($C$3:C82,商品マスタ[[#This Row],[仕入先]],$F$3:F82), "0000") | H82: kg | I82: 約7-12kg/本 | J82: 1本 | K82: ブロック（カット・スライスなし） | L82: 3400 | M82: 45957 | O82: =IF(COUNT(商品マスタ[[#This Row],[参考上代 （税込)]]) > 0, (商品マスタ[[#This Row],[参考上代 （税込)]]-商品マスタ[[#This Row],[国内定価 （15％）]])/(商品マスタ[[#This Row],[参考上代 （税込)]]/1.08), "") | P82: 0.1 | Q82: =商品マスタ[[#This Row],[仕入 単価]]*商品マスタ[[#This Row],[標準国内送料率]] | S82: =IF(ISBLANK(商品マスタ[[#This Row],[実績 国内送料]]),商品マスタ[[#This Row],[標準国内送料]],) | T82: =商品マスタ[[#This Row],[仕入 単価]]+商品マスタ[[#This Row],[国内送料]] | U82: =ROUNDUP(商品マスタ[[#This Row],[仕入単価+国内送料]]/0.8,-1) | V82: =商品マスタ[[#This Row],[海外定価 （20％）]]-商品マスタ[[#This Row],[仕入単価+国内送料]] | W82: =ROUNDUP(商品マスタ[[#This Row],[仕入単価+国内送料]]/0.85,-1) | X82: =商品マスタ[[#This Row],[国内定価 （15％）]]-商品マスタ[[#This Row],[仕入単価+国内送料]] | Y82: 0.08
A83: 精肉 | B83: 和牛 | C83: 上田精肉店 | D83: ="PRD_SNJ_"& _xlfn.XLOOKUP(商品マスタ[[#This Row],[仕入先]],テーブル1[仕入先名],テーブル1[仕入先コード],"XXX",0,1)& "_"& 商品マスタ[[#This Row],[シリアル]]& "_"& TEXT(COUNTIFS(商品マスタ!$C$3:C83,商品マスタ[[#This Row],[仕入先]],商品マスタ!$E$3:E83,商品マスタ[[#This Row],[商品名]]), "00") | E83: エゾシカ サドル | F83: =IF(COUNTIFS($C$3:C83,商品マスタ[[#This Row],[仕入先]],$E$3:E83,商品マスタ[[#This Row],[商品名]]) = 1, 1,0) | G83: =TEXT(SUMIF($C$3:C83,商品マスタ[[#This Row],[仕入先]],$F$3:F83), "0000") | H83: kg | I83: 約6-10kg/本 | J83: 1本 | K83: ブロック（カット・スライスなし） | L83: 3800 | M83: 45957 | O83: =IF(COUNT(商品マスタ[[#This Row],[参考上代 （税込)]]) > 0, (商品マスタ[[#This Row],[参考上代 （税込)]]-商品マスタ[[#This Row],[国内定価 （15％）]])/(商品マスタ[[#This Row],[参考上代 （税込)]]/1.08), "") | P83: 0.1 | Q83: =商品マスタ[[#This Row],[仕入 単価]]*商品マスタ[[#This Row],[標準国内送料率]] | S83: =IF(ISBLANK(商品マスタ[[#This Row],[実績 国内送料]]),商品マスタ[[#This Row],[標準国内送料]],) | T83: =商品マスタ[[#This Row],[仕入 単価]]+商品マスタ[[#This Row],[国内送料]] | U83: =ROUNDUP(商品マスタ[[#This Row],[仕入単価+国内送料]]/0.8,-1) | V83: =商品マスタ[[#This Row],[海外定価 （20％）]]-商品マスタ[[#This Row],[仕入単価+国内送料]] | W83: =ROUNDUP(商品マスタ[[#This Row],[仕入単価+国内送料]]/0.85,-1) | X83: =商品マスタ[[#This Row],[国内定価 （15％）]]-商品マスタ[[#This Row],[仕入単価+国内送料]] | Y83: 0.08
A84: 精肉 | B84: 和牛 | C84: 上田精肉店 | D84: ="PRD_SNJ_"& _xlfn.XLOOKUP(商品マスタ[[#This Row],[仕入先]],テーブル1[仕入先名],テーブル1[仕入先コード],"XXX",0,1)& "_"& 商品マスタ[[#This Row],[シリアル]]& "_"& TEXT(COUNTIFS(商品マスタ!$C$3:C84,商品マスタ[[#This Row],[仕入先]],商品マスタ!$E$3:E84,商品マスタ[[#This Row],[商品名]]), "00") | E84: エゾシカ 枝肉（半頭） | F84: =IF(COUNTIFS($C$3:C84,商品マスタ[[#This Row],[仕入先]],$E$3:E84,商品マスタ[[#This Row],[商品名]]) = 1, 1,0) | G84: =TEXT(SUMIF($C$3:C84,商品マスタ[[#This Row],[仕入先]],$F$3:F84), "0000") | H84: kg | I84: 約18-25kg/セット | J84: 1セット | K84: 背割半身 | L84: 1350 | M84: 45957 | O84: =IF(COUNT(商品マスタ[[#This Row],[参考上代 （税込)]]) > 0, (商品マスタ[[#This Row],[参考上代 （税込)]]-商品マスタ[[#This Row],[国内定価 （15％）]])/(商品マスタ[[#This Row],[参考上代 （税込)]]/1.08), "") | P84: 0.1 | Q84: =商品マスタ[[#This Row],[仕入 単価]]*商品マスタ[[#This Row],[標準国内送料率]] | S84: =IF(ISBLANK(商品マスタ[[#This Row],[実績 国内送料]]),商品マスタ[[#This Row],[標準国内送料]],) | T84: =商品マスタ[[#This Row],[仕入 単価]]+商品マスタ[[#This Row],[国内送料]] | U84: =ROUNDUP(商品マスタ[[#This Row],[仕入単価+国内送料]]/0.8,-1) | V84: =商品マスタ[[#This Row],[海外定価 （20％）]]-商品マスタ[[#This Row],[仕入単価+国内送料]] | W84: =ROUNDUP(商品マスタ[[#This Row],[仕入単価+国内送料]]/0.85,-1) | X84: =商品マスタ[[#This Row],[国内定価 （15％）]]-商品マスタ[[#This Row],[仕入単価+国内送料]] | Y84: 0.08
A85: 精肉 | B85: 和牛 | C85: 上田精肉店 | D85: ="PRD_SNJ_"& _xlfn.XLOOKUP(商品マスタ[[#This Row],[仕入先]],テーブル1[仕入先名],テーブル1[仕入先コード],"XXX",0,1)& "_"& 商品マスタ[[#This Row],[シリアル]]& "_"& TEXT(COUNTIFS(商品マスタ!$C$3:C85,商品マスタ[[#This Row],[仕入先]],商品マスタ!$E$3:E85,商品マスタ[[#This Row],[商品名]]), "00") | E85: エゾシカ 子鹿半頭セット | F85: =IF(COUNTIFS($C$3:C85,商品マスタ[[#This Row],[仕入先]],$E$3:E85,商品マスタ[[#This Row],[商品名]]) = 1, 1,0) | G85: =TEXT(SUMIF($C$3:C85,商品マスタ[[#This Row],[仕入先]],$F$3:F85), "0000") | H85: kg | I85: 約5-7kg/セット | J85: 1セット | K85: 背割半身 | L85: 3000 | M85: 45957 | O85: =IF(COUNT(商品マスタ[[#This Row],[参考上代 （税込)]]) > 0, (商品マスタ[[#This Row],[参考上代 （税込)]]-商品マスタ[[#This Row],[国内定価 （15％）]])/(商品マスタ[[#This Row],[参考上代 （税込)]]/1.08), "") | P85: 0.1 | Q85: =商品マスタ[[#This Row],[仕入 単価]]*商品マスタ[[#This Row],[標準国内送料率]] | S85: =IF(ISBLANK(商品マスタ[[#This Row],[実績 国内送料]]),商品マスタ[[#This Row],[標準国内送料]],) | T85: =商品マスタ[[#This Row],[仕入 単価]]+商品マスタ[[#This Row],[国内送料]] | U85: =ROUNDUP(商品マスタ[[#This Row],[仕入単価+国内送料]]/0.8,-1) | V85: =商品マスタ[[#This Row],[海外定価 （20％）]]-商品マスタ[[#This Row],[仕入単価+国内送料]] | W85: =ROUNDUP(商品マスタ[[#This Row],[仕入単価+国内送料]]/0.85,-1) | X85: =商品マスタ[[#This Row],[国内定価 （15％）]]-商品マスタ[[#This Row],[仕入単価+国内送料]] | Y85: 0.08
A86: 精肉 | B86: 和牛 | C86: 上田精肉店 | D86: ="PRD_SNJ_"& _xlfn.XLOOKUP(商品マスタ[[#This Row],[仕入先]],テーブル1[仕入先名],テーブル1[仕入先コード],"XXX",0,1)& "_"& 商品マスタ[[#This Row],[シリアル]]& "_"& TEXT(COUNTIFS(商品マスタ!$C$3:C86,商品マスタ[[#This Row],[仕入先]],商品マスタ!$E$3:E86,商品マスタ[[#This Row],[商品名]]), "00") | E86: エゾシカ トリミング | F86: =IF(COUNTIFS($C$3:C86,商品マスタ[[#This Row],[仕入先]],$E$3:E86,商品マスタ[[#This Row],[商品名]]) = 1, 1,0) | G86: =TEXT(SUMIF($C$3:C86,商品マスタ[[#This Row],[仕入先]],$F$3:F86), "0000") | H86: kg | I86: 15kg/ケース | J86: 1ケース | K86: スジ・脂等 | L86: 1400 | M86: 45957 | O86: =IF(COUNT(商品マスタ[[#This Row],[参考上代 （税込)]]) > 0, (商品マスタ[[#This Row],[参考上代 （税込)]]-商品マスタ[[#This Row],[国内定価 （15％）]])/(商品マスタ[[#This Row],[参考上代 （税込)]]/1.08), "") | P86: 0.1 | Q86: =商品マスタ[[#This Row],[仕入 単価]]*商品マスタ[[#This Row],[標準国内送料率]] | S86: =IF(ISBLANK(商品マスタ[[#This Row],[実績 国内送料]]),商品マスタ[[#This Row],[標準国内送料]],) | T86: =商品マスタ[[#This Row],[仕入 単価]]+商品マスタ[[#This Row],[国内送料]] | U86: =ROUNDUP(商品マスタ[[#This Row],[仕入単価+国内送料]]/0.8,-1) | V86: =商品マスタ[[#This Row],[海外定価 （20％）]]-商品マスタ[[#This Row],[仕入単価+国内送料]] | W86: =ROUNDUP(商品マスタ[[#This Row],[仕入単価+国内送料]]/0.85,-1) | X86: =商品マスタ[[#This Row],[国内定価 （15％）]]-商品マスタ[[#This Row],[仕入単価+国内送料]] | Y86: 0.08
A87: 精肉 | B87: 和牛 | C87: 上田精肉店 | D87: ="PRD_SNJ_"& _xlfn.XLOOKUP(商品マスタ[[#This Row],[仕入先]],テーブル1[仕入先名],テーブル1[仕入先コード],"XXX",0,1)& "_"& 商品マスタ[[#This Row],[シリアル]]& "_"& TEXT(COUNTIFS(商品マスタ!$C$3:C87,商品マスタ[[#This Row],[仕入先]],商品マスタ!$E$3:E87,商品マスタ[[#This Row],[商品名]]), "00") | E87: エゾシカ スネ肉 | F87: =IF(COUNTIFS($C$3:C87,商品マスタ[[#This Row],[仕入先]],$E$3:E87,商品マスタ[[#This Row],[商品名]]) = 1, 1,0) | G87: =TEXT(SUMIF($C$3:C87,商品マスタ[[#This Row],[仕入先]],$F$3:F87), "0000") | H87: kg | I87: 10kg/ケース | J87: 1ケース | K87: スジ肉 | L87: 1100 | M87: 45957 | O87: =IF(COUNT(商品マスタ[[#This Row],[参考上代 （税込)]]) > 0, (商品マスタ[[#This Row],[参考上代 （税込)]]-商品マスタ[[#This Row],[国内定価 （15％）]])/(商品マスタ[[#This Row],[参考上代 （税込)]]/1.08), "") | P87: 0.1 | Q87: =商品マスタ[[#This Row],[仕入 単価]]*商品マスタ[[#This Row],[標準国内送料率]] | S87: =IF(ISBLANK(商品マスタ[[#This Row],[実績 国内送料]]),商品マスタ[[#This Row],[標準国内送料]],) | T87: =商品マスタ[[#This Row],[仕入 単価]]+商品マスタ[[#This Row],[国内送料]] | U87: =ROUNDUP(商品マスタ[[#This Row],[仕入単価+国内送料]]/0.8,-1) | V87: =商品マスタ[[#This Row],[海外定価 （20％）]]-商品マスタ[[#This Row],[仕入単価+国内送料]] | W87: =ROUNDUP(商品マスタ[[#This Row],[仕入単価+国内送料]]/0.85,-1) | X87: =商品マスタ[[#This Row],[国内定価 （15％）]]-商品マスタ[[#This Row],[仕入単価+国内送料]] | Y87: 0.08
A88: 精肉 | B88: 和牛 | C88: 上田精肉店 | D88: ="PRD_SNJ_"& _xlfn.XLOOKUP(商品マスタ[[#This Row],[仕入先]],テーブル1[仕入先名],テーブル1[仕入先コード],"XXX",0,1)& "_"& 商品マスタ[[#This Row],[シリアル]]& "_"& TEXT(COUNTIFS(商品マスタ!$C$3:C88,商品マスタ[[#This Row],[仕入先]],商品マスタ!$E$3:E88,商品マスタ[[#This Row],[商品名]]), "00") | E88: エゾシカ 丸骨 | F88: =IF(COUNTIFS($C$3:C88,商品マスタ[[#This Row],[仕入先]],$E$3:E88,商品マスタ[[#This Row],[商品名]]) = 1, 1,0) | G88: =TEXT(SUMIF($C$3:C88,商品マスタ[[#This Row],[仕入先]],$F$3:F88), "0000") | H88: kg | I88: 15kg/ケース | J88: 1ケース | K88: 骨 | L88: 200 | M88: 45957 | O88: =IF(COUNT(商品マスタ[[#This Row],[参考上代 （税込)]]) > 0, (商品マスタ[[#This Row],[参考上代 （税込)]]-商品マスタ[[#This Row],[国内定価 （15％）]])/(商品マスタ[[#This Row],[参考上代 （税込)]]/1.08), "") | P88: 0.1 | Q88: =商品マスタ[[#This Row],[仕入 単価]]*商品マスタ[[#This Row],[標準国内送料率]] | S88: =IF(ISBLANK(商品マスタ[[#This Row],[実績 国内送料]]),商品マスタ[[#This Row],[標準国内送料]],) | T88: =商品マスタ[[#This Row],[仕入 単価]]+商品マスタ[[#This Row],[国内送料]] | U88: =ROUNDUP(商品マスタ[[#This Row],[仕入単価+国内送料]]/0.8,-1) | V88: =商品マスタ[[#This Row],[海外定価 （20％）]]-商品マスタ[[#This Row],[仕入単価+国内送料]] | W88: =ROUNDUP(商品マスタ[[#This Row],[仕入単価+国内送料]]/0.85,-1) | X88: =商品マスタ[[#This Row],[国内定価 （15％）]]-商品マスタ[[#This Row],[仕入単価+国内送料]] | Y88: 0.08
A89: 精肉 | B89: 和牛 | C89: 上田精肉店 | D89: ="PRD_SNJ_"& _xlfn.XLOOKUP(商品マスタ[[#This Row],[仕入先]],テーブル1[仕入先名],テーブル1[仕入先コード],"XXX",0,1)& "_"& 商品マスタ[[#This Row],[シリアル]]& "_"& TEXT(COUNTIFS(商品マスタ!$C$3:C89,商品マスタ[[#This Row],[仕入先]],商品マスタ!$E$3:E89,商品マスタ[[#This Row],[商品名]]), "00") | E89: エゾシカ 旨味噌ジンギスカン | F89: =IF(COUNTIFS($C$3:C89,商品マスタ[[#This Row],[仕入先]],$E$3:E89,商品マスタ[[#This Row],[商品名]]) = 1, 1,0) | G89: =TEXT(SUMIF($C$3:C89,商品マスタ[[#This Row],[仕入先]],$F$3:F89), "0000") | H89: パック | I89: 500g/パック | J89: 1ケース | K89: 1ケース20個入 | L89: 1355 | M89: 45957 | O89: =IF(COUNT(商品マスタ[[#This Row],[参考上代 （税込)]]) > 0, (商品マスタ[[#This Row],[参考上代 （税込)]]-商品マスタ[[#This Row],[国内定価 （15％）]])/(商品マスタ[[#This Row],[参考上代 （税込)]]/1.08), "") | P89: 0.1 | Q89: =商品マスタ[[#This Row],[仕入 単価]]*商品マスタ[[#This Row],[標準国内送料率]] | S89: =IF(ISBLANK(商品マスタ[[#This Row],[実績 国内送料]]),商品マスタ[[#This Row],[標準国内送料]],) | T89: =商品マスタ[[#This Row],[仕入 単価]]+商品マスタ[[#This Row],[国内送料]] | U89: =ROUNDUP(商品マスタ[[#This Row],[仕入単価+国内送料]]/0.8,-1) | V89: =商品マスタ[[#This Row],[海外定価 （20％）]]-商品マスタ[[#This Row],[仕入単価+国内送料]] | W89: =ROUNDUP(商品マスタ[[#This Row],[仕入単価+国内送料]]/0.85,-1) | X89: =商品マスタ[[#This Row],[国内定価 （15％）]]-商品マスタ[[#This Row],[仕入単価+国内送料]] | Y89: 0.08
A90: 精肉 | B90: 和牛 | C90: 上田精肉店 | D90: ="PRD_SNJ_"& _xlfn.XLOOKUP(商品マスタ[[#This Row],[仕入先]],テーブル1[仕入先名],テーブル1[仕入先コード],"XXX",0,1)& "_"& 商品マスタ[[#This Row],[シリアル]]& "_"& TEXT(COUNTIFS(商品マスタ!$C$3:C90,商品マスタ[[#This Row],[仕入先]],商品マスタ!$E$3:E90,商品マスタ[[#This Row],[商品名]]), "00") | E90: エゾシカ プレミアムジンギスカン（極） | F90: =IF(COUNTIFS($C$3:C90,商品マスタ[[#This Row],[仕入先]],$E$3:E90,商品マスタ[[#This Row],[商品名]]) = 1, 1,0) | G90: =TEXT(SUMIF($C$3:C90,商品マスタ[[#This Row],[仕入先]],$F$3:F90), "0000") | H90: パック | I90: 500g/パック | J90: 1ケース | K90: 1ケース20個入 | L90: 1355 | M90: 45957 | O90: =IF(COUNT(商品マスタ[[#This Row],[参考上代 （税込)]]) > 0, (商品マスタ[[#This Row],[参考上代 （税込)]]-商品マスタ[[#This Row],[国内定価 （15％）]])/(商品マスタ[[#This Row],[参考上代 （税込)]]/1.08), "") | P90: 0.1 | Q90: =商品マスタ[[#This Row],[仕入 単価]]*商品マスタ[[#This Row],[標準国内送料率]] | S90: =IF(ISBLANK(商品マスタ[[#This Row],[実績 国内送料]]),商品マスタ[[#This Row],[標準国内送料]],) | T90: =商品マスタ[[#This Row],[仕入 単価]]+商品マスタ[[#This Row],[国内送料]] | U90: =ROUNDUP(商品マスタ[[#This Row],[仕入単価+国内送料]]/0.8,-1) | V90: =商品マスタ[[#This Row],[海外定価 （20％）]]-商品マスタ[[#This Row],[仕入単価+国内送料]] | W90: =ROUNDUP(商品マスタ[[#This Row],[仕入単価+国内送料]]/0.85,-1) | X90: =商品マスタ[[#This Row],[国内定価 （15％）]]-商品マスタ[[#This Row],[仕入単価+国内送料]] | Y90: 0.08
A91: 精肉 | B91: 和牛 | C91: 上田精肉店 | D91: ="PRD_SNJ_"& _xlfn.XLOOKUP(商品マスタ[[#This Row],[仕入先]],テーブル1[仕入先名],テーブル1[仕入先コード],"XXX",0,1)& "_"& 商品マスタ[[#This Row],[シリアル]]& "_"& TEXT(COUNTIFS(商品マスタ!$C$3:C91,商品マスタ[[#This Row],[仕入先]],商品マスタ!$E$3:E91,商品マスタ[[#This Row],[商品名]]), "00") | E91: エゾシカ 味付カルビ | F91: =IF(COUNTIFS($C$3:C91,商品マスタ[[#This Row],[仕入先]],$E$3:E91,商品マスタ[[#This Row],[商品名]]) = 1, 1,0) | G91: =TEXT(SUMIF($C$3:C91,商品マスタ[[#This Row],[仕入先]],$F$3:F91), "0000") | H91: パック | I91: 300g/パック | J91: 1ケース | K91: 1ケース30個入 | L91: 800 | M91: 45957 | O91: =IF(COUNT(商品マスタ[[#This Row],[参考上代 （税込)]]) > 0, (商品マスタ[[#This Row],[参考上代 （税込)]]-商品マスタ[[#This Row],[国内定価 （15％）]])/(商品マスタ[[#This Row],[参考上代 （税込)]]/1.08), "") | P91: 0.1 | Q91: =商品マスタ[[#This Row],[仕入 単価]]*商品マスタ[[#This Row],[標準国内送料率]] | S91: =IF(ISBLANK(商品マスタ[[#This Row],[実績 国内送料]]),商品マスタ[[#This Row],[標準国内送料]],) | T91: =商品マスタ[[#This Row],[仕入 単価]]+商品マスタ[[#This Row],[国内送料]] | U91: =ROUNDUP(商品マスタ[[#This Row],[仕入単価+国内送料]]/0.8,-1) | V91: =商品マスタ[[#This Row],[海外定価 （20％）]]-商品マスタ[[#This Row],[仕入単価+国内送料]] | W91: =ROUNDUP(商品マスタ[[#This Row],[仕入単価+国内送料]]/0.85,-1) | X91: =商品マスタ[[#This Row],[国内定価 （15％）]]-商品マスタ[[#This Row],[仕入単価+国内送料]] | Y91: 0.08
... A272: 水産 | B272: 水産物 | C272: 東しゃこたん漁協 | D272: ="PRD_SNJ_"& _xlfn.XLOOKUP(商品マスタ[[#This Row],[仕入先]],テーブル1[仕入先名],テーブル1[仕入先コード],"XXX",0,1)& "_"& 商品マスタ[[#This Row],[シリアル]]& "_"& TEXT(COUNTIFS(商品マスタ!$C$3:C272,商品マスタ[[#This Row],[仕入先]],商品マスタ!$E$3:E272,商品マスタ[[#This Row],[商品名]]), "00") | E272: えびアイス | F272: =IF(COUNTIFS($C$3:C272,商品マスタ[[#This Row],[仕入先]],$E$3:E272,商品マスタ[[#This Row],[商品名]]) = 1, 1,0) | G272: =TEXT(SUMIF($C$3:C272,商品マスタ[[#This Row],[仕入先]],$F$3:F272), "0000") | H272: パック | I272: 120ml/パック | J272: 2箱 | K272: 1箱24パック入 アイスクリーム | L272: 280 | M272: 45955 | O272: =IF(COUNT(商品マスタ[[#This Row],[参考上代 （税込)]]) > 0, (商品マスタ[[#This Row],[参考上代 （税込)]]-商品マスタ[[#This Row],[国内定価 （15％）]])/(商品マスタ[[#This Row],[参考上代 （税込)]]/1.08), "") | P272: 0.1 | Q272: =商品マスタ[[#This Row],[仕入 単価]]*商品マスタ[[#This Row],[標準国内送料率]] | S272: =IF(ISBLANK(商品マスタ[[#This Row],[実績 国内送料]]),商品マスタ[[#This Row],[標準国内送料]],) | T272: =商品マスタ[[#This Row],[仕入 単価]]+商品マスタ[[#This Row],[国内送料]] | U272: =ROUNDUP(商品マスタ[[#This Row],[仕入単価+国内送料]]/0.8,-1) | V272: =商品マスタ[[#This Row],[海外定価 （20％）]]-商品マスタ[[#This Row],[仕入単価+国内送料]] | W272: =ROUNDUP(商品マスタ[[#This Row],[仕入単価+国内送料]]/0.85,-1) | X272: =商品マスタ[[#This Row],[国内定価 （15％）]]-商品マスタ[[#This Row],[仕入単価+国内送料]] | Y272: 0.08
A273: 水産 | B273: 水産物 | C273: 三海幸 | D273: ="PRD_SNJ_"& _xlfn.XLOOKUP(商品マスタ[[#This Row],[仕入先]],テーブル1[仕入先名],テーブル1[仕入先コード],"XXX",0,1)& "_"& 商品マスタ[[#This Row],[シリアル]]& "_"& TEXT(COUNTIFS(商品マスタ!$C$3:C273,商品マスタ[[#This Row],[仕入先]],商品マスタ!$E$3:E273,商品マスタ[[#This Row],[商品名]]), "00") | E273: がっつりタコ風味のおつまみイカ | F273: =IF(COUNTIFS($C$3:C273,商品マスタ[[#This Row],[仕入先]],$E$3:E273,商品マスタ[[#This Row],[商品名]]) = 1, 1,0) | G273: =TEXT(SUMIF($C$3:C273,商品マスタ[[#This Row],[仕入先]],$F$3:F273), "0000") | H273: 個 | L273: 300 | O273: =IF(COUNT(商品マスタ[[#This Row],[参考上代 （税込)]]) > 0, (商品マスタ[[#This Row],[参考上代 （税込)]]-商品マスタ[[#This Row],[国内定価 （15％）]])/(商品マスタ[[#This Row],[参考上代 （税込)]]/1.08), "") | P273: 0.1 | Q273: =商品マスタ[[#This Row],[仕入 単価]]*商品マスタ[[#This Row],[標準国内送料率]] | S273: =IF(ISBLANK(商品マスタ[[#This Row],[実績 国内送料]]),商品マスタ[[#This Row],[標準国内送料]],) | T273: =商品マスタ[[#This Row],[仕入 単価]]+商品マスタ[[#This Row],[国内送料]] | U273: =ROUNDUP(商品マスタ[[#This Row],[仕入単価+国内送料]]/0.8,-1) | V273: =商品マスタ[[#This Row],[海外定価 （20％）]]-商品マスタ[[#This Row],[仕入単価+国内送料]] | W273: =ROUNDUP(商品マスタ[[#This Row],[仕入単価+国内送料]]/0.85,-1) | X273: =商品マスタ[[#This Row],[国内定価 （15％）]]-商品マスタ[[#This Row],[仕入単価+国内送料]] | Y273: 0.08
A274: 水産 | B274: 水産物 | C274: 三海幸 | D274: ="PRD_SNJ_"& _xlfn.XLOOKUP(商品マスタ[[#This Row],[仕入先]],テーブル1[仕入先名],テーブル1[仕入先コード],"XXX",0,1)& "_"& 商品マスタ[[#This Row],[シリアル]]& "_"& TEXT(COUNTIFS(商品マスタ!$C$3:C274,商品マスタ[[#This Row],[仕入先]],商品マスタ!$E$3:E274,商品マスタ[[#This Row],[商品名]]), "00") | E274: がっつり黒胡椒の北海道鮭とば | F274: =IF(COUNTIFS($C$3:C274,商品マスタ[[#This Row],[仕入先]],$E$3:E274,商品マスタ[[#This Row],[商品名]]) = 1, 1,0) | G274: =TEXT(SUMIF($C$3:C274,商品マスタ[[#This Row],[仕入先]],$F$3:F274), "0000") | H274: 個 | L274: 360 | O274: =IF(COUNT(商品マスタ[[#This Row],[参考上代 （税込)]]) > 0, (商品マスタ[[#This Row],[参考上代 （税込)]]-商品マスタ[[#This Row],[国内定価 （15％）]])/(商品マスタ[[#This Row],[参考上代 （税込)]]/1.08), "") | P274: 0.1 | Q274: =商品マスタ[[#This Row],[仕入 単価]]*商品マスタ[[#This Row],[標準国内送料率]] | S274: =IF(ISBLANK(商品マスタ[[#This Row],[実績 国内送料]]),商品マスタ[[#This Row],[標準国内送料]],) | T274: =商品マスタ[[#This Row],[仕入 単価]]+商品マスタ[[#This Row],[国内送料]] | U274: =ROUNDUP(商品マスタ[[#This Row],[仕入単価+国内送料]]/0.8,-1) | V274: =商品マスタ[[#This Row],[海外定価 （20％）]]-商品マスタ[[#This Row],[仕入単価+国内送料]] | W274: =ROUNDUP(商品マスタ[[#This Row],[仕入単価+国内送料]]/0.85,-1) | X274: =商品マスタ[[#This Row],[国内定価 （15％）]]-商品マスタ[[#This Row],[仕入単価+国内送料]] | Y274: 0.08
A275: 水産 | B275: 水産物 | C275: 三海幸 | D275: ="PRD_SNJ_"& _xlfn.XLOOKUP(商品マスタ[[#This Row],[仕入先]],テーブル1[仕入先名],テーブル1[仕入先コード],"XXX",0,1)& "_"& 商品マスタ[[#This Row],[シリアル]]& "_"& TEXT(COUNTIFS(商品マスタ!$C$3:C275,商品マスタ[[#This Row],[仕入先]],商品マスタ!$E$3:E275,商品マスタ[[#This Row],[商品名]]), "00") | E275: がっつりチーズのやわらかイカ | F275: =IF(COUNTIFS($C$3:C275,商品マスタ[[#This Row],[仕入先]],$E$3:E275,商品マスタ[[#This Row],[商品名]]) = 1, 1,0) | G275: =TEXT(SUMIF($C$3:C275,商品マスタ[[#This Row],[仕入先]],$F$3:F275), "0000") | H275: 個 | L275: 300 | O275: =IF(COUNT(商品マスタ[[#This Row],[参考上代 （税込)]]) > 0, (商品マスタ[[#This Row],[参考上代 （税込)]]-商品マスタ[[#This Row],[国内定価 （15％）]])/(商品マスタ[[#This Row],[参考上代 （税込)]]/1.08), "") | P275: 0.1 | Q275: =商品マスタ[[#This Row],[仕入 単価]]*商品マスタ[[#This Row],[標準国内送料率]] | S275: =IF(ISBLANK(商品マスタ[[#This Row],[実績 国内送料]]),商品マスタ[[#This Row],[標準国内送料]],) | T275: =商品マスタ[[#This Row],[仕入 単価]]+商品マスタ[[#This Row],[国内送料]] | U275: =ROUNDUP(商品マスタ[[#This Row],[仕入単価+国内送料]]/0.8,-1) | V275: =商品マスタ[[#This Row],[海外定価 （20％）]]-商品マスタ[[#This Row],[仕入単価+国内送料]] | W275: =ROUNDUP(商品マスタ[[#This Row],[仕入単価+国内送料]]/0.85,-1) | X275: =商品マスタ[[#This Row],[国内定価 （15％）]]-商品マスタ[[#This Row],[仕入単価+国内送料]] | Y275: 0.08
A276: 水産 | B276: 水産物 | C276: 佐藤水産 | D276: ="PRD_SNJ_"& _xlfn.XLOOKUP(商品マスタ[[#This Row],[仕入先]],テーブル1[仕入先名],テーブル1[仕入先コード],"XXX",0,1)& "_"& 商品マスタ[[#This Row],[シリアル]]& "_"& TEXT(COUNTIFS(商品マスタ!$C$3:C276,商品マスタ[[#This Row],[仕入先]],商品マスタ!$E$3:E276,商品マスタ[[#This Row],[商品名]]), "00") | E276: サーモンソーセージ | F276: =IF(COUNTIFS($C$3:C276,商品マスタ[[#This Row],[仕入先]],$E$3:E276,商品マスタ[[#This Row],[商品名]]) = 1, 1,0) | G276: =TEXT(SUMIF($C$3:C276,商品マスタ[[#This Row],[仕入先]],$F$3:F276), "0000") | H276: 個 | L276: 120 | O276: =IF(COUNT(商品マスタ[[#This Row],[参考上代 （税込)]]) > 0, (商品マスタ[[#This Row],[参考上代 （税込)]]-商品マスタ[[#This Row],[国内定価 （15％）]])/(商品マスタ[[#This Row],[参考上代 （税込)]]/1.08), "") | P276: 0.1 | Q276: =商品マスタ[[#This Row],[仕入 単価]]*商品マスタ[[#This Row],[標準国内送料率]] | S276: =IF(ISBLANK(商品マスタ[[#This Row],[実績 国内送料]]),商品マスタ[[#This Row],[標準国内送料]],) | T276: =商品マスタ[[#This Row],[仕入 単価]]+商品マスタ[[#This Row],[国内送料]] | U276: =ROUNDUP(商品マスタ[[#This Row],[仕入単価+国内送料]]/0.8,-1) | V276: =商品マスタ[[#This Row],[海外定価 （20％）]]-商品マスタ[[#This Row],[仕入単価+国内送料]] | W276: =ROUNDUP(商品マスタ[[#This Row],[仕入単価+国内送料]]/0.85,-1) | X276: =商品マスタ[[#This Row],[国内定価 （15％）]]-商品マスタ[[#This Row],[仕入単価+国内送料]] | Y276: 0.08
A277: 水産 | B277: 水産物 | C277: 佐藤水産 | D277: ="PRD_SNJ_"& _xlfn.XLOOKUP(商品マスタ[[#This Row],[仕入先]],テーブル1[仕入先名],テーブル1[仕入先コード],"XXX",0,1)& "_"& 商品マスタ[[#This Row],[シリアル]]& "_"& TEXT(COUNTIFS(商品マスタ!$C$3:C277,商品マスタ[[#This Row],[仕入先]],商品マスタ!$E$3:E277,商品マスタ[[#This Row],[商品名]]), "00") | E277: 酒の肴シリーズ鮭ちっぷ | F277: =IF(COUNTIFS($C$3:C277,商品マスタ[[#This Row],[仕入先]],$E$3:E277,商品マスタ[[#This Row],[商品名]]) = 1, 1,0) | G277: =TEXT(SUMIF($C$3:C277,商品マスタ[[#This Row],[仕入先]],$F$3:F277), "0000") | H277: 個 | L277: 300 | O277: =IF(COUNT(商品マスタ[[#This Row],[参考上代 （税込)]]) > 0, (商品マスタ[[#This Row],[参考上代 （税込)]]-商品マスタ[[#This Row],[国内定価 （15％）]])/(商品マスタ[[#This Row],[参考上代 （税込)]]/1.08), "") | P277: 0.1 | Q277: =商品マスタ[[#This Row],[仕入 単価]]*商品マスタ[[#This Row],[標準国内送料率]] | S277: =IF(ISBLANK(商品マスタ[[#This Row],[実績 国内送料]]),商品マスタ[[#This Row],[標準国内送料]],) | T277: =商品マスタ[[#This Row],[仕入 単価]]+商品マスタ[[#This Row],[国内送料]] | U277: =ROUNDUP(商品マスタ[[#This Row],[仕入単価+国内送料]]/0.8,-1) | V277: =商品マスタ[[#This Row],[海外定価 （20％）]]-商品マスタ[[#This Row],[仕入単価+国内送料]] | W277: =ROUNDUP(商品マスタ[[#This Row],[仕入単価+国内送料]]/0.85,-1) | X277: =商品マスタ[[#This Row],[国内定価 （15％）]]-商品マスタ[[#This Row],[仕入単価+国内送料]] | Y277: 0.08
A278: 水産 | B278: 水産物 | C278: 佐藤水産 | D278: ="PRD_SNJ_"& _xlfn.XLOOKUP(商品マスタ[[#This Row],[仕入先]],テーブル1[仕入先名],テーブル1[仕入先コード],"XXX",0,1)& "_"& 商品マスタ[[#This Row],[シリアル]]& "_"& TEXT(COUNTIFS(商品マスタ!$C$3:C278,商品マスタ[[#This Row],[仕入先]],商品マスタ!$E$3:E278,商品マスタ[[#This Row],[商品名]]), "00") | E278: 酒の肴シリーズ鮭ジャーキー | F278: =IF(COUNTIFS($C$3:C278,商品マスタ[[#This Row],[仕入先]],$E$3:E278,商品マスタ[[#This Row],[商品名]]) = 1, 1,0) | G278: =TEXT(SUMIF($C$3:C278,商品マスタ[[#This Row],[仕入先]],$F$3:F278), "0000") | H278: 個 | L278: 300 | O278: =IF(COUNT(商品マスタ[[#This Row],[参考上代 （税込)]]) > 0, (商品マスタ[[#This Row],[参考上代 （税込)]]-商品マスタ[[#This Row],[国内定価 （15％）]])/(商品マスタ[[#This Row],[参考上代 （税込)]]/1.08), "") | P278: 0.1 | Q278: =商品マスタ[[#This Row],[仕入 単価]]*商品マスタ[[#This Row],[標準国内送料率]] | S278: =IF(ISBLANK(商品マスタ[[#This Row],[実績 国内送料]]),商品マスタ[[#This Row],[標準国内送料]],) | T278: =商品マスタ[[#This Row],[仕入 単価]]+商品マスタ[[#This Row],[国内送料]] | U278: =ROUNDUP(商品マスタ[[#This Row],[仕入単価+国内送料]]/0.8,-1) | V278: =商品マスタ[[#This Row],[海外定価 （20％）]]-商品マスタ[[#This Row],[仕入単価+国内送料]] | W278: =ROUNDUP(商品マスタ[[#This Row],[仕入単価+国内送料]]/0.85,-1) | X278: =商品マスタ[[#This Row],[国内定価 （15％）]]-商品マスタ[[#This Row],[仕入単価+国内送料]] | Y278: 0.08
A279: 水産 | B279: 水産物 | C279: マルトシ吉野商店 | D279: ="PRD_SNJ_"& _xlfn.XLOOKUP(商品マスタ[[#This Row],[仕入先]],テーブル1[仕入先名],テーブル1[仕入先コード],"XXX",0,1)& "_"& 商品マスタ[[#This Row],[シリアル]]& "_"& TEXT(COUNTIFS(商品マスタ!$C$3:C279,商品マスタ[[#This Row],[仕入先]],商品マスタ!$E$3:E279,商品マスタ[[#This Row],[商品名]]), "00") | E279: 鮭寿荒ほぐし100ｇ | F279: =IF(COUNTIFS($C$3:C279,商品マスタ[[#This Row],[仕入先]],$E$3:E279,商品マスタ[[#This Row],[商品名]]) = 1, 1,0) | G279: =TEXT(SUMIF($C$3:C279,商品マスタ[[#This Row],[仕入先]],$F$3:F279), "0000") | H279: 個 | L279: 780 | O279: =IF(COUNT(商品マスタ[[#This Row],[参考上代 （税込)]]) > 0, (商品マスタ[[#This Row],[参考上代 （税込)]]-商品マスタ[[#This Row],[国内定価 （15％）]])/(商品マスタ[[#This Row],[参考上代 （税込)]]/1.08), "") | P279: 0.1 | Q279: =商品マスタ[[#This Row],[仕入 単価]]*商品マスタ[[#This Row],[標準国内送料率]] | S279: =IF(ISBLANK(商品マスタ[[#This Row],[実績 国内送料]]),商品マスタ[[#This Row],[標準国内送料]],) | T279: =商品マスタ[[#This Row],[仕入 単価]]+商品マスタ[[#This Row],[国内送料]] | U279: =ROUNDUP(商品マスタ[[#This Row],[仕入単価+国内送料]]/0.8,-1) | V279: =商品マスタ[[#This Row],[海外定価 （20％）]]-商品マスタ[[#This Row],[仕入単価+国内送料]] | W279: =ROUNDUP(商品マスタ[[#This Row],[仕入単価+国内送料]]/0.85,-1) | X279: =商品マスタ[[#This Row],[国内定価 （15％）]]-商品マスタ[[#This Row],[仕入単価+国内送料]] | Y279: 0.08
A280: 水産 | B280: 水産物 | C280: マルトシ吉野商店 | D280: ="PRD_SNJ_"& _xlfn.XLOOKUP(商品マスタ[[#This Row],[仕入先]],テーブル1[仕入先名],テーブル1[仕入先コード],"XXX",0,1)& "_"& 商品マスタ[[#This Row],[シリアル]]& "_"& TEXT(COUNTIFS(商品マスタ!$C$3:C280,商品マスタ[[#This Row],[仕入先]],商品マスタ!$E$3:E280,商品マスタ[[#This Row],[商品名]]), "00") | E280: 送料差額 | F280: =IF(COUNTIFS($C$3:C280,商品マスタ[[#This Row],[仕入先]],$E$3:E280,商品マスタ[[#This Row],[商品名]]) = 1, 1,0) | G280: =TEXT(SUMIF($C$3:C280,商品マスタ[[#This Row],[仕入先]],$F$3:F280), "0000") | H280: 式 | O280: =IF(COUNT(商品マスタ[[#This Row],[参考上代 （税込)]]) > 0, (商品マスタ[[#This Row],[参考上代 （税込)]]-商品マスタ[[#This Row],[国内定価 （15％）]])/(商品マスタ[[#This Row],[参考上代 （税込)]]/1.08), "") | P280: 0.1 | Q280: =商品マスタ[[#This Row],[仕入 単価]]*商品マスタ[[#This Row],[標準国内送料率]] | S280: =IF(ISBLANK(商品マスタ[[#This Row],[実績 国内送料]]),商品マスタ[[#This Row],[標準国内送料]],) | T280: =商品マスタ[[#This Row],[仕入 単価]]+商品マスタ[[#This Row],[国内送料]] | U280: =ROUNDUP(商品マスタ[[#This Row],[仕入単価+国内送料]]/0.8,-1) | V280: =商品マスタ[[#This Row],[海外定価 （20％）]]-商品マスタ[[#This Row],[仕入単価+国内送料]] | W280: =ROUNDUP(商品マスタ[[#This Row],[仕入単価+国内送料]]/0.85,-1) | X280: =商品マスタ[[#This Row],[国内定価 （15％）]]-商品マスタ[[#This Row],[仕入単価+国内送料]] | Y280: 0.08
A281: 青果 | B281: 野菜 | C281: にんにく種蔵 | D281: ="PRD_SNJ_"& _xlfn.XLOOKUP(商品マスタ[[#This Row],[仕入先]],テーブル1[仕入先名],テーブル1[仕入先コード],"XXX",0,1)& "_"& 商品マスタ[[#This Row],[シリアル]]& "_"& TEXT(COUNTIFS(商品マスタ!$C$3:C281,商品マスタ[[#This Row],[仕入先]],商品マスタ!$E$3:E281,商品マスタ[[#This Row],[商品名]]), "00") | E281: にんスコ | F281: =IF(COUNTIFS($C$3:C281,商品マスタ[[#This Row],[仕入先]],$E$3:E281,商品マスタ[[#This Row],[商品名]]) = 1, 1,0) | G281: =TEXT(SUMIF($C$3:C281,商品マスタ[[#This Row],[仕入先]],$F$3:F281), "0000") | H281: 瓶 | L281: 456 | O281: =IF(COUNT(商品マスタ[[#This Row],[参考上代 （税込)]]) > 0, (商品マスタ[[#This Row],[参考上代 （税込)]]-商品マスタ[[#This Row],[国内定価 （15％）]])/(商品マスタ[[#This Row],[参考上代 （税込)]]/1.08), "") | P281: 0.1 | Q281: =商品マスタ[[#This Row],[仕入 単価]]*商品マスタ[[#This Row],[標準国内送料率]] | S281: =IF(ISBLANK(商品マスタ[[#This Row],[実績 国内送料]]),商品マスタ[[#This Row],[標準国内送料]],) | T281: =商品マスタ[[#This Row],[仕入 単価]]+商品マスタ[[#This Row],[国内送料]] | U281: =ROUNDUP(商品マスタ[[#This Row],[仕入単価+国内送料]]/0.8,-1) | V281: =商品マスタ[[#This Row],[海外定価 （20％）]]-商品マスタ[[#This Row],[仕入単価+国内送料]] | W281: =ROUNDUP(商品マスタ[[#This Row],[仕入単価+国内送料]]/0.85,-1) | X281: =商品マスタ[[#This Row],[国内定価 （15％）]]-商品マスタ[[#This Row],[仕入単価+国内送料]] | Y281: 0.08
A282: 精肉 | B282: 和牛 | C282: GOODGOOD | D282: ="PRD_SNJ_"& _xlfn.XLOOKUP(商品マスタ[[#This Row],[仕入先]],テーブル1[仕入先名],テーブル1[仕入先コード],"XXX",0,1)& "_"& 商品マスタ[[#This Row],[シリアル]]& "_"& TEXT(COUNTIFS(商品マスタ!$C$3:C282,商品マスタ[[#This Row],[仕入先]],商品マスタ!$E$3:E282,商品マスタ[[#This Row],[商品名]]), "00") | E282: 牧草あか牛 牛脂（チチカブ） | F282: =IF(COUNTIFS($C$3:C282,商品マスタ[[#This Row],[仕入先]],$E$3:E282,商品マスタ[[#This Row],[商品名]]) = 1, 1,0) | G282: =TEXT(SUMIF($C$3:C282,商品マスタ[[#This Row],[仕入先]],$F$3:F282), "0000") | H282: セット | I282: 4kg | J282: 1 | L282: 2000 | O282: =IF(COUNT(商品マスタ[[#This Row],[参考上代 （税込)]]) > 0, (商品マスタ[[#This Row],[参考上代 （税込)]]-商品マスタ[[#This Row],[国内定価 （15％）]])/(商品マスタ[[#This Row],[参考上代 （税込)]]/1.08), "") | P282: 0.1 | Q282: =商品マスタ[[#This Row],[仕入 単価]]*商品マスタ[[#This Row],[標準国内送料率]] | R282: 0 | S282: =IF(ISBLANK(商品マスタ[[#This Row],[実績 国内送料]]),商品マスタ[[#This Row],[標準国内送料]],) | T282: =商品マスタ[[#This Row],[仕入 単価]]+商品マスタ[[#This Row],[国内送料]] | U282: =ROUNDUP(商品マスタ[[#This Row],[仕入単価+国内送料]]/0.8,-1) | V282: =商品マスタ[[#This Row],[海外定価 （20％）]]-商品マスタ[[#This Row],[仕入単価+国内送料]] | W282: =ROUNDUP(商品マスタ[[#This Row],[仕入単価+国内送料]]/0.85,-1) | X282: =商品マスタ[[#This Row],[国内定価 （15％）]]-商品マスタ[[#This Row],[仕入単価+国内送料]] | Y282: 0.08
A283: 菓子 | B283: 洋菓子 | C283: コットンクラブ | D283: ="PRD_SNJ_"& _xlfn.XLOOKUP(商品マスタ[[#This Row],[仕入先]],テーブル1[仕入先名],テーブル1[仕入先コード],"XXX",0,1)& "_"& 商品マスタ[[#This Row],[シリアル]]& "_"& TEXT(COUNTIFS(商品マスタ!$C$3:C283,商品マスタ[[#This Row],[仕入先]],商品マスタ!$E$3:E283,商品マスタ[[#This Row],[商品名]]), "00") | E283: 和歌山のほんまもんの炭 紀州備長炭 中丸 | F283: =IF(COUNTIFS($C$3:C283,商品マスタ[[#This Row],[仕入先]],$E$3:E283,商品マスタ[[#This Row],[商品名]]) = 1, 1,0) | G283: =TEXT(SUMIF($C$3:C283,商品マスタ[[#This Row],[仕入先]],$F$3:F283), "0000") | H283: kg | L283: 1767 | O283: =IF(COUNT(商品マスタ[[#This Row],[参考上代 （税込)]]) > 0, (商品マスタ[[#This Row],[参考上代 （税込)]]-商品マスタ[[#This Row],[国内定価 （15％）]])/(商品マスタ[[#This Row],[参考上代 （税込)]]/1.08), "") | P283: 0.1 | Q283: =商品マスタ[[#This Row],[仕入 単価]]*商品マスタ[[#This Row],[標準国内送料率]] | S283: =IF(ISBLANK(商品マスタ[[#This Row],[実績 国内送料]]),商品マスタ[[#This Row],[標準国内送料]],) | T283: =商品マスタ[[#This Row],[仕入 単価]]+商品マスタ[[#This Row],[国内送料]] | U283: =ROUNDUP(商品マスタ[[#This Row],[仕入単価+国内送料]]/0.8,-1) | V283: =商品マスタ[[#This Row],[海外定価 （20％）]]-商品マスタ[[#This Row],[仕入単価+国内送料]] | W283: =ROUNDUP(商品マスタ[[#This Row],[仕入単価+国内送料]]/0.85,-1) | X283: =商品マスタ[[#This Row],[国内定価 （15％）]]-商品マスタ[[#This Row],[仕入単価+国内送料]] | Y283: 0.1
...

Sheet 案件番号採番
A1: ※灰色セルは自動入力
A2: ID | B2: 年 | C2: 月 | D2: 担当者 | E2: 支店 | F2: 顧客 | G2: 案件番号 | H2: 商品
A3: =ROW([1]!tbl_採番[[#This Row],[ID]])-2 | B3: 2026 | C3: 1 | D3: 杉田 | E3: 大阪 | F3: 日新堂株式会社 | G3: =IF(ISBLANK([1]!tbl_採番[[#This Row],[年]]),"",(RIGHT([1]!tbl_採番[[#This Row],[年]],2)&TEXT([1]!tbl_採番[[#This Row],[月]],"00")&"-1"&TEXT(COUNTIFS(B$3:B3,B3,C$3:C3,C3),"000")&"-"&_xlfn.XLOOKUP([1]!tbl_採番[[#This Row],[担当者]],[1]入力ルール用シート!$D$2:$D$8,[1]入力ルール用シート!$E$2:$E$8,"",0,1)&_xlfn.XLOOKUP([1]!tbl_採番[[#This Row],[支店]],[1]入力ルール用シート!$F$2:$F$3,[1]入力ルール用シート!$G$2:$G$3,"",0,1)))
A4: =ROW([1]!tbl_採番[[#This Row],[ID]])-2 | B4: 2026 | C4: 1 | D4: 杉田 | E4: 大阪 | F4: 日新堂株式会社 | G4: =IF(ISBLANK([1]!tbl_採番[[#This Row],[年]]),"",(RIGHT([1]!tbl_採番[[#This Row],[年]],2)&TEXT([1]!tbl_採番[[#This Row],[月]],"00")&"-1"&TEXT(COUNTIFS(B$3:B4,B4,C$3:C4,C4),"000")&"-"&_xlfn.XLOOKUP([1]!tbl_採番[[#This Row],[担当者]],[1]入力ルール用シート!$D$2:$D$8,[1]入力ルール用シート!$E$2:$E$8,"",0,1)&_xlfn.XLOOKUP([1]!tbl_採番[[#This Row],[支店]],[1]入力ルール用シート!$F$2:$F$3,[1]入力ルール用シート!$G$2:$G$3,"",0,1)))
A5: =ROW([1]!tbl_採番[[#This Row],[ID]])-2 | B5: 2026 | C5: 1 | D5: 永井 | E5: 大阪 | F5: オーセントホテルズ（楽水山） | G5: =IF(ISBLANK([1]!tbl_採番[[#This Row],[年]]),"",(RIGHT([1]!tbl_採番[[#This Row],[年]],2)&TEXT([1]!tbl_採番[[#This Row],[月]],"00")&"-1"&TEXT(COUNTIFS(B$3:B5,B5,C$3:C5,C5),"000")&"-"&_xlfn.XLOOKUP([1]!tbl_採番[[#This Row],[担当者]],[1]入力ルール用シート!$D$2:$D$8,[1]入力ルール用シート!$E$2:$E$8,"",0,1)&_xlfn.XLOOKUP([1]!tbl_採番[[#This Row],[支店]],[1]入力ルール用シート!$F$2:$F$3,[1]入力ルール用シート!$G$2:$G$3,"",0,1)))
A6: =ROW([1]!tbl_採番[[#This Row],[ID]])-2 | B6: 2026 | C6: 1 | D6: 杉田 | E6: 大阪 | F6: ホロニック（ガーデンシティクラブ大阪） | G6: =IF(ISBLANK([1]!tbl_採番[[#This Row],[年]]),"",(RIGHT([1]!tbl_採番[[#This Row],[年]],2)&TEXT([1]!tbl_採番[[#This Row],[月]],"00")&"-1"&TEXT(COUNTIFS(B$3:B6,B6,C$3:C6,C6),"000")&"-"&_xlfn.XLOOKUP([1]!tbl_採番[[#This Row],[担当者]],[1]入力ルール用シート!$D$2:$D$8,[1]入力ルール用シート!$E$2:$E$8,"",0,1)&_xlfn.XLOOKUP([1]!tbl_採番[[#This Row],[支店]],[1]入力ルール用シート!$F$2:$F$3,[1]入力ルール用シート!$G$2:$G$3,"",0,1)))
A7: =ROW([1]!tbl_採番[[#This Row],[ID]])-2 | B7: 2026 | C7: 1 | D7: 杉田 | E7: 大阪 | F7: 日新堂株式会社 | G7: =IF(ISBLANK([1]!tbl_採番[[#This Row],[年]]),"",(RIGHT([1]!tbl_採番[[#This Row],[年]],2)&TEXT([1]!tbl_採番[[#This Row],[月]],"00")&"-1"&TEXT(COUNTIFS(B$3:B7,B7,C$3:C7,C7),"000")&"-"&_xlfn.XLOOKUP([1]!tbl_採番[[#This Row],[担当者]],[1]入力ルール用シート!$D$2:$D$8,[1]入力ルール用シート!$E$2:$E$8,"",0,1)&_xlfn.XLOOKUP([1]!tbl_採番[[#This Row],[支店]],[1]入力ルール用シート!$F$2:$F$3,[1]入力ルール用シート!$G$2:$G$3,"",0,1)))
A8: =ROW([1]!tbl_採番[[#This Row],[ID]])-2 | B8: 2026 | C8: 1 | D8: 杉田 | E8: 大阪 | F8: 雲鶴 | G8: =IF(ISBLANK([1]!tbl_採番[[#This Row],[年]]),"",(RIGHT([1]!tbl_採番[[#This Row],[年]],2)&TEXT([1]!tbl_採番[[#This Row],[月]],"00")&"-1"&TEXT(COUNTIFS(B$3:B8,B8,C$3:C8,C8),"000")&"-"&_xlfn.XLOOKUP([1]!tbl_採番[[#This Row],[担当者]],[1]入力ルール用シート!$D$2:$D$8,[1]入力ルール用シート!$E$2:$E$8,"",0,1)&_xlfn.XLOOKUP([1]!tbl_採番[[#This Row],[支店]],[1]入力ルール用シート!$F$2:$F$3,[1]入力ルール用シート!$G$2:$G$3,"",0,1)))
A9: =ROW([1]!tbl_採番[[#This Row],[ID]])-2 | B9: 2026 | C9: 1 | D9: 杉田 | E9: 大阪 | F9: オーセントホテルズ株式会社 | G9: =IF(ISBLANK([1]!tbl_採番[[#This Row],[年]]),"",(RIGHT([1]!tbl_採番[[#This Row],[年]],2)&TEXT([1]!tbl_採番[[#This Row],[月]],"00")&"-1"&TEXT(COUNTIFS(B$3:B9,B9,C$3:C9,C9),"000")&"-"&_xlfn.XLOOKUP([1]!tbl_採番[[#This Row],[担当者]],[1]入力ルール用シート!$D$2:$D$8,[1]入力ルール用シート!$E$2:$E$8,"",0,1)&_xlfn.XLOOKUP([1]!tbl_採番[[#This Row],[支店]],[1]入力ルール用シート!$F$2:$F$3,[1]入力ルール用シート!$G$2:$G$3,"",0,1)))
A10: =ROW([1]!tbl_採番[[#This Row],[ID]])-2 | B10: 2026 | C10: 2 | D10: 永井 | E10: 大阪 | F10: フェリーサービス株式会社 | G10: =IF(ISBLANK([1]!tbl_採番[[#This Row],[年]]),"",(RIGHT([1]!tbl_採番[[#This Row],[年]],2)&TEXT([1]!tbl_採番[[#This Row],[月]],"00")&"-1"&TEXT(COUNTIFS(B$3:B10,B10,C$3:C10,C10),"000")&"-"&_xlfn.XLOOKUP([1]!tbl_採番[[#This Row],[担当者]],[1]入力ルール用シート!$D$2:$D$8,[1]入力ルール用シート!$E$2:$E$8,"",0,1)&_xlfn.XLOOKUP([1]!tbl_採番[[#This Row],[支店]],[1]入力ルール用シート!$F$2:$F$3,[1]入力ルール用シート!$G$2:$G$3,"",0,1)))
A11: =ROW([1]!tbl_採番[[#This Row],[ID]])-2 | B11: 2026 | C11: 2 | D11: 門永 | E11: 大阪 | F11: NISSHAビジネスサービス | G11: =IF(ISBLANK([1]!tbl_採番[[#This Row],[年]]),"",(RIGHT([1]!tbl_採番[[#This Row],[年]],2)&TEXT([1]!tbl_採番[[#This Row],[月]],"00")&"-1"&TEXT(COUNTIFS(B$3:B11,B11,C$3:C11,C11),"000")&"-"&_xlfn.XLOOKUP([1]!tbl_採番[[#This Row],[担当者]],[1]入力ルール用シート!$D$2:$D$8,[1]入力ルール用シート!$E$2:$E$8,"",0,1)&_xlfn.XLOOKUP([1]!tbl_採番[[#This Row],[支店]],[1]入力ルール用シート!$F$2:$F$3,[1]入力ルール用シート!$G$2:$G$3,"",0,1)))
A12: =ROW([1]!tbl_採番[[#This Row],[ID]])-2 | B12: 2026 | C12: 2 | D12: 杉田 | E12: 大阪 | F12: 日新堂株式会社 | G12: =IF(ISBLANK([1]!tbl_採番[[#This Row],[年]]),"",(RIGHT([1]!tbl_採番[[#This Row],[年]],2)&TEXT([1]!tbl_採番[[#This Row],[月]],"00")&"-1"&TEXT(COUNTIFS(B$3:B12,B12,C$3:C12,C12),"000")&"-"&_xlfn.XLOOKUP([1]!tbl_採番[[#This Row],[担当者]],[1]入力ルール用シート!$D$2:$D$8,[1]入力ルール用シート!$E$2:$E$8,"",0,1)&_xlfn.XLOOKUP([1]!tbl_採番[[#This Row],[支店]],[1]入力ルール用シート!$F$2:$F$3,[1]入力ルール用シート!$G$2:$G$3,"",0,1)))
A13: =ROW([1]!tbl_採番[[#This Row],[ID]])-2 | B13: 2026 | C13: 2 | D13: 杉田 | E13: 大阪 | F13: 日新堂株式会社 | G13: =IF(ISBLANK([1]!tbl_採番[[#This Row],[年]]),"",(RIGHT([1]!tbl_採番[[#This Row],[年]],2)&TEXT([1]!tbl_採番[[#This Row],[月]],"00")&"-1"&TEXT(COUNTIFS(B$3:B13,B13,C$3:C13,C13),"000")&"-"&_xlfn.XLOOKUP([1]!tbl_採番[[#This Row],[担当者]],[1]入力ルール用シート!$D$2:$D$8,[1]入力ルール用シート!$E$2:$E$8,"",0,1)&_xlfn.XLOOKUP([1]!tbl_採番[[#This Row],[支店]],[1]入力ルール用シート!$F$2:$F$3,[1]入力ルール用シート!$G$2:$G$3,"",0,1)))
A14: =ROW([1]!tbl_採番[[#This Row],[ID]])-2 | B14: 2026 | C14: 2 | D14: 門永 | E14: 大阪 | F14: NISSHAビジネスサービス | G14: =IF(ISBLANK([1]!tbl_採番[[#This Row],[年]]),"",(RIGHT([1]!tbl_採番[[#This Row],[年]],2)&TEXT([1]!tbl_採番[[#This Row],[月]],"00")&"-1"&TEXT(COUNTIFS(B$3:B14,B14,C$3:C14,C14),"000")&"-"&_xlfn.XLOOKUP([1]!tbl_採番[[#This Row],[担当者]],[1]入力ルール用シート!$D$2:$D$8,[1]入力ルール用シート!$E$2:$E$8,"",0,1)&_xlfn.XLOOKUP([1]!tbl_採番[[#This Row],[支店]],[1]入力ルール用シート!$F$2:$F$3,[1]入力ルール用シート!$G$2:$G$3,"",0,1)))
A15: =ROW([1]!tbl_採番[[#This Row],[ID]])-2 | B15: 2026 | C15: 2 | D15: 杉田 | E15: 大阪 | F15: 雲鶴 | G15: =IF(ISBLANK([1]!tbl_採番[[#This Row],[年]]),"",(RIGHT([1]!tbl_採番[[#This Row],[年]],2)&TEXT([1]!tbl_採番[[#This Row],[月]],"00")&"-1"&TEXT(COUNTIFS(B$3:B15,B15,C$3:C15,C15),"000")&"-"&_xlfn.XLOOKUP([1]!tbl_採番[[#This Row],[担当者]],[1]入力ルール用シート!$D$2:$D$8,[1]入力ルール用シート!$E$2:$E$8,"",0,1)&_xlfn.XLOOKUP([1]!tbl_採番[[#This Row],[支店]],[1]入力ルール用シート!$F$2:$F$3,[1]入力ルール用シート!$G$2:$G$3,"",0,1))) | H15: 牛脂
A16: =ROW([1]!tbl_採番[[#This Row],[ID]])-2 | B16: 2026 | C16: 3 | D16: 杉田 | E16: 大阪 | F16: オーセントホテルズ株式会社 | G16: =IF(ISBLANK([1]!tbl_採番[[#This Row],[年]]),"",(RIGHT([1]!tbl_採番[[#This Row],[年]],2)&TEXT([1]!tbl_採番[[#This Row],[月]],"00")&"-1"&TEXT(COUNTIFS(B$3:B16,B16,C$3:C16,C16),"000")&"-"&_xlfn.XLOOKUP([1]!tbl_採番[[#This Row],[担当者]],[1]入力ルール用シート!$D$2:$D$8,[1]入力ルール用シート!$E$2:$E$8,"",0,1)&_xlfn.XLOOKUP([1]!tbl_採番[[#This Row],[支店]],[1]入力ルール用シート!$F$2:$F$3,[1]入力ルール用シート!$G$2:$G$3,"",0,1))) | H16: 備長炭
A17: =ROW([1]!tbl_採番[[#This Row],[ID]])-2 | B17: 2026 | C17: 3 | D17: 杉田 | E17: 大阪 | F17: 下関グランドホテル株式会社 | G17: =IF(ISBLANK([1]!tbl_採番[[#This Row],[年]]),"",(RIGHT([1]!tbl_採番[[#This Row],[年]],2)&TEXT([1]!tbl_採番[[#This Row],[月]],"00")&"-1"&TEXT(COUNTIFS(B$3:B17,B17,C$3:C17,C17),"000")&"-"&_xlfn.XLOOKUP([1]!tbl_採番[[#This Row],[担当者]],[1]入力ルール用シート!$D$2:$D$8,[1]入力ルール用シート!$E$2:$E$8,"",0,1)&_xlfn.XLOOKUP([1]!tbl_採番[[#This Row],[支店]],[1]入力ルール用シート!$F$2:$F$3,[1]入力ルール用シート!$G$2:$G$3,"",0,1))) | H17: あつまいも（商品なし）
A18: =ROW([1]!tbl_採番[[#This Row],[ID]])-2 | B18: 2026 | C18: 3 | D18: 杉田 | E18: 大阪 | F18: オーセントホテルズ株式会社 | G18: =IF(ISBLANK([1]!tbl_採番[[#This Row],[年]]),"",(RIGHT([1]!tbl_採番[[#This Row],[年]],2)&TEXT([1]!tbl_採番[[#This Row],[月]],"00")&"-1"&TEXT(COUNTIFS(B$3:B18,B18,C$3:C18,C18),"000")&"-"&_xlfn.XLOOKUP([1]!tbl_採番[[#This Row],[担当者]],[1]入力ルール用シート!$D$2:$D$8,[1]入力ルール用シート!$E$2:$E$8,"",0,1)&_xlfn.XLOOKUP([1]!tbl_採番[[#This Row],[支店]],[1]入力ルール用シート!$F$2:$F$3,[1]入力ルール用シート!$G$2:$G$3,"",0,1))) | H18: 不知火（商品なし）
A19: =ROW([1]!tbl_採番[[#This Row],[ID]])-2 | B19: 2026 | C19: 3 | D19: 杉田 | E19: 大阪 | F19: 加古川ヤマトヤシキ | G19: =IF(ISBLANK([1]!tbl_採番[[#This Row],[年]]),"",(RIGHT([1]!tbl_採番[[#This Row],[年]],2)&TEXT([1]!tbl_採番[[#This Row],[月]],"00")&"-1"&TEXT(COUNTIFS(B$3:B19,B19,C$3:C19,C19),"000")&"-"&_xlfn.XLOOKUP([1]!tbl_採番[[#This Row],[担当者]],[1]入力ルール用シート!$D$2:$D$8,[1]入力ルール用シート!$E$2:$E$8,"",0,1)&_xlfn.XLOOKUP([1]!tbl_採番[[#This Row],[支店]],[1]入力ルール用シート!$F$2:$F$3,[1]入力ルール用シート!$G$2:$G$3,"",0,1))) | H19: 各種
A20: =ROW([1]!tbl_採番[[#This Row],[ID]])-2 | G20: =IF(ISBLANK([1]!tbl_採番[[#This Row],[年]]),"",(RIGHT([1]!tbl_採番[[#This Row],[年]],2)&TEXT([1]!tbl_採番[[#This Row],[月]],"00")&"-1"&TEXT(COUNTIFS(B$3:B20,B20,C$3:C20,C20),"000")&"-"&_xlfn.XLOOKUP([1]!tbl_採番[[#This Row],[担当者]],[1]入力ルール用シート!$D$2:$D$8,[1]入力ルール用シート!$E$2:$E$8,"",0,1)&_xlfn.XLOOKUP([1]!tbl_採番[[#This Row],[支店]],[1]入力ルール用シート!$F$2:$F$3,[1]入力ルール用シート!$G$2:$G$3,"",0,1)))
A21: =ROW([1]!tbl_採番[[#This Row],[ID]])-2 | G21: =IF(ISBLANK([1]!tbl_採番[[#This Row],[年]]),"",(RIGHT([1]!tbl_採番[[#This Row],[年]],2)&TEXT([1]!tbl_採番[[#This Row],[月]],"00")&"-1"&TEXT(COUNTIFS(B$3:B21,B21,C$3:C21,C21),"000")&"-"&_xlfn.XLOOKUP([1]!tbl_採番[[#This Row],[担当者]],[1]入力ルール用シート!$D$2:$D$8,[1]入力ルール用シート!$E$2:$E$8,"",0,1)&_xlfn.XLOOKUP([1]!tbl_採番[[#This Row],[支店]],[1]入力ルール用シート!$F$2:$F$3,[1]入力ルール用シート!$G$2:$G$3,"",0,1)))
A22: =ROW([1]!tbl_採番[[#This Row],[ID]])-2 | G22: =IF(ISBLANK([1]!tbl_採番[[#This Row],[年]]),"",(RIGHT([1]!tbl_採番[[#This Row],[年]],2)&TEXT([1]!tbl_採番[[#This Row],[月]],"00")&"-1"&TEXT(COUNTIFS(B$3:B22,B22,C$3:C22,C22),"000")&"-"&_xlfn.XLOOKUP([1]!tbl_採番[[#This Row],[担当者]],[1]入力ルール用シート!$D$2:$D$8,[1]入力ルール用シート!$E$2:$E$8,"",0,1)&_xlfn.XLOOKUP([1]!tbl_採番[[#This Row],[支店]],[1]入力ルール用シート!$F$2:$F$3,[1]入力ルール用シート!$G$2:$G$3,"",0,1)))
A23: =ROW([1]!tbl_採番[[#This Row],[ID]])-2 | G23: =IF(ISBLANK([1]!tbl_採番[[#This Row],[年]]),"",(RIGHT([1]!tbl_採番[[#This Row],[年]],2)&TEXT([1]!tbl_採番[[#This Row],[月]],"00")&"-1"&TEXT(COUNTIFS(B$3:B23,B23,C$3:C23,C23),"000")&"-"&_xlfn.XLOOKUP([1]!tbl_採番[[#This Row],[担当者]],[1]入力ルール用シート!$D$2:$D$8,[1]入力ルール用シート!$E$2:$E$8,"",0,1)&_xlfn.XLOOKUP([1]!tbl_採番[[#This Row],[支店]],[1]入力ルール用シート!$F$2:$F$3,[1]入力ルール用シート!$G$2:$G$3,"",0,1)))
A24: =ROW([1]!tbl_採番[[#This Row],[ID]])-2 | G24: =IF(ISBLANK([1]!tbl_採番[[#This Row],[年]]),"",(RIGHT([1]!tbl_採番[[#This Row],[年]],2)&TEXT([1]!tbl_採番[[#This Row],[月]],"00")&"-1"&TEXT(COUNTIFS(B$3:B24,B24,C$3:C24,C24),"000")&"-"&_xlfn.XLOOKUP([1]!tbl_採番[[#This Row],[担当者]],[1]入力ルール用シート!$D$2:$D$8,[1]入力ルール用シート!$E$2:$E$8,"",0,1)&_xlfn.XLOOKUP([1]!tbl_採番[[#This Row],[支店]],[1]入力ルール用シート!$F$2:$F$3,[1]入力ルール用シート!$G$2:$G$3,"",0,1)))
A25: =ROW([1]!tbl_採番[[#This Row],[ID]])-2 | G25: =IF(ISBLANK([1]!tbl_採番[[#This Row],[年]]),"",(RIGHT([1]!tbl_採番[[#This Row],[年]],2)&TEXT([1]!tbl_採番[[#This Row],[月]],"00")&"-1"&TEXT(COUNTIFS(B$3:B25,B25,C$3:C25,C25),"000")&"-"&_xlfn.XLOOKUP([1]!tbl_採番[[#This Row],[担当者]],[1]入力ルール用シート!$D$2:$D$8,[1]入力ルール用シート!$E$2:$E$8,"",0,1)&_xlfn.XLOOKUP([1]!tbl_採番[[#This Row],[支店]],[1]入力ルール用シート!$F$2:$F$3,[1]入力ルール用シート!$G$2:$G$3,"",0,1)))
A26: =ROW([1]!tbl_採番[[#This Row],[ID]])-2 | G26: =IF(ISBLANK([1]!tbl_採番[[#This Row],[年]]),"",(RIGHT([1]!tbl_採番[[#This Row],[年]],2)&TEXT([1]!tbl_採番[[#This Row],[月]],"00")&"-1"&TEXT(COUNTIFS(B$3:B26,B26,C$3:C26,C26),"000")&"-"&_xlfn.XLOOKUP([1]!tbl_採番[[#This Row],[担当者]],[1]入力ルール用シート!$D$2:$D$8,[1]入力ルール用シート!$E$2:$E$8,"",0,1)&_xlfn.XLOOKUP([1]!tbl_採番[[#This Row],[支店]],[1]入力ルール用シート!$F$2:$F$3,[1]入力ルール用シート!$G$2:$G$3,"",0,1)))
A27: =ROW([1]!tbl_採番[[#This Row],[ID]])-2 | G27: =IF(ISBLANK([1]!tbl_採番[[#This Row],[年]]),"",(RIGHT([1]!tbl_採番[[#This Row],[年]],2)&TEXT([1]!tbl_採番[[#This Row],[月]],"00")&"-1"&TEXT(COUNTIFS(B$3:B27,B27,C$3:C27,C27),"000")&"-"&_xlfn.XLOOKUP([1]!tbl_採番[[#This Row],[担当者]],[1]入力ルール用シート!$D$2:$D$8,[1]入力ルール用シート!$E$2:$E$8,"",0,1)&_xlfn.XLOOKUP([1]!tbl_採番[[#This Row],[支店]],[1]入力ルール用シート!$F$2:$F$3,[1]入力ルール用シート!$G$2:$G$3,"",0,1)))
A28: =ROW([1]!tbl_採番[[#This Row],[ID]])-2 | G28: =IF(ISBLANK([1]!tbl_採番[[#This Row],[年]]),"",(RIGHT([1]!tbl_採番[[#This Row],[年]],2)&TEXT([1]!tbl_採番[[#This Row],[月]],"00")&"-1"&TEXT(COUNTIFS(B$3:B28,B28,C$3:C28,C28),"000")&"-"&_xlfn.XLOOKUP([1]!tbl_採番[[#This Row],[担当者]],[1]入力ルール用シート!$D$2:$D$8,[1]入力ルール用シート!$E$2:$E$8,"",0,1)&_xlfn.XLOOKUP([1]!tbl_採番[[#This Row],[支店]],[1]入力ルール用シート!$F$2:$F$3,[1]入力ルール用シート!$G$2:$G$3,"",0,1)))
A29: =ROW([1]!tbl_採番[[#This Row],[ID]])-2 | G29: =IF(ISBLANK([1]!tbl_採番[[#This Row],[年]]),"",(RIGHT([1]!tbl_採番[[#This Row],[年]],2)&TEXT([1]!tbl_採番[[#This Row],[月]],"00")&"-1"&TEXT(COUNTIFS(B$3:B29,B29,C$3:C29,C29),"000")&"-"&_xlfn.XLOOKUP([1]!tbl_採番[[#This Row],[担当者]],[1]入力ルール用シート!$D$2:$D$8,[1]入力ルール用シート!$E$2:$E$8,"",0,1)&_xlfn.XLOOKUP([1]!tbl_採番[[#This Row],[支店]],[1]入力ルール用シート!$F$2:$F$3,[1]入力ルール用シート!$G$2:$G$3,"",0,1)))
A30: =ROW([1]!tbl_採番[[#This Row],[ID]])-2 | G30: =IF(ISBLANK([1]!tbl_採番[[#This Row],[年]]),"",(RIGHT([1]!tbl_採番[[#This Row],[年]],2)&TEXT([1]!tbl_採番[[#This Row],[月]],"00")&"-1"&TEXT(COUNTIFS(B$3:B30,B30,C$3:C30,C30),"000")&"-"&_xlfn.XLOOKUP([1]!tbl_採番[[#This Row],[担当者]],[1]入力ルール用シート!$D$2:$D$8,[1]入力ルール用シート!$E$2:$E$8,"",0,1)&_xlfn.XLOOKUP([1]!tbl_採番[[#This Row],[支店]],[1]入力ルール用シート!$F$2:$F$3,[1]入力ルール用シート!$G$2:$G$3,"",0,1)))
A31: =ROW([1]!tbl_採番[[#This Row],[ID]])-2 | G31: =IF(ISBLANK([1]!tbl_採番[[#This Row],[年]]),"",(RIGHT([1]!tbl_採番[[#This Row],[年]],2)&TEXT([1]!tbl_採番[[#This Row],[月]],"00")&"-1"&TEXT(COUNTIFS(B$3:B31,B31,C$3:C31,C31),"000")&"-"&_xlfn.XLOOKUP([1]!tbl_採番[[#This Row],[担当者]],[1]入力ルール用シート!$D$2:$D$8,[1]入力ルール用シート!$E$2:$E$8,"",0,1)&_xlfn.XLOOKUP([1]!tbl_採番[[#This Row],[支店]],[1]入力ルール用シート!$F$2:$F$3,[1]入力ルール用シート!$G$2:$G$3,"",0,1)))
... A158: =ROW([1]!tbl_採番[[#This Row],[ID]])-2 | G158: =IF(ISBLANK([1]!tbl_採番[[#This Row],[年]]),"",(RIGHT([1]!tbl_採番[[#This Row],[年]],2)&TEXT([1]!tbl_採番[[#This Row],[月]],"00")&"-1"&TEXT(COUNTIFS(B$3:B158,B158,C$3:C158,C158),"000")&"-"&_xlfn.XLOOKUP([1]!tbl_採番[[#This Row],[担当者]],[1]入力ルール用シート!$D$2:$D$8,[1]入力ルール用シート!$E$2:$E$8,"",0,1)&_xlfn.XLOOKUP([1]!tbl_採番[[#This Row],[支店]],[1]入力ルール用シート!$F$2:$F$3,[1]入力ルール用シート!$G$2:$G$3,"",0,1)))

Sheet 顧客与信管理
A1: ※灰色セルは自動入力
A2: 顧客名 | B2: 区分 | C2: 調査機関 | D2: 評点/格付 | E2: 調査日 | F2: 年間売上高 | G2: 年間利益金 | H2: 自己資本率 | I2: 与信限度額 | J2: 算定根拠 | K2: 稟議番号 | L2: 稟議決裁日 | M2: 売掛金更新日 | N2: 現在売掛残高 | O2: 残与信枠 | P2: 支払条件 | Q2: 備考
A3: サンプル日新堂株式会社 | B3: 国内 | C3: 帝国DB | D3: 30 | E3: 46032 | F3: 50000000 | G3: 3000000 | H3: 0.35 | I3: =IF(ISBLANK(tbl_与信[[#This Row],[顧客名]]),"", IF(tbl_与信[[#This Row],[区分]]="海外", IF(tbl_与信[[#This Row],[評点/格付]]="EC", 0, ""), IF(tbl_与信[[#This Row],[評点/格付]]<50, 0, MIN( tbl_与信[[#This Row],[年間売上高]]*IF(tbl_与信[[#This Row],[評点/格付]]>=65, 0.05, 0.02), tbl_与信[[#This Row],[年間利益金]]*0.5 )*IF(tbl_与信[[#This Row],[自己資本率]]<0.2, 0.4, IF(tbl_与信[[#This Row],[自己資本率]]<0.4, 0.7, 1)) ) ) ) | J3: =IF(ISBLANK(tbl_与信[[#This Row],[顧客名]]),"", IF(tbl_与信[[#This Row],[区分]]="海外", IF(tbl_与信[[#This Row],[評点/格付]]="EC", "格付EC→前金必須", "保険引受限度額準拠"), IF(tbl_与信[[#This Row],[評点/格付]]<50, "評点49以下→前金必須", IF(tbl_与信[[#This Row],[年間売上高]]*IF(tbl_与信[[#This Row],[評点/格付]]>=65,0.05,0.02) < tbl_与信[[#This Row],[年間利益金]]*0.5, "売上高ベース("&IF(tbl_与信[[#This Row],[評点/格付]]>=65,"5%","2%")&")×抑制"&IF(tbl_与信[[#This Row],[自己資本率]]<0.2,"0.4",IF(tbl_与信[[#This Row],[自己資本率]]<0.4,"0.7","1.0")), "利益金ベース(50%)×抑制"&IF(tbl_与信[[#This Row],[自己資本率]]<0.2,"0.4",IF(tbl_与信[[#This Row],[自己資本率]]<0.4,"0.7","1.0")) ) ) ) ) | L3: 46034 | N3: 800000 | O3: =IF(ISBLANK(tbl_与信[[#This Row],[顧客名]]),"",IF(ISNUMBER(tbl_与信[[#This Row],[与信限度額]]), tbl_与信[[#This Row],[与信限度額]]-tbl_与信[[#This Row],[現在売掛残高]], "-")) | P3: 掛売
A4: サンプル株式会社ホロニック | B4: 国内 | C4: TSR | D4: 60 | E4: 45976 | F4: 120000000 | G4: 5000000 | H4: 0.25 | I4: =IF(ISBLANK(tbl_与信[[#This Row],[顧客名]]),"", IF(tbl_与信[[#This Row],[区分]]="海外", IF(tbl_与信[[#This Row],[評点/格付]]="EC", 0, ""), IF(tbl_与信[[#This Row],[評点/格付]]<50, 0, MIN( tbl_与信[[#This Row],[年間売上高]]*IF(tbl_与信[[#This Row],[評点/格付]]>=65, 0.05, 0.02), tbl_与信[[#This Row],[年間利益金]]*0.5 )*IF(tbl_与信[[#This Row],[自己資本率]]<0.2, 0.4, IF(tbl_与信[[#This Row],[自己資本率]]<0.4, 0.7, 1)) ) ) ) | J4: =IF(ISBLANK(tbl_与信[[#This Row],[顧客名]]),"", IF(tbl_与信[[#This Row],[区分]]="海外", IF(tbl_与信[[#This Row],[評点/格付]]="EC", "格付EC→前金必須", "保険引受限度額準拠"), IF(tbl_与信[[#This Row],[評点/格付]]<50, "評点49以下→前金必須", IF(tbl_与信[[#This Row],[年間売上高]]*IF(tbl_与信[[#This Row],[評点/格付]]>=65,0.05,0.02) < tbl_与信[[#This Row],[年間利益金]]*0.5, "売上高ベース("&IF(tbl_与信[[#This Row],[評点/格付]]>=65,"5%","2%")&")×抑制"&IF(tbl_与信[[#This Row],[自己資本率]]<0.2,"0.4",IF(tbl_与信[[#This Row],[自己資本率]]<0.4,"0.7","1.0")), "利益金ベース(50%)×抑制"&IF(tbl_与信[[#This Row],[自己資本率]]<0.2,"0.4",IF(tbl_与信[[#This Row],[自己資本率]]<0.4,"0.7","1.0")) ) ) ) ) | L4: 45981 | N4: 1200000 | O4: =IF(ISBLANK(tbl_与信[[#This Row],[顧客名]]),"",IF(ISNUMBER(tbl_与信[[#This Row],[与信限度額]]), tbl_与信[[#This Row],[与信限度額]]-tbl_与信[[#This Row],[現在売掛残高]], "-")) | P4: 掛売
A5: サンプルABC Trading (HK) | B5: 海外 | C5: NEXI | D5: EA | E5: 45992 | I5: =IF(ISBLANK(tbl_与信[[#This Row],[顧客名]]),"", IF(tbl_与信[[#This Row],[区分]]="海外", IF(tbl_与信[[#This Row],[評点/格付]]="EC", 0, ""), IF(tbl_与信[[#This Row],[評点/格付]]<50, 0, MIN( tbl_与信[[#This Row],[年間売上高]]*IF(tbl_与信[[#This Row],[評点/格付]]>=65, 0.05, 0.02), tbl_与信[[#This Row],[年間利益金]]*0.5 )*IF(tbl_与信[[#This Row],[自己資本率]]<0.2, 0.4, IF(tbl_与信[[#This Row],[自己資本率]]<0.4, 0.7, 1)) ) ) ) | J5: =IF(ISBLANK(tbl_与信[[#This Row],[顧客名]]),"", IF(tbl_与信[[#This Row],[区分]]="海外", IF(tbl_与信[[#This Row],[評点/格付]]="EC", "格付EC→前金必須", "保険引受限度額準拠"), IF(tbl_与信[[#This Row],[評点/格付]]<50, "評点49以下→前金必須", IF(tbl_与信[[#This Row],[年間売上高]]*IF(tbl_与信[[#This Row],[評点/格付]]>=65,0.05,0.02) < tbl_与信[[#This Row],[年間利益金]]*0.5, "売上高ベース("&IF(tbl_与信[[#This Row],[評点/格付]]>=65,"5%","2%")&")×抑制"&IF(tbl_与信[[#This Row],[自己資本率]]<0.2,"0.4",IF(tbl_与信[[#This Row],[自己資本率]]<0.4,"0.7","1.0")), "利益金ベース(50%)×抑制"&IF(tbl_与信[[#This Row],[自己資本率]]<0.2,"0.4",IF(tbl_与信[[#This Row],[自己資本率]]<0.4,"0.7","1.0")) ) ) ) ) | L5: - | N5: 0 | O5: =IF(ISBLANK(tbl_与信[[#This Row],[顧客名]]),"",IF(ISNUMBER(tbl_与信[[#This Row],[与信限度額]]), tbl_与信[[#This Row],[与信限度額]]-tbl_与信[[#This Row],[現在売掛残高]], "-")) | P5: 掛売（保険付保）
A6: サンプルXYZ Foods Vietnam | B6: 海外 | C6: NEXI | D6: EC | E6: 46027 | I6: =IF(ISBLANK(tbl_与信[[#This Row],[顧客名]]),"", IF(tbl_与信[[#This Row],[区分]]="海外", IF(tbl_与信[[#This Row],[評点/格付]]="EC", 0, ""), IF(tbl_与信[[#This Row],[評点/格付]]<50, 0, MIN( tbl_与信[[#This Row],[年間売上高]]*IF(tbl_与信[[#This Row],[評点/格付]]>=65, 0.05, 0.02), tbl_与信[[#This Row],[年間利益金]]*0.5 )*IF(tbl_与信[[#This Row],[自己資本率]]<0.2, 0.4, IF(tbl_与信[[#This Row],[自己資本率]]<0.4, 0.7, 1)) ) ) ) | J6: =IF(ISBLANK(tbl_与信[[#This Row],[顧客名]]),"", IF(tbl_与信[[#This Row],[区分]]="海外", IF(tbl_与信[[#This Row],[評点/格付]]="EC", "格付EC→前金必須", "保険引受限度額準拠"), IF(tbl_与信[[#This Row],[評点/格付]]<50, "評点49以下→前金必須", IF(tbl_与信[[#This Row],[年間売上高]]*IF(tbl_与信[[#This Row],[評点/格付]]>=65,0.05,0.02) < tbl_与信[[#This Row],[年間利益金]]*0.5, "売上高ベース("&IF(tbl_与信[[#This Row],[評点/格付]]>=65,"5%","2%")&")×抑制"&IF(tbl_与信[[#This Row],[自己資本率]]<0.2,"0.4",IF(tbl_与信[[#This Row],[自己資本率]]<0.4,"0.7","1.0")), "利益金ベース(50%)×抑制"&IF(tbl_与信[[#This Row],[自己資本率]]<0.2,"0.4",IF(tbl_与信[[#This Row],[自己資本率]]<0.4,"0.7","1.0")) ) ) ) ) | L6: - | N6: 0 | O6: =IF(ISBLANK(tbl_与信[[#This Row],[顧客名]]),"",IF(ISNUMBER(tbl_与信[[#This Row],[与信限度額]]), tbl_与信[[#This Row],[与信限度額]]-tbl_与信[[#This Row],[現在売掛残高]], "-")) | P6: 前金
I7: =IF(ISBLANK(tbl_与信[[#This Row],[顧客名]]),"", IF(tbl_与信[[#This Row],[区分]]="海外", IF(tbl_与信[[#This Row],[評点/格付]]="EC", 0, ""), IF(tbl_与信[[#This Row],[評点/格付]]<50, 0, MIN( tbl_与信[[#This Row],[年間売上高]]*IF(tbl_与信[[#This Row],[評点/格付]]>=65, 0.05, 0.02), tbl_与信[[#This Row],[年間利益金]]*0.5 )*IF(tbl_与信[[#This Row],[自己資本率]]<0.2, 0.4, IF(tbl_与信[[#This Row],[自己資本率]]<0.4, 0.7, 1)) ) ) ) | J7: =IF(ISBLANK(tbl_与信[[#This Row],[顧客名]]),"", IF(tbl_与信[[#This Row],[区分]]="海外", IF(tbl_与信[[#This Row],[評点/格付]]="EC", "格付EC→前金必須", "保険引受限度額準拠"), IF(tbl_与信[[#This Row],[評点/格付]]<50, "評点49以下→前金必須", IF(tbl_与信[[#This Row],[年間売上高]]*IF(tbl_与信[[#This Row],[評点/格付]]>=65,0.05,0.02) < tbl_与信[[#This Row],[年間利益金]]*0.5, "売上高ベース("&IF(tbl_与信[[#This Row],[評点/格付]]>=65,"5%","2%")&")×抑制"&IF(tbl_与信[[#This Row],[自己資本率]]<0.2,"0.4",IF(tbl_与信[[#This Row],[自己資本率]]<0.4,"0.7","1.0")), "利益金ベース(50%)×抑制"&IF(tbl_与信[[#This Row],[自己資本率]]<0.2,"0.4",IF(tbl_与信[[#This Row],[自己資本率]]<0.4,"0.7","1.0")) ) ) ) ) | O7: =IF(ISBLANK(tbl_与信[[#This Row],[顧客名]]),"",IF(ISNUMBER(tbl_与信[[#This Row],[与信限度額]]), tbl_与信[[#This Row],[与信限度額]]-tbl_与信[[#This Row],[現在売掛残高]], "-"))
I8: =IF(ISBLANK(tbl_与信[[#This Row],[顧客名]]),"", IF(tbl_与信[[#This Row],[区分]]="海外", IF(tbl_与信[[#This Row],[評点/格付]]="EC", 0, ""), IF(tbl_与信[[#This Row],[評点/格付]]<50, 0, MIN( tbl_与信[[#This Row],[年間売上高]]*IF(tbl_与信[[#This Row],[評点/格付]]>=65, 0.05, 0.02), tbl_与信[[#This Row],[年間利益金]]*0.5 )*IF(tbl_与信[[#This Row],[自己資本率]]<0.2, 0.4, IF(tbl_与信[[#This Row],[自己資本率]]<0.4, 0.7, 1)) ) ) ) | J8: =IF(ISBLANK(tbl_与信[[#This Row],[顧客名]]),"", IF(tbl_与信[[#This Row],[区分]]="海外", IF(tbl_与信[[#This Row],[評点/格付]]="EC", "格付EC→前金必須", "保険引受限度額準拠"), IF(tbl_与信[[#This Row],[評点/格付]]<50, "評点49以下→前金必須", IF(tbl_与信[[#This Row],[年間売上高]]*IF(tbl_与信[[#This Row],[評点/格付]]>=65,0.05,0.02) < tbl_与信[[#This Row],[年間利益金]]*0.5, "売上高ベース("&IF(tbl_与信[[#This Row],[評点/格付]]>=65,"5%","2%")&")×抑制"&IF(tbl_与信[[#This Row],[自己資本率]]<0.2,"0.4",IF(tbl_与信[[#This Row],[自己資本率]]<0.4,"0.7","1.0")), "利益金ベース(50%)×抑制"&IF(tbl_与信[[#This Row],[自己資本率]]<0.2,"0.4",IF(tbl_与信[[#This Row],[自己資本率]]<0.4,"0.7","1.0")) ) ) ) ) | O8: =IF(ISBLANK(tbl_与信[[#This Row],[顧客名]]),"",IF(ISNUMBER(tbl_与信[[#This Row],[与信限度額]]), tbl_与信[[#This Row],[与信限度額]]-tbl_与信[[#This Row],[現在売掛残高]], "-"))
I9: =IF(ISBLANK(tbl_与信[[#This Row],[顧客名]]),"", IF(tbl_与信[[#This Row],[区分]]="海外", IF(tbl_与信[[#This Row],[評点/格付]]="EC", 0, ""), IF(tbl_与信[[#This Row],[評点/格付]]<50, 0, MIN( tbl_与信[[#This Row],[年間売上高]]*IF(tbl_与信[[#This Row],[評点/格付]]>=65, 0.05, 0.02), tbl_与信[[#This Row],[年間利益金]]*0.5 )*IF(tbl_与信[[#This Row],[自己資本率]]<0.2, 0.4, IF(tbl_与信[[#This Row],[自己資本率]]<0.4, 0.7, 1)) ) ) ) | J9: =IF(ISBLANK(tbl_与信[[#This Row],[顧客名]]),"", IF(tbl_与信[[#This Row],[区分]]="海外", IF(tbl_与信[[#This Row],[評点/格付]]="EC", "格付EC→前金必須", "保険引受限度額準拠"), IF(tbl_与信[[#This Row],[評点/格付]]<50, "評点49以下→前金必須", IF(tbl_与信[[#This Row],[年間売上高]]*IF(tbl_与信[[#This Row],[評点/格付]]>=65,0.05,0.02) < tbl_与信[[#This Row],[年間利益金]]*0.5, "売上高ベース("&IF(tbl_与信[[#This Row],[評点/格付]]>=65,"5%","2%")&")×抑制"&IF(tbl_与信[[#This Row],[自己資本率]]<0.2,"0.4",IF(tbl_与信[[#This Row],[自己資本率]]<0.4,"0.7","1.0")), "利益金ベース(50%)×抑制"&IF(tbl_与信[[#This Row],[自己資本率]]<0.2,"0.4",IF(tbl_与信[[#This Row],[自己資本率]]<0.4,"0.7","1.0")) ) ) ) ) | O9: =IF(ISBLANK(tbl_与信[[#This Row],[顧客名]]),"",IF(ISNUMBER(tbl_与信[[#This Row],[与信限度額]]), tbl_与信[[#This Row],[与信限度額]]-tbl_与信[[#This Row],[現在売掛残高]], "-"))
I10: =IF(ISBLANK(tbl_与信[[#This Row],[顧客名]]),"", IF(tbl_与信[[#This Row],[区分]]="海外", IF(tbl_与信[[#This Row],[評点/格付]]="EC", 0, ""), IF(tbl_与信[[#This Row],[評点/格付]]<50, 0, MIN( tbl_与信[[#This Row],[年間売上高]]*IF(tbl_与信[[#This Row],[評点/格付]]>=65, 0.05, 0.02), tbl_与信[[#This Row],[年間利益金]]*0.5 )*IF(tbl_与信[[#This Row],[自己資本率]]<0.2, 0.4, IF(tbl_与信[[#This Row],[自己資本率]]<0.4, 0.7, 1)) ) ) ) | J10: =IF(ISBLANK(tbl_与信[[#This Row],[顧客名]]),"", IF(tbl_与信[[#This Row],[区分]]="海外", IF(tbl_与信[[#This Row],[評点/格付]]="EC", "格付EC→前金必須", "保険引受限度額準拠"), IF(tbl_与信[[#This Row],[評点/格付]]<50, "評点49以下→前金必須", IF(tbl_与信[[#This Row],[年間売上高]]*IF(tbl_与信[[#This Row],[評点/格付]]>=65,0.05,0.02) < tbl_与信[[#This Row],[年間利益金]]*0.5, "売上高ベース("&IF(tbl_与信[[#This Row],[評点/格付]]>=65,"5%","2%")&")×抑制"&IF(tbl_与信[[#This Row],[自己資本率]]<0.2,"0.4",IF(tbl_与信[[#This Row],[自己資本率]]<0.4,"0.7","1.0")), "利益金ベース(50%)×抑制"&IF(tbl_与信[[#This Row],[自己資本率]]<0.2,"0.4",IF(tbl_与信[[#This Row],[自己資本率]]<0.4,"0.7","1.0")) ) ) ) ) | O10: =IF(ISBLANK(tbl_与信[[#This Row],[顧客名]]),"",IF(ISNUMBER(tbl_与信[[#This Row],[与信限度額]]), tbl_与信[[#This Row],[与信限度額]]-tbl_与信[[#This Row],[現在売掛残高]], "-"))
I11: =IF(ISBLANK(tbl_与信[[#This Row],[顧客名]]),"", IF(tbl_与信[[#This Row],[区分]]="海外", IF(tbl_与信[[#This Row],[評点/格付]]="EC", 0, ""), IF(tbl_与信[[#This Row],[評点/格付]]<50, 0, MIN( tbl_与信[[#This Row],[年間売上高]]*IF(tbl_与信[[#This Row],[評点/格付]]>=65, 0.05, 0.02), tbl_与信[[#This Row],[年間利益金]]*0.5 )*IF(tbl_与信[[#This Row],[自己資本率]]<0.2, 0.4, IF(tbl_与信[[#This Row],[自己資本率]]<0.4, 0.7, 1)) ) ) ) | J11: =IF(ISBLANK(tbl_与信[[#This Row],[顧客名]]),"", IF(tbl_与信[[#This Row],[区分]]="海外", IF(tbl_与信[[#This Row],[評点/格付]]="EC", "格付EC→前金必須", "保険引受限度額準拠"), IF(tbl_与信[[#This Row],[評点/格付]]<50, "評点49以下→前金必須", IF(tbl_与信[[#This Row],[年間売上高]]*IF(tbl_与信[[#This Row],[評点/格付]]>=65,0.05,0.02) < tbl_与信[[#This Row],[年間利益金]]*0.5, "売上高ベース("&IF(tbl_与信[[#This Row],[評点/格付]]>=65,"5%","2%")&")×抑制"&IF(tbl_与信[[#This Row],[自己資本率]]<0.2,"0.4",IF(tbl_与信[[#This Row],[自己資本率]]<0.4,"0.7","1.0")), "利益金ベース(50%)×抑制"&IF(tbl_与信[[#This Row],[自己資本率]]<0.2,"0.4",IF(tbl_与信[[#This Row],[自己資本率]]<0.4,"0.7","1.0")) ) ) ) ) | O11: =IF(ISBLANK(tbl_与信[[#This Row],[顧客名]]),"",IF(ISNUMBER(tbl_与信[[#This Row],[与信限度額]]), tbl_与信[[#This Row],[与信限度額]]-tbl_与信[[#This Row],[現在売掛残高]], "-"))
I12: =IF(ISBLANK(tbl_与信[[#This Row],[顧客名]]),"", IF(tbl_与信[[#This Row],[区分]]="海外", IF(tbl_与信[[#This Row],[評点/格付]]="EC", 0, ""), IF(tbl_与信[[#This Row],[評点/格付]]<50, 0, MIN( tbl_与信[[#This Row],[年間売上高]]*IF(tbl_与信[[#This Row],[評点/格付]]>=65, 0.05, 0.02), tbl_与信[[#This Row],[年間利益金]]*0.5 )*IF(tbl_与信[[#This Row],[自己資本率]]<0.2, 0.4, IF(tbl_与信[[#This Row],[自己資本率]]<0.4, 0.7, 1)) ) ) ) | J12: =IF(ISBLANK(tbl_与信[[#This Row],[顧客名]]),"", IF(tbl_与信[[#This Row],[区分]]="海外", IF(tbl_与信[[#This Row],[評点/格付]]="EC", "格付EC→前金必須", "保険引受限度額準拠"), IF(tbl_与信[[#This Row],[評点/格付]]<50, "評点49以下→前金必須", IF(tbl_与信[[#This Row],[年間売上高]]*IF(tbl_与信[[#This Row],[評点/格付]]>=65,0.05,0.02) < tbl_与信[[#This Row],[年間利益金]]*0.5, "売上高ベース("&IF(tbl_与信[[#This Row],[評点/格付]]>=65,"5%","2%")&")×抑制"&IF(tbl_与信[[#This Row],[自己資本率]]<0.2,"0.4",IF(tbl_与信[[#This Row],[自己資本率]]<0.4,"0.7","1.0")), "利益金ベース(50%)×抑制"&IF(tbl_与信[[#This Row],[自己資本率]]<0.2,"0.4",IF(tbl_与信[[#This Row],[自己資本率]]<0.4,"0.7","1.0")) ) ) ) ) | O12: =IF(ISBLANK(tbl_与信[[#This Row],[顧客名]]),"",IF(ISNUMBER(tbl_与信[[#This Row],[与信限度額]]), tbl_与信[[#This Row],[与信限度額]]-tbl_与信[[#This Row],[現在売掛残高]], "-"))
I13: =IF(ISBLANK(tbl_与信[[#This Row],[顧客名]]),"", IF(tbl_与信[[#This Row],[区分]]="海外", IF(tbl_与信[[#This Row],[評点/格付]]="EC", 0, ""), IF(tbl_与信[[#This Row],[評点/格付]]<50, 0, MIN( tbl_与信[[#This Row],[年間売上高]]*IF(tbl_与信[[#This Row],[評点/格付]]>=65, 0.05, 0.02), tbl_与信[[#This Row],[年間利益金]]*0.5 )*IF(tbl_与信[[#This Row],[自己資本率]]<0.2, 0.4, IF(tbl_与信[[#This Row],[自己資本率]]<0.4, 0.7, 1)) ) ) ) | J13: =IF(ISBLANK(tbl_与信[[#This Row],[顧客名]]),"", IF(tbl_与信[[#This Row],[区分]]="海外", IF(tbl_与信[[#This Row],[評点/格付]]="EC", "格付EC→前金必須", "保険引受限度額準拠"), IF(tbl_与信[[#This Row],[評点/格付]]<50, "評点49以下→前金必須", IF(tbl_与信[[#This Row],[年間売上高]]*IF(tbl_与信[[#This Row],[評点/格付]]>=65,0.05,0.02) < tbl_与信[[#This Row],[年間利益金]]*0.5, "売上高ベース("&IF(tbl_与信[[#This Row],[評点/格付]]>=65,"5%","2%")&")×抑制"&IF(tbl_与信[[#This Row],[自己資本率]]<0.2,"0.4",IF(tbl_与信[[#This Row],[自己資本率]]<0.4,"0.7","1.0")), "利益金ベース(50%)×抑制"&IF(tbl_与信[[#This Row],[自己資本率]]<0.2,"0.4",IF(tbl_与信[[#This Row],[自己資本率]]<0.4,"0.7","1.0")) ) ) ) ) | O13: =IF(ISBLANK(tbl_与信[[#This Row],[顧客名]]),"",IF(ISNUMBER(tbl_与信[[#This Row],[与信限度額]]), tbl_与信[[#This Row],[与信限度額]]-tbl_与信[[#This Row],[現在売掛残高]], "-"))
I14: =IF(ISBLANK(tbl_与信[[#This Row],[顧客名]]),"", IF(tbl_与信[[#This Row],[区分]]="海外", IF(tbl_与信[[#This Row],[評点/格付]]="EC", 0, ""), IF(tbl_与信[[#This Row],[評点/格付]]<50, 0, MIN( tbl_与信[[#This Row],[年間売上高]]*IF(tbl_与信[[#This Row],[評点/格付]]>=65, 0.05, 0.02), tbl_与信[[#This Row],[年間利益金]]*0.5 )*IF(tbl_与信[[#This Row],[自己資本率]]<0.2, 0.4, IF(tbl_与信[[#This Row],[自己資本率]]<0.4, 0.7, 1)) ) ) ) | J14: =IF(ISBLANK(tbl_与信[[#This Row],[顧客名]]),"", IF(tbl_与信[[#This Row],[区分]]="海外", IF(tbl_与信[[#This Row],[評点/格付]]="EC", "格付EC→前金必須", "保険引受限度額準拠"), IF(tbl_与信[[#This Row],[評点/格付]]<50, "評点49以下→前金必須", IF(tbl_与信[[#This Row],[年間売上高]]*IF(tbl_与信[[#This Row],[評点/格付]]>=65,0.05,0.02) < tbl_与信[[#This Row],[年間利益金]]*0.5, "売上高ベース("&IF(tbl_与信[[#This Row],[評点/格付]]>=65,"5%","2%")&")×抑制"&IF(tbl_与信[[#This Row],[自己資本率]]<0.2,"0.4",IF(tbl_与信[[#This Row],[自己資本率]]<0.4,"0.7","1.0")), "利益金ベース(50%)×抑制"&IF(tbl_与信[[#This Row],[自己資本率]]<0.2,"0.4",IF(tbl_与信[[#This Row],[自己資本率]]<0.4,"0.7","1.0")) ) ) ) ) | O14: =IF(ISBLANK(tbl_与信[[#This Row],[顧客名]]),"",IF(ISNUMBER(tbl_与信[[#This Row],[与信限度額]]), tbl_与信[[#This Row],[与信限度額]]-tbl_与信[[#This Row],[現在売掛残高]], "-"))
I15: =IF(ISBLANK(tbl_与信[[#This Row],[顧客名]]),"", IF(tbl_与信[[#This Row],[区分]]="海外", IF(tbl_与信[[#This Row],[評点/格付]]="EC", 0, ""), IF(tbl_与信[[#This Row],[評点/格付]]<50, 0, MIN( tbl_与信[[#This Row],[年間売上高]]*IF(tbl_与信[[#This Row],[評点/格付]]>=65, 0.05, 0.02), tbl_与信[[#This Row],[年間利益金]]*0.5 )*IF(tbl_与信[[#This Row],[自己資本率]]<0.2, 0.4, IF(tbl_与信[[#This Row],[自己資本率]]<0.4, 0.7, 1)) ) ) ) | J15: =IF(ISBLANK(tbl_与信[[#This Row],[顧客名]]),"", IF(tbl_与信[[#This Row],[区分]]="海外", IF(tbl_与信[[#This Row],[評点/格付]]="EC", "格付EC→前金必須", "保険引受限度額準拠"), IF(tbl_与信[[#This Row],[評点/格付]]<50, "評点49以下→前金必須", IF(tbl_与信[[#This Row],[年間売上高]]*IF(tbl_与信[[#This Row],[評点/格付]]>=65,0.05,0.02) < tbl_与信[[#This Row],[年間利益金]]*0.5, "売上高ベース("&IF(tbl_与信[[#This Row],[評点/格付]]>=65,"5%","2%")&")×抑制"&IF(tbl_与信[[#This Row],[自己資本率]]<0.2,"0.4",IF(tbl_与信[[#This Row],[自己資本率]]<0.4,"0.7","1.0")), "利益金ベース(50%)×抑制"&IF(tbl_与信[[#This Row],[自己資本率]]<0.2,"0.4",IF(tbl_与信[[#This Row],[自己資本率]]<0.4,"0.7","1.0")) ) ) ) ) | O15: =IF(ISBLANK(tbl_与信[[#This Row],[顧客名]]),"",IF(ISNUMBER(tbl_与信[[#This Row],[与信限度額]]), tbl_与信[[#This Row],[与信限度額]]-tbl_与信[[#This Row],[現在売掛残高]], "-"))
I16: =IF(ISBLANK(tbl_与信[[#This Row],[顧客名]]),"", IF(tbl_与信[[#This Row],[区分]]="海外", IF(tbl_与信[[#This Row],[評点/格付]]="EC", 0, ""), IF(tbl_与信[[#This Row],[評点/格付]]<50, 0, MIN( tbl_与信[[#This Row],[年間売上高]]*IF(tbl_与信[[#This Row],[評点/格付]]>=65, 0.05, 0.02), tbl_与信[[#This Row],[年間利益金]]*0.5 )*IF(tbl_与信[[#This Row],[自己資本率]]<0.2, 0.4, IF(tbl_与信[[#This Row],[自己資本率]]<0.4, 0.7, 1)) ) ) ) | J16: =IF(ISBLANK(tbl_与信[[#This Row],[顧客名]]),"", IF(tbl_与信[[#This Row],[区分]]="海外", IF(tbl_与信[[#This Row],[評点/格付]]="EC", "格付EC→前金必須", "保険引受限度額準拠"), IF(tbl_与信[[#This Row],[評点/格付]]<50, "評点49以下→前金必須", IF(tbl_与信[[#This Row],[年間売上高]]*IF(tbl_与信[[#This Row],[評点/格付]]>=65,0.05,0.02) < tbl_与信[[#This Row],[年間利益金]]*0.5, "売上高ベース("&IF(tbl_与信[[#This Row],[評点/格付]]>=65,"5%","2%")&")×抑制"&IF(tbl_与信[[#This Row],[自己資本率]]<0.2,"0.4",IF(tbl_与信[[#This Row],[自己資本率]]<0.4,"0.7","1.0")), "利益金ベース(50%)×抑制"&IF(tbl_与信[[#This Row],[自己資本率]]<0.2,"0.4",IF(tbl_与信[[#This Row],[自己資本率]]<0.4,"0.7","1.0")) ) ) ) ) | O16: =IF(ISBLANK(tbl_与信[[#This Row],[顧客名]]),"",IF(ISNUMBER(tbl_与信[[#This Row],[与信限度額]]), tbl_与信[[#This Row],[与信限度額]]-tbl_与信[[#This Row],[現在売掛残高]], "-"))
I17: =IF(ISBLANK(tbl_与信[[#This Row],[顧客名]]),"", IF(tbl_与信[[#This Row],[区分]]="海外", IF(tbl_与信[[#This Row],[評点/格付]]="EC", 0, ""), IF(tbl_与信[[#This Row],[評点/格付]]<50, 0, MIN( tbl_与信[[#This Row],[年間売上高]]*IF(tbl_与信[[#This Row],[評点/格付]]>=65, 0.05, 0.02), tbl_与信[[#This Row],[年間利益金]]*0.5 )*IF(tbl_与信[[#This Row],[自己資本率]]<0.2, 0.4, IF(tbl_与信[[#This Row],[自己資本率]]<0.4, 0.7, 1)) ) ) ) | J17: =IF(ISBLANK(tbl_与信[[#This Row],[顧客名]]),"", IF(tbl_与信[[#This Row],[区分]]="海外", IF(tbl_与信[[#This Row],[評点/格付]]="EC", "格付EC→前金必須", "保険引受限度額準拠"), IF(tbl_与信[[#This Row],[評点/格付]]<50, "評点49以下→前金必須", IF(tbl_与信[[#This Row],[年間売上高]]*IF(tbl_与信[[#This Row],[評点/格付]]>=65,0.05,0.02) < tbl_与信[[#This Row],[年間利益金]]*0.5, "売上高ベース("&IF(tbl_与信[[#This Row],[評点/格付]]>=65,"5%","2%")&")×抑制"&IF(tbl_与信[[#This Row],[自己資本率]]<0.2,"0.4",IF(tbl_与信[[#This Row],[自己資本率]]<0.4,"0.7","1.0")), "利益金ベース(50%)×抑制"&IF(tbl_与信[[#This Row],[自己資本率]]<0.2,"0.4",IF(tbl_与信[[#This Row],[自己資本率]]<0.4,"0.7","1.0")) ) ) ) ) | O17: =IF(ISBLANK(tbl_与信[[#This Row],[顧客名]]),"",IF(ISNUMBER(tbl_与信[[#This Row],[与信限度額]]), tbl_与信[[#This Row],[与信限度額]]-tbl_与信[[#This Row],[現在売掛残高]], "-"))
I18: =IF(ISBLANK(tbl_与信[[#This Row],[顧客名]]),"", IF(tbl_与信[[#This Row],[区分]]="海外", IF(tbl_与信[[#This Row],[評点/格付]]="EC", 0, ""), IF(tbl_与信[[#This Row],[評点/格付]]<50, 0, MIN( tbl_与信[[#This Row],[年間売上高]]*IF(tbl_与信[[#This Row],[評点/格付]]>=65, 0.05, 0.02), tbl_与信[[#This Row],[年間利益金]]*0.5 )*IF(tbl_与信[[#This Row],[自己資本率]]<0.2, 0.4, IF(tbl_与信[[#This Row],[自己資本率]]<0.4, 0.7, 1)) ) ) ) | J18: =IF(ISBLANK(tbl_与信[[#This Row],[顧客名]]),"", IF(tbl_与信[[#This Row],[区分]]="海外", IF(tbl_与信[[#This Row],[評点/格付]]="EC", "格付EC→前金必須", "保険引受限度額準拠"), IF(tbl_与信[[#This Row],[評点/格付]]<50, "評点49以下→前金必須", IF(tbl_与信[[#This Row],[年間売上高]]*IF(tbl_与信[[#This Row],[評点/格付]]>=65,0.05,0.02) < tbl_与信[[#This Row],[年間利益金]]*0.5, "売上高ベース("&IF(tbl_与信[[#This Row],[評点/格付]]>=65,"5%","2%")&")×抑制"&IF(tbl_与信[[#This Row],[自己資本率]]<0.2,"0.4",IF(tbl_与信[[#This Row],[自己資本率]]<0.4,"0.7","1.0")), "利益金ベース(50%)×抑制"&IF(tbl_与信[[#This Row],[自己資本率]]<0.2,"0.4",IF(tbl_与信[[#This Row],[自己資本率]]<0.4,"0.7","1.0")) ) ) ) ) | O18: =IF(ISBLANK(tbl_与信[[#This Row],[顧客名]]),"",IF(ISNUMBER(tbl_与信[[#This Row],[与信限度額]]), tbl_与信[[#This Row],[与信限度額]]-tbl_与信[[#This Row],[現在売掛残高]], "-"))
... I62: =IF(ISBLANK(tbl_与信[[#This Row],[顧客名]]),"", IF(tbl_与信[[#This Row],[区分]]="海外", IF(tbl_与信[[#This Row],[評点/格付]]="EC", 0, ""), IF(tbl_与信[[#This Row],[評点/格付]]<50, 0, MIN( tbl_与信[[#This Row],[年間売上高]]*IF(tbl_与信[[#This Row],[評点/格付]]>=65, 0.05, 0.02), tbl_与信[[#This Row],[年間利益金]]*0.5 )*IF(tbl_与信[[#This Row],[自己資本率]]<0.2, 0.4, IF(tbl_与信[[#This Row],[自己資本率]]<0.4, 0.7, 1)) ) ) ) | J62: =IF(ISBLANK(tbl_与信[[#This Row],[顧客名]]),"", IF(tbl_与信[[#This Row],[区分]]="海外", IF(tbl_与信[[#This Row],[評点/格付]]="EC", "格付EC→前金必須", "保険引受限度額準拠"), IF(tbl_与信[[#This Row],[評点/格付]]<50, "評点49以下→前金必須", IF(tbl_与信[[#This Row],[年間売上高]]*IF(tbl_与信[[#This Row],[評点/格付]]>=65,0.05,0.02) < tbl_与信[[#This Row],[年間利益金]]*0.5, "売上高ベース("&IF(tbl_与信[[#This Row],[評点/格付]]>=65,"5%","2%")&")×抑制"&IF(tbl_与信[[#This Row],[自己資本率]]<0.2,"0.4",IF(tbl_与信[[#This Row],[自己資本率]]<0.4,"0.7","1.0")), "利益金ベース(50%)×抑制"&IF(tbl_与信[[#This Row],[自己資本率]]<0.2,"0.4",IF(tbl_与信[[#This Row],[自己資本率]]<0.4,"0.7","1.0")) ) ) ) ) | O62: =IF(ISBLANK(tbl_与信[[#This Row],[顧客名]]),"",IF(ISNUMBER(tbl_与信[[#This Row],[与信限度額]]), tbl_与信[[#This Row],[与信限度額]]-tbl_与信[[#This Row],[現在売掛残高]], "-"))

Sheet 案件明細
A1: ※灰色セルは自動入力 | G1: 自動入力（売値・数量以外） 商品マスタにある商品 | N1: 手動入力 商品マスタにない商品 または個別に調整したい場合
A2: 案件番号 | B2: No | C2: （非表示）仕入No. | D2: 顧客名 | E2: 商品ID | F2: 仕入先 | G2: 商品名 | H2: 仕入価格 | I2: 販売価格（定価） | J2: 販売価格（売値） | K2: 数量 | L2: 単位 | M2: 利益率 | N2: 税率 | O2: 仕入先（M) | P2: 商品名（M) | Q2: 仕入価格（M) | R2: 販売価格（M) | S2: 数量（M) | T2: 単位（M) | U2: 税率（M） | V2: 備考（仕入先向け） | W2: 備考（顧客向け） | X2: 単価×数（仕入） | Y2: 単価×数（売値） | Z2: 発注フラグ | AA2: (非表示）販売価格の和 | AB2: 税込価格
A3: 2601-1001-S01 | B3: =IF(ISBLANK(tbl_明細[[#This Row],[案件番号]]),"",COUNTIFS($A$3:A3,tbl_明細[[#This Row],[案件番号]],$AA$3:AA3,">0")) | C3: =COUNTIFS($A$3:A3,tbl_明細[[#This Row],[案件番号]],$F$3:F3,tbl_明細[[#This Row],[仕入先]]) | D3: =_xlfn.XLOOKUP(tbl_明細[[#This Row],[案件番号]],tbl_採番[案件番号],tbl_採番[顧客],"",0,1) | E3: PRD_SNJ_SDH_0016_01 | F3: =IF(ISBLANK(tbl_明細[[#This Row],[仕入先（M)]]),_xlfn.XLOOKUP(tbl_明細[[#This Row],[商品ID]],商品マスタ[商品連番],商品マスタ[仕入先],"",0,1),tbl_明細[[#This Row],[仕入先（M)]]) | G3: =IF(ISBLANK(tbl_明細[[#This Row],[商品名（M)]]),_xlfn.XLOOKUP(tbl_明細[[#This Row],[商品ID]],商品マスタ[商品連番],商品マスタ[商品名],"",0,),tbl_明細[[#This Row],[商品名（M)]]) | H3: =IF(ISBLANK(tbl_明細[[#This Row],[仕入価格（M)]]),_xlfn.XLOOKUP(tbl_明細[[#This Row],[商品ID]],商品マスタ[商品連番],商品マスタ[仕入 単価],"",0,1),tbl_明細[[#This Row],[仕入価格（M)]]) | I3: =_xlfn.XLOOKUP(tbl_明細[[#This Row],[商品ID]],商品マスタ[商品連番],商品マスタ[国内定価 （15％）],"",0,1) | J3: 18000 | K3: 4.781 | L3: =_xlfn.XLOOKUP(tbl_明細[[#This Row],[商品ID]],商品マスタ[商品連番],商品マスタ[単位],"",0,1) | M3: =1-tbl_明細[[#This Row],[仕入価格]]/tbl_明細[[#This Row],[販売価格（売値）]] | N3: =_xlfn.XLOOKUP(tbl_明細[[#This Row],[商品ID]],商品マスタ[商品連番],商品マスタ[税率],"",0,1) | X3: =tbl_明細[[#This Row],[仕入価格]]*tbl_明細[[#This Row],[数量]]+tbl_明細[[#This Row],[仕入価格（M)]]*tbl_明細[[#This Row],[数量（M)]] | Y3: =tbl_明細[[#This Row],[販売価格（売値）]]*tbl_明細[[#This Row],[数量]]+tbl_明細[[#This Row],[販売価格（M)]]*tbl_明細[[#This Row],[数量（M)]] | Z3: =_xlfn.XLOOKUP(tbl_明細[[#This Row],[案件番号]],tbl_案件追跡[案件番号],tbl_案件追跡[受注],"",0,1) | AA3: =tbl_明細[[#This Row],[販売価格（売値）]]+tbl_明細[[#This Row],[販売価格（M)]] | AB3: =tbl_明細[[#This Row],[販売価格（売値）]]*1.08+tbl_明細[[#This Row],[販売価格（M)]]*1.08
A4: 2601-1001-S01 | B4: =IF(ISBLANK(tbl_明細[[#This Row],[案件番号]]),"",COUNTIFS($A$3:A4,tbl_明細[[#This Row],[案件番号]],$AA$3:AA4,">0")) | C4: =COUNTIFS($A$3:A4,tbl_明細[[#This Row],[案件番号]],$F$3:F4,tbl_明細[[#This Row],[仕入先]]) | D4: =_xlfn.XLOOKUP(tbl_明細[[#This Row],[案件番号]],tbl_採番[案件番号],tbl_採番[顧客],"",0,1) | E4: other | F4: =IF(ISBLANK(tbl_明細[[#This Row],[仕入先（M)]]),_xlfn.XLOOKUP(tbl_明細[[#This Row],[商品ID]],商品マスタ[商品連番],商品マスタ[仕入先],"",0,1),tbl_明細[[#This Row],[仕入先（M)]]) | G4: =IF(ISBLANK(tbl_明細[[#This Row],[商品名（M)]]),_xlfn.XLOOKUP(tbl_明細[[#This Row],[商品ID]],商品マスタ[商品連番],商品マスタ[商品名],"",0,),tbl_明細[[#This Row],[商品名（M)]]) | H4: =IF(ISBLANK(tbl_明細[[#This Row],[仕入価格（M)]]),_xlfn.XLOOKUP(tbl_明細[[#This Row],[商品ID]],商品マスタ[商品連番],商品マスタ[仕入 単価],"",0,1),tbl_明細[[#This Row],[仕入価格（M)]]) | I4: =_xlfn.XLOOKUP(tbl_明細[[#This Row],[商品ID]],商品マスタ[商品連番],商品マスタ[国内定価 （15％）],"",0,1) | L4: =_xlfn.XLOOKUP(tbl_明細[[#This Row],[商品ID]],商品マスタ[商品連番],商品マスタ[単位],"",0,1) | M4: =1-tbl_明細[[#This Row],[仕入価格]]/tbl_明細[[#This Row],[販売価格（売値）]] | N4: =_xlfn.XLOOKUP(tbl_明細[[#This Row],[商品ID]],商品マスタ[商品連番],商品マスタ[税率],"",0,1) | O4: ソバージュド函館 | P4: 送料（北海道） | Q4: 1180 | R4: 1180 | S4: 1 | T4: 式 | U4: 0.1 | X4: =tbl_明細[[#This Row],[仕入価格]]*tbl_明細[[#This Row],[数量]]+tbl_明細[[#This Row],[仕入価格（M)]]*tbl_明細[[#This Row],[数量（M)]] | Y4: =tbl_明細[[#This Row],[販売価格（売値）]]*tbl_明細[[#This Row],[数量]]+tbl_明細[[#This Row],[販売価格（M)]]*tbl_明細[[#This Row],[数量（M)]] | Z4: =_xlfn.XLOOKUP(tbl_明細[[#This Row],[案件番号]],tbl_案件追跡[案件番号],tbl_案件追跡[受注],"",0,1) | AA4: =tbl_明細[[#This Row],[販売価格（売値）]]+tbl_明細[[#This Row],[販売価格（M)]] | AB4: =tbl_明細[[#This Row],[販売価格（売値）]]*1.08+tbl_明細[[#This Row],[販売価格（M)]]*1.08
A5: 2601-1001-S01 | B5: =IF(ISBLANK(tbl_明細[[#This Row],[案件番号]]),"",COUNTIFS($A$3:A5,tbl_明細[[#This Row],[案件番号]],$AA$3:AA5,">0")) | C5: =COUNTIFS($A$3:A5,tbl_明細[[#This Row],[案件番号]],$F$3:F5,tbl_明細[[#This Row],[仕入先]]) | D5: =_xlfn.XLOOKUP(tbl_明細[[#This Row],[案件番号]],tbl_採番[案件番号],tbl_採番[顧客],"",0,1) | E5: PRD_SNJ_SDH_0016_01 | F5: =IF(ISBLANK(tbl_明細[[#This Row],[仕入先（M)]]),_xlfn.XLOOKUP(tbl_明細[[#This Row],[商品ID]],商品マスタ[商品連番],商品マスタ[仕入先],"",0,1),tbl_明細[[#This Row],[仕入先（M)]]) | G5: =IF(ISBLANK(tbl_明細[[#This Row],[商品名（M)]]),_xlfn.XLOOKUP(tbl_明細[[#This Row],[商品ID]],商品マスタ[商品連番],商品マスタ[商品名],"",0,),tbl_明細[[#This Row],[商品名（M)]]) | H5: =IF(ISBLANK(tbl_明細[[#This Row],[仕入価格（M)]]),_xlfn.XLOOKUP(tbl_明細[[#This Row],[商品ID]],商品マスタ[商品連番],商品マスタ[仕入 単価],"",0,1),tbl_明細[[#This Row],[仕入価格（M)]]) | I5: =_xlfn.XLOOKUP(tbl_明細[[#This Row],[商品ID]],商品マスタ[商品連番],商品マスタ[国内定価 （15％）],"",0,1) | J5: 18000 | K5: 3.627 | L5: =_xlfn.XLOOKUP(tbl_明細[[#This Row],[商品ID]],商品マスタ[商品連番],商品マスタ[単位],"",0,1) | M5: =1-tbl_明細[[#This Row],[仕入価格]]/tbl_明細[[#This Row],[販売価格（売値）]] | N5: =_xlfn.XLOOKUP(tbl_明細[[#This Row],[商品ID]],商品マスタ[商品連番],商品マスタ[税率],"",0,1) | X5: =tbl_明細[[#This Row],[仕入価格]]*tbl_明細[[#This Row],[数量]]+tbl_明細[[#This Row],[仕入価格（M)]]*tbl_明細[[#This Row],[数量（M)]] | Y5: =tbl_明細[[#This Row],[販売価格（売値）]]*tbl_明細[[#This Row],[数量]]+tbl_明細[[#This Row],[販売価格（M)]]*tbl_明細[[#This Row],[数量（M)]] | Z5: =_xlfn.XLOOKUP(tbl_明細[[#This Row],[案件番号]],tbl_案件追跡[案件番号],tbl_案件追跡[受注],"",0,1) | AA5: =tbl_明細[[#This Row],[販売価格（売値）]]+tbl_明細[[#This Row],[販売価格（M)]] | AB5: =tbl_明細[[#This Row],[販売価格（売値）]]*1.08+tbl_明細[[#This Row],[販売価格（M)]]*1.08
A6: 2601-1001-S01 | B6: =IF(ISBLANK(tbl_明細[[#This Row],[案件番号]]),"",COUNTIFS($A$3:A6,tbl_明細[[#This Row],[案件番号]],$AA$3:AA6,">0")) | C6: =COUNTIFS($A$3:A6,tbl_明細[[#This Row],[案件番号]],$F$3:F6,tbl_明細[[#This Row],[仕入先]]) | D6: =_xlfn.XLOOKUP(tbl_明細[[#This Row],[案件番号]],tbl_採番[案件番号],tbl_採番[顧客],"",0,1) | E6: other | F6: =IF(ISBLANK(tbl_明細[[#This Row],[仕入先（M)]]),_xlfn.XLOOKUP(tbl_明細[[#This Row],[商品ID]],商品マスタ[商品連番],商品マスタ[仕入先],"",0,1),tbl_明細[[#This Row],[仕入先（M)]]) | G6: =IF(ISBLANK(tbl_明細[[#This Row],[商品名（M)]]),_xlfn.XLOOKUP(tbl_明細[[#This Row],[商品ID]],商品マスタ[商品連番],商品マスタ[商品名],"",0,),tbl_明細[[#This Row],[商品名（M)]]) | H6: =IF(ISBLANK(tbl_明細[[#This Row],[仕入価格（M)]]),_xlfn.XLOOKUP(tbl_明細[[#This Row],[商品ID]],商品マスタ[商品連番],商品マスタ[仕入 単価],"",0,1),tbl_明細[[#This Row],[仕入価格（M)]]) | I6: =_xlfn.XLOOKUP(tbl_明細[[#This Row],[商品ID]],商品マスタ[商品連番],商品マスタ[国内定価 （15％）],"",0,1) | L6: =_xlfn.XLOOKUP(tbl_明細[[#This Row],[商品ID]],商品マスタ[商品連番],商品マスタ[単位],"",0,1) | M6: =1-tbl_明細[[#This Row],[仕入価格]]/tbl_明細[[#This Row],[販売価格（売値）]] | N6: =_xlfn.XLOOKUP(tbl_明細[[#This Row],[商品ID]],商品マスタ[商品連番],商品マスタ[税率],"",0,1) | O6: ソバージュド函館 | P6: 送料（北海道） | Q6: 1180 | R6: 1180 | S6: 1 | T6: 式 | U6: 0.1 | X6: =tbl_明細[[#This Row],[仕入価格]]*tbl_明細[[#This Row],[数量]]+tbl_明細[[#This Row],[仕入価格（M)]]*tbl_明細[[#This Row],[数量（M)]] | Y6: =tbl_明細[[#This Row],[販売価格（売値）]]*tbl_明細[[#This Row],[数量]]+tbl_明細[[#This Row],[販売価格（M)]]*tbl_明細[[#This Row],[数量（M)]] | Z6: =_xlfn.XLOOKUP(tbl_明細[[#This Row],[案件番号]],tbl_案件追跡[案件番号],tbl_案件追跡[受注],"",0,1) | AA6: =tbl_明細[[#This Row],[販売価格（売値）]]+tbl_明細[[#This Row],[販売価格（M)]] | AB6: =tbl_明細[[#This Row],[販売価格（売値）]]*1.08+tbl_明細[[#This Row],[販売価格（M)]]*1.08
A7: 2601-1001-S01 | B7: =IF(ISBLANK(tbl_明細[[#This Row],[案件番号]]),"",COUNTIFS($A$3:A7,tbl_明細[[#This Row],[案件番号]],$AA$3:AA7,">0")) | C7: =COUNTIFS($A$3:A7,tbl_明細[[#This Row],[案件番号]],$F$3:F7,tbl_明細[[#This Row],[仕入先]]) | D7: =_xlfn.XLOOKUP(tbl_明細[[#This Row],[案件番号]],tbl_採番[案件番号],tbl_採番[顧客],"",0,1) | E7: PRD_SNJ_SDH_0016_01 | F7: =IF(ISBLANK(tbl_明細[[#This Row],[仕入先（M)]]),_xlfn.XLOOKUP(tbl_明細[[#This Row],[商品ID]],商品マスタ[商品連番],商品マスタ[仕入先],"",0,1),tbl_明細[[#This Row],[仕入先（M)]]) | G7: =IF(ISBLANK(tbl_明細[[#This Row],[商品名（M)]]),_xlfn.XLOOKUP(tbl_明細[[#This Row],[商品ID]],商品マスタ[商品連番],商品マスタ[商品名],"",0,),tbl_明細[[#This Row],[商品名（M)]]) | H7: =IF(ISBLANK(tbl_明細[[#This Row],[仕入価格（M)]]),_xlfn.XLOOKUP(tbl_明細[[#This Row],[商品ID]],商品マスタ[商品連番],商品マスタ[仕入 単価],"",0,1),tbl_明細[[#This Row],[仕入価格（M)]]) | I7: =_xlfn.XLOOKUP(tbl_明細[[#This Row],[商品ID]],商品マスタ[商品連番],商品マスタ[国内定価 （15％）],"",0,1) | J7: 18000 | K7: 0.911 | L7: =_xlfn.XLOOKUP(tbl_明細[[#This Row],[商品ID]],商品マスタ[商品連番],商品マスタ[単位],"",0,1) | M7: =1-tbl_明細[[#This Row],[仕入価格]]/tbl_明細[[#This Row],[販売価格（売値）]] | N7: =_xlfn.XLOOKUP(tbl_明細[[#This Row],[商品ID]],商品マスタ[商品連番],商品マスタ[税率],"",0,1) | X7: =tbl_明細[[#This Row],[仕入価格]]*tbl_明細[[#This Row],[数量]]+tbl_明細[[#This Row],[仕入価格（M)]]*tbl_明細[[#This Row],[数量（M)]] | Y7: =tbl_明細[[#This Row],[販売価格（売値）]]*tbl_明細[[#This Row],[数量]]+tbl_明細[[#This Row],[販売価格（M)]]*tbl_明細[[#This Row],[数量（M)]] | Z7: =_xlfn.XLOOKUP(tbl_明細[[#This Row],[案件番号]],tbl_案件追跡[案件番号],tbl_案件追跡[受注],"",0,1) | AA7: =tbl_明細[[#This Row],[販売価格（売値）]]+tbl_明細[[#This Row],[販売価格（M)]] | AB7: =tbl_明細[[#This Row],[販売価格（売値）]]*1.08+tbl_明細[[#This Row],[販売価格（M)]]*1.08
A8: 2601-1001-S01 | B8: =IF(ISBLANK(tbl_明細[[#This Row],[案件番号]]),"",COUNTIFS($A$3:A8,tbl_明細[[#This Row],[案件番号]],$AA$3:AA8,">0")) | C8: =COUNTIFS($A$3:A8,tbl_明細[[#This Row],[案件番号]],$F$3:F8,tbl_明細[[#This Row],[仕入先]]) | D8: =_xlfn.XLOOKUP(tbl_明細[[#This Row],[案件番号]],tbl_採番[案件番号],tbl_採番[顧客],"",0,1) | E8: other | F8: =IF(ISBLANK(tbl_明細[[#This Row],[仕入先（M)]]),_xlfn.XLOOKUP(tbl_明細[[#This Row],[商品ID]],商品マスタ[商品連番],商品マスタ[仕入先],"",0,1),tbl_明細[[#This Row],[仕入先（M)]]) | G8: =IF(ISBLANK(tbl_明細[[#This Row],[商品名（M)]]),_xlfn.XLOOKUP(tbl_明細[[#This Row],[商品ID]],商品マスタ[商品連番],商品マスタ[商品名],"",0,),tbl_明細[[#This Row],[商品名（M)]]) | H8: =IF(ISBLANK(tbl_明細[[#This Row],[仕入価格（M)]]),_xlfn.XLOOKUP(tbl_明細[[#This Row],[商品ID]],商品マスタ[商品連番],商品マスタ[仕入 単価],"",0,1),tbl_明細[[#This Row],[仕入価格（M)]]) | I8: =_xlfn.XLOOKUP(tbl_明細[[#This Row],[商品ID]],商品マスタ[商品連番],商品マスタ[国内定価 （15％）],"",0,1) | L8: =_xlfn.XLOOKUP(tbl_明細[[#This Row],[商品ID]],商品マスタ[商品連番],商品マスタ[単位],"",0,1) | M8: =1-tbl_明細[[#This Row],[仕入価格]]/tbl_明細[[#This Row],[販売価格（売値）]] | N8: =_xlfn.XLOOKUP(tbl_明細[[#This Row],[商品ID]],商品マスタ[商品連番],商品マスタ[税率],"",0,1) | O8: ソバージュド函館 | P8: 送料（北海道） | Q8: 1180 | R8: 1180 | S8: 1 | T8: 式 | U8: 0.1 | X8: =tbl_明細[[#This Row],[仕入価格]]*tbl_明細[[#This Row],[数量]]+tbl_明細[[#This Row],[仕入価格（M)]]*tbl_明細[[#This Row],[数量（M)]] | Y8: =tbl_明細[[#This Row],[販売価格（売値）]]*tbl_明細[[#This Row],[数量]]+tbl_明細[[#This Row],[販売価格（M)]]*tbl_明細[[#This Row],[数量（M)]] | Z8: =_xlfn.XLOOKUP(tbl_明細[[#This Row],[案件番号]],tbl_案件追跡[案件番号],tbl_案件追跡[受注],"",0,1) | AA8: =tbl_明細[[#This Row],[販売価格（売値）]]+tbl_明細[[#This Row],[販売価格（M)]] | AB8: =tbl_明細[[#This Row],[販売価格（売値）]]*1.08+tbl_明細[[#This Row],[販売価格（M)]]*1.08
A9: 2601-1002-S01 | B9: =IF(ISBLANK(tbl_明細[[#This Row],[案件番号]]),"",COUNTIFS($A$3:A9,tbl_明細[[#This Row],[案件番号]],$AA$3:AA9,">0")) | C9: =COUNTIFS($A$3:A9,tbl_明細[[#This Row],[案件番号]],$F$3:F9,tbl_明細[[#This Row],[仕入先]]) | D9: =_xlfn.XLOOKUP(tbl_明細[[#This Row],[案件番号]],tbl_採番[案件番号],tbl_採番[顧客],"",0,1) | E9: PRD_SNJ_KDK_0001_01 | F9: =IF(ISBLANK(tbl_明細[[#This Row],[仕入先（M)]]),_xlfn.XLOOKUP(tbl_明細[[#This Row],[商品ID]],商品マスタ[商品連番],商品マスタ[仕入先],"",0,1),tbl_明細[[#This Row],[仕入先（M)]]) | G9: =IF(ISBLANK(tbl_明細[[#This Row],[商品名（M)]]),_xlfn.XLOOKUP(tbl_明細[[#This Row],[商品ID]],商品マスタ[商品連番],商品マスタ[商品名],"",0,),tbl_明細[[#This Row],[商品名（M)]]) | H9: =IF(ISBLANK(tbl_明細[[#This Row],[仕入価格（M)]]),_xlfn.XLOOKUP(tbl_明細[[#This Row],[商品ID]],商品マスタ[商品連番],商品マスタ[仕入 単価],"",0,1),tbl_明細[[#This Row],[仕入価格（M)]]) | I9: =_xlfn.XLOOKUP(tbl_明細[[#This Row],[商品ID]],商品マスタ[商品連番],商品マスタ[国内定価 （15％）],"",0,1) | J9: 24000 | K9: 1.289 | L9: =_xlfn.XLOOKUP(tbl_明細[[#This Row],[商品ID]],商品マスタ[商品連番],商品マスタ[単位],"",0,1) | M9: =1-tbl_明細[[#This Row],[仕入価格]]/tbl_明細[[#This Row],[販売価格（売値）]] | N9: =_xlfn.XLOOKUP(tbl_明細[[#This Row],[商品ID]],商品マスタ[商品連番],商品マスタ[税率],"",0,1) | X9: =tbl_明細[[#This Row],[仕入価格]]*tbl_明細[[#This Row],[数量]]+tbl_明細[[#This Row],[仕入価格（M)]]*tbl_明細[[#This Row],[数量（M)]] | Y9: =tbl_明細[[#This Row],[販売価格（売値）]]*tbl_明細[[#This Row],[数量]]+tbl_明細[[#This Row],[販売価格（M)]]*tbl_明細[[#This Row],[数量（M)]] | Z9: =_xlfn.XLOOKUP(tbl_明細[[#This Row],[案件番号]],tbl_案件追跡[案件番号],tbl_案件追跡[受注],"",0,1) | AA9: =tbl_明細[[#This Row],[販売価格（売値）]]+tbl_明細[[#This Row],[販売価格（M)]] | AB9: =tbl_明細[[#This Row],[販売価格（売値）]]*1.08+tbl_明細[[#This Row],[販売価格（M)]]*1.08
A10: 2601-1002-S01 | B10: =IF(ISBLANK(tbl_明細[[#This Row],[案件番号]]),"",COUNTIFS($A$3:A10,tbl_明細[[#This Row],[案件番号]],$AA$3:AA10,">0")) | C10: =COUNTIFS($A$3:A10,tbl_明細[[#This Row],[案件番号]],$F$3:F10,tbl_明細[[#This Row],[仕入先]]) | D10: =_xlfn.XLOOKUP(tbl_明細[[#This Row],[案件番号]],tbl_採番[案件番号],tbl_採番[顧客],"",0,1) | E10: PRD_SNJ_KDK_0001_01 | F10: =IF(ISBLANK(tbl_明細[[#This Row],[仕入先（M)]]),_xlfn.XLOOKUP(tbl_明細[[#This Row],[商品ID]],商品マスタ[商品連番],商品マスタ[仕入先],"",0,1),tbl_明細[[#This Row],[仕入先（M)]]) | G10: =IF(ISBLANK(tbl_明細[[#This Row],[商品名（M)]]),_xlfn.XLOOKUP(tbl_明細[[#This Row],[商品ID]],商品マスタ[商品連番],商品マスタ[商品名],"",0,),tbl_明細[[#This Row],[商品名（M)]]) | H10: =IF(ISBLANK(tbl_明細[[#This Row],[仕入価格（M)]]),_xlfn.XLOOKUP(tbl_明細[[#This Row],[商品ID]],商品マスタ[商品連番],商品マスタ[仕入 単価],"",0,1),tbl_明細[[#This Row],[仕入価格（M)]]) | I10: =_xlfn.XLOOKUP(tbl_明細[[#This Row],[商品ID]],商品マスタ[商品連番],商品マスタ[国内定価 （15％）],"",0,1) | J10: 24000 | K10: 1.177 | L10: =_xlfn.XLOOKUP(tbl_明細[[#This Row],[商品ID]],商品マスタ[商品連番],商品マスタ[単位],"",0,1) | M10: =1-tbl_明細[[#This Row],[仕入価格]]/tbl_明細[[#This Row],[販売価格（売値）]] | N10: =_xlfn.XLOOKUP(tbl_明細[[#This Row],[商品ID]],商品マスタ[商品連番],商品マスタ[税率],"",0,1) | X10: =tbl_明細[[#This Row],[仕入価格]]*tbl_明細[[#This Row],[数量]]+tbl_明細[[#This Row],[仕入価格（M)]]*tbl_明細[[#This Row],[数量（M)]] | Y10: =tbl_明細[[#This Row],[販売価格（売値）]]*tbl_明細[[#This Row],[数量]]+tbl_明細[[#This Row],[販売価格（M)]]*tbl_明細[[#This Row],[数量（M)]] | Z10: =_xlfn.XLOOKUP(tbl_明細[[#This Row],[案件番号]],tbl_案件追跡[案件番号],tbl_案件追跡[受注],"",0,1) | AA10: =tbl_明細[[#This Row],[販売価格（売値）]]+tbl_明細[[#This Row],[販売価格（M)]] | AB10: =tbl_明細[[#This Row],[販売価格（売値）]]*1.08+tbl_明細[[#This Row],[販売価格（M)]]*1.08
A11: 2601-1002-S01 | B11: =IF(ISBLANK(tbl_明細[[#This Row],[案件番号]]),"",COUNTIFS($A$3:A11,tbl_明細[[#This Row],[案件番号]],$AA$3:AA11,">0")) | C11: =COUNTIFS($A$3:A11,tbl_明細[[#This Row],[案件番号]],$F$3:F11,tbl_明細[[#This Row],[仕入先]]) | D11: =_xlfn.XLOOKUP(tbl_明細[[#This Row],[案件番号]],tbl_採番[案件番号],tbl_採番[顧客],"",0,1) | E11: PRD_SNJ_KDK_0001_01 | F11: =IF(ISBLANK(tbl_明細[[#This Row],[仕入先（M)]]),_xlfn.XLOOKUP(tbl_明細[[#This Row],[商品ID]],商品マスタ[商品連番],商品マスタ[仕入先],"",0,1),tbl_明細[[#This Row],[仕入先（M)]]) | G11: =IF(ISBLANK(tbl_明細[[#This Row],[商品名（M)]]),_xlfn.XLOOKUP(tbl_明細[[#This Row],[商品ID]],商品マスタ[商品連番],商品マスタ[商品名],"",0,),tbl_明細[[#This Row],[商品名（M)]]) | H11: =IF(ISBLANK(tbl_明細[[#This Row],[仕入価格（M)]]),_xlfn.XLOOKUP(tbl_明細[[#This Row],[商品ID]],商品マスタ[商品連番],商品マスタ[仕入 単価],"",0,1),tbl_明細[[#This Row],[仕入価格（M)]]) | I11: =_xlfn.XLOOKUP(tbl_明細[[#This Row],[商品ID]],商品マスタ[商品連番],商品マスタ[国内定価 （15％）],"",0,1) | J11: 24000 | K11: 0.506 | L11: =_xlfn.XLOOKUP(tbl_明細[[#This Row],[商品ID]],商品マスタ[商品連番],商品マスタ[単位],"",0,1) | M11: =1-tbl_明細[[#This Row],[仕入価格]]/tbl_明細[[#This Row],[販売価格（売値）]] | N11: =_xlfn.XLOOKUP(tbl_明細[[#This Row],[商品ID]],商品マスタ[商品連番],商品マスタ[税率],"",0,1) | X11: =tbl_明細[[#This Row],[仕入価格]]*tbl_明細[[#This Row],[数量]]+tbl_明細[[#This Row],[仕入価格（M)]]*tbl_明細[[#This Row],[数量（M)]] | Y11: =tbl_明細[[#This Row],[販売価格（売値）]]*tbl_明細[[#This Row],[数量]]+tbl_明細[[#This Row],[販売価格（M)]]*tbl_明細[[#This Row],[数量（M)]] | Z11: =_xlfn.XLOOKUP(tbl_明細[[#This Row],[案件番号]],tbl_案件追跡[案件番号],tbl_案件追跡[受注],"",0,1) | AA11: =tbl_明細[[#This Row],[販売価格（売値）]]+tbl_明細[[#This Row],[販売価格（M)]] | AB11: =tbl_明細[[#This Row],[販売価格（売値）]]*1.08+tbl_明細[[#This Row],[販売価格（M)]]*1.08
A12: 2601-1002-S01 | B12: =IF(ISBLANK(tbl_明細[[#This Row],[案件番号]]),"",COUNTIFS($A$3:A12,tbl_明細[[#This Row],[案件番号]],$AA$3:AA12,">0")) | C12: =COUNTIFS($A$3:A12,tbl_明細[[#This Row],[案件番号]],$F$3:F12,tbl_明細[[#This Row],[仕入先]]) | D12: =_xlfn.XLOOKUP(tbl_明細[[#This Row],[案件番号]],tbl_採番[案件番号],tbl_採番[顧客],"",0,1) | E12: PRD_SNJ_KDK_0001_01 | F12: =IF(ISBLANK(tbl_明細[[#This Row],[仕入先（M)]]),_xlfn.XLOOKUP(tbl_明細[[#This Row],[商品ID]],商品マスタ[商品連番],商品マスタ[仕入先],"",0,1),tbl_明細[[#This Row],[仕入先（M)]]) | G12: =IF(ISBLANK(tbl_明細[[#This Row],[商品名（M)]]),_xlfn.XLOOKUP(tbl_明細[[#This Row],[商品ID]],商品マスタ[商品連番],商品マスタ[商品名],"",0,),tbl_明細[[#This Row],[商品名（M)]]) | H12: =IF(ISBLANK(tbl_明細[[#This Row],[仕入価格（M)]]),_xlfn.XLOOKUP(tbl_明細[[#This Row],[商品ID]],商品マスタ[商品連番],商品マスタ[仕入 単価],"",0,1),tbl_明細[[#This Row],[仕入価格（M)]]) | I12: =_xlfn.XLOOKUP(tbl_明細[[#This Row],[商品ID]],商品マスタ[商品連番],商品マスタ[国内定価 （15％）],"",0,1) | J12: 24000 | K12: 0.815 | L12: =_xlfn.XLOOKUP(tbl_明細[[#This Row],[商品ID]],商品マスタ[商品連番],商品マスタ[単位],"",0,1) | M12: =1-tbl_明細[[#This Row],[仕入価格]]/tbl_明細[[#This Row],[販売価格（売値）]] | N12: =_xlfn.XLOOKUP(tbl_明細[[#This Row],[商品ID]],商品マスタ[商品連番],商品マスタ[税率],"",0,1) | X12: =tbl_明細[[#This Row],[仕入価格]]*tbl_明細[[#This Row],[数量]]+tbl_明細[[#This Row],[仕入価格（M)]]*tbl_明細[[#This Row],[数量（M)]] | Y12: =tbl_明細[[#This Row],[販売価格（売値）]]*tbl_明細[[#This Row],[数量]]+tbl_明細[[#This Row],[販売価格（M)]]*tbl_明細[[#This Row],[数量（M)]] | Z12: =_xlfn.XLOOKUP(tbl_明細[[#This Row],[案件番号]],tbl_案件追跡[案件番号],tbl_案件追跡[受注],"",0,1) | AA12: =tbl_明細[[#This Row],[販売価格（売値）]]+tbl_明細[[#This Row],[販売価格（M)]] | AB12: =tbl_明細[[#This Row],[販売価格（売値）]]*1.08+tbl_明細[[#This Row],[販売価格（M)]]*1.08
A13: 2601-1002-S01 | B13: =IF(ISBLANK(tbl_明細[[#This Row],[案件番号]]),"",COUNTIFS($A$3:A13,tbl_明細[[#This Row],[案件番号]],$AA$3:AA13,">0")) | C13: =COUNTIFS($A$3:A13,tbl_明細[[#This Row],[案件番号]],$F$3:F13,tbl_明細[[#This Row],[仕入先]]) | D13: =_xlfn.XLOOKUP(tbl_明細[[#This Row],[案件番号]],tbl_採番[案件番号],tbl_採番[顧客],"",0,1) | E13: other | F13: =IF(ISBLANK(tbl_明細[[#This Row],[仕入先（M)]]),_xlfn.XLOOKUP(tbl_明細[[#This Row],[商品ID]],商品マスタ[商品連番],商品マスタ[仕入先],"",0,1),tbl_明細[[#This Row],[仕入先（M)]]) | G13: =IF(ISBLANK(tbl_明細[[#This Row],[商品名（M)]]),_xlfn.XLOOKUP(tbl_明細[[#This Row],[商品ID]],商品マスタ[商品連番],商品マスタ[商品名],"",0,),tbl_明細[[#This Row],[商品名（M)]]) | H13: =IF(ISBLANK(tbl_明細[[#This Row],[仕入価格（M)]]),_xlfn.XLOOKUP(tbl_明細[[#This Row],[商品ID]],商品マスタ[商品連番],商品マスタ[仕入 単価],"",0,1),tbl_明細[[#This Row],[仕入価格（M)]]) | I13: =_xlfn.XLOOKUP(tbl_明細[[#This Row],[商品ID]],商品マスタ[商品連番],商品マスタ[国内定価 （15％）],"",0,1) | L13: =_xlfn.XLOOKUP(tbl_明細[[#This Row],[商品ID]],商品マスタ[商品連番],商品マスタ[単位],"",0,1) | M13: =1-tbl_明細[[#This Row],[仕入価格]]/tbl_明細[[#This Row],[販売価格（売値）]] | N13: =_xlfn.XLOOKUP(tbl_明細[[#This Row],[商品ID]],商品マスタ[商品連番],商品マスタ[税率],"",0,1) | O13: 狩人の蔵 | P13: 送料（大阪） | Q13: 1620 | R13: 1620 | S13: 1 | T13: 式 | U13: 0.1 | X13: =tbl_明細[[#This Row],[仕入価格]]*tbl_明細[[#This Row],[数量]]+tbl_明細[[#This Row],[仕入価格（M)]]*tbl_明細[[#This Row],[数量（M)]] | Y13: =tbl_明細[[#This Row],[販売価格（売値）]]*tbl_明細[[#This Row],[数量]]+tbl_明細[[#This Row],[販売価格（M)]]*tbl_明細[[#This Row],[数量（M)]] | Z13: =_xlfn.XLOOKUP(tbl_明細[[#This Row],[案件番号]],tbl_案件追跡[案件番号],tbl_案件追跡[受注],"",0,1) | AA13: =tbl_明細[[#This Row],[販売価格（売値）]]+tbl_明細[[#This Row],[販売価格（M)]] | AB13: =tbl_明細[[#This Row],[販売価格（売値）]]*1.08+tbl_明細[[#This Row],[販売価格（M)]]*1.08
A14: 2601-1003-A01 | B14: =IF(ISBLANK(tbl_明細[[#This Row],[案件番号]]),"",COUNTIFS($A$3:A14,tbl_明細[[#This Row],[案件番号]],$AA$3:AA14,">0")) | C14: =COUNTIFS($A$3:A14,tbl_明細[[#This Row],[案件番号]],$F$3:F14,tbl_明細[[#This Row],[仕入先]]) | D14: =_xlfn.XLOOKUP(tbl_明細[[#This Row],[案件番号]],tbl_採番[案件番号],tbl_採番[顧客],"",0,1) | E14: PRD_SNJ_KYS_0005_01 | F14: =IF(ISBLANK(tbl_明細[[#This Row],[仕入先（M)]]),_xlfn.XLOOKUP(tbl_明細[[#This Row],[商品ID]],商品マスタ[商品連番],商品マスタ[仕入先],"",0,1),tbl_明細[[#This Row],[仕入先（M)]]) | G14: =IF(ISBLANK(tbl_明細[[#This Row],[商品名（M)]]),_xlfn.XLOOKUP(tbl_明細[[#This Row],[商品ID]],商品マスタ[商品連番],商品マスタ[商品名],"",0,),tbl_明細[[#This Row],[商品名（M)]]) | H14: =IF(ISBLANK(tbl_明細[[#This Row],[仕入価格（M)]]),_xlfn.XLOOKUP(tbl_明細[[#This Row],[商品ID]],商品マスタ[商品連番],商品マスタ[仕入 単価],"",0,1),tbl_明細[[#This Row],[仕入価格（M)]]) | I14: =_xlfn.XLOOKUP(tbl_明細[[#This Row],[商品ID]],商品マスタ[商品連番],商品マスタ[国内定価 （15％）],"",0,1) | J14: 1806 | K14: 10 | L14: =_xlfn.XLOOKUP(tbl_明細[[#This Row],[商品ID]],商品マスタ[商品連番],商品マスタ[単位],"",0,1) | M14: =1-tbl_明細[[#This Row],[仕入価格]]/tbl_明細[[#This Row],[販売価格（売値）]] | N14: =_xlfn.XLOOKUP(tbl_明細[[#This Row],[商品ID]],商品マスタ[商品連番],商品マスタ[税率],"",0,1) | X14: =tbl_明細[[#This Row],[仕入価格]]*tbl_明細[[#This Row],[数量]]+tbl_明細[[#This Row],[仕入価格（M)]]*tbl_明細[[#This Row],[数量（M)]] | Y14: =tbl_明細[[#This Row],[販売価格（売値）]]*tbl_明細[[#This Row],[数量]]+tbl_明細[[#This Row],[販売価格（M)]]*tbl_明細[[#This Row],[数量（M)]] | Z14: =_xlfn.XLOOKUP(tbl_明細[[#This Row],[案件番号]],tbl_案件追跡[案件番号],tbl_案件追跡[受注],"",0,1) | AA14: =tbl_明細[[#This Row],[販売価格（売値）]]+tbl_明細[[#This Row],[販売価格（M)]] | AB14: =tbl_明細[[#This Row],[販売価格（売値）]]*1.08+tbl_明細[[#This Row],[販売価格（M)]]*1.08
A15: 2601-1003-A01 | B15: =IF(ISBLANK(tbl_明細[[#This Row],[案件番号]]),"",COUNTIFS($A$3:A15,tbl_明細[[#This Row],[案件番号]],$AA$3:AA15,">0")) | C15: =COUNTIFS($A$3:A15,tbl_明細[[#This Row],[案件番号]],$F$3:F15,tbl_明細[[#This Row],[仕入先]]) | D15: =_xlfn.XLOOKUP(tbl_明細[[#This Row],[案件番号]],tbl_採番[案件番号],tbl_採番[顧客],"",0,1) | E15: other | F15: =IF(ISBLANK(tbl_明細[[#This Row],[仕入先（M)]]),_xlfn.XLOOKUP(tbl_明細[[#This Row],[商品ID]],商品マスタ[商品連番],商品マスタ[仕入先],"",0,1),tbl_明細[[#This Row],[仕入先（M)]]) | G15: =IF(ISBLANK(tbl_明細[[#This Row],[商品名（M)]]),_xlfn.XLOOKUP(tbl_明細[[#This Row],[商品ID]],商品マスタ[商品連番],商品マスタ[商品名],"",0,),tbl_明細[[#This Row],[商品名（M)]]) | H15: =IF(ISBLANK(tbl_明細[[#This Row],[仕入価格（M)]]),_xlfn.XLOOKUP(tbl_明細[[#This Row],[商品ID]],商品マスタ[商品連番],商品マスタ[仕入 単価],"",0,1),tbl_明細[[#This Row],[仕入価格（M)]]) | I15: =_xlfn.XLOOKUP(tbl_明細[[#This Row],[商品ID]],商品マスタ[商品連番],商品マスタ[国内定価 （15％）],"",0,1) | L15: =_xlfn.XLOOKUP(tbl_明細[[#This Row],[商品ID]],商品マスタ[商品連番],商品マスタ[単位],"",0,1) | M15: =1-tbl_明細[[#This Row],[仕入価格]]/tbl_明細[[#This Row],[販売価格（売値）]] | N15: =_xlfn.XLOOKUP(tbl_明細[[#This Row],[商品ID]],商品マスタ[商品連番],商品マスタ[税率],"",0,1) | O15: 協栄製茶 壱之庄 | P15: 送料（140サイズ） | Q15: 1300 | R15: 1300 | S15: 1 | T15: 式 | U15: 0.1 | X15: =tbl_明細[[#This Row],[仕入価格]]*tbl_明細[[#This Row],[数量]]+tbl_明細[[#This Row],[仕入価格（M)]]*tbl_明細[[#This Row],[数量（M)]] | Y15: =tbl_明細[[#This Row],[販売価格（売値）]]*tbl_明細[[#This Row],[数量]]+tbl_明細[[#This Row],[販売価格（M)]]*tbl_明細[[#This Row],[数量（M)]] | Z15: =_xlfn.XLOOKUP(tbl_明細[[#This Row],[案件番号]],tbl_案件追跡[案件番号],tbl_案件追跡[受注],"",0,1) | AA15: =tbl_明細[[#This Row],[販売価格（売値）]]+tbl_明細[[#This Row],[販売価格（M)]] | AB15: =tbl_明細[[#This Row],[販売価格（売値）]]*1.08+tbl_明細[[#This Row],[販売価格（M)]]*1.08
A16: 2601-1004-S01 | B16: =IF(ISBLANK(tbl_明細[[#This Row],[案件番号]]),"",COUNTIFS($A$3:A16,tbl_明細[[#This Row],[案件番号]],$AA$3:AA16,">0")) | C16: =COUNTIFS($A$3:A16,tbl_明細[[#This Row],[案件番号]],$F$3:F16,tbl_明細[[#This Row],[仕入先]]) | D16: =_xlfn.XLOOKUP(tbl_明細[[#This Row],[案件番号]],tbl_採番[案件番号],tbl_採番[顧客],"",0,1) | E16: PRD_SNJ_APK_0002_01 | F16: =IF(ISBLANK(tbl_明細[[#This Row],[仕入先（M)]]),_xlfn.XLOOKUP(tbl_明細[[#This Row],[商品ID]],商品マスタ[商品連番],商品マスタ[仕入先],"",0,1),tbl_明細[[#This Row],[仕入先（M)]]) | G16: =IF(ISBLANK(tbl_明細[[#This Row],[商品名（M)]]),_xlfn.XLOOKUP(tbl_明細[[#This Row],[商品ID]],商品マスタ[商品連番],商品マスタ[商品名],"",0,),tbl_明細[[#This Row],[商品名（M)]]) | H16: =IF(ISBLANK(tbl_明細[[#This Row],[仕入価格（M)]]),_xlfn.XLOOKUP(tbl_明細[[#This Row],[商品ID]],商品マスタ[商品連番],商品マスタ[仕入 単価],"",0,1),tbl_明細[[#This Row],[仕入価格（M)]]) | I16: =_xlfn.XLOOKUP(tbl_明細[[#This Row],[商品ID]],商品マスタ[商品連番],商品マスタ[国内定価 （15％）],"",0,1) | J16: 5300 | K16: 5 | L16: =_xlfn.XLOOKUP(tbl_明細[[#This Row],[商品ID]],商品マスタ[商品連番],商品マスタ[単位],"",0,1) | M16: =1-tbl_明細[[#This Row],[仕入価格]]/tbl_明細[[#This Row],[販売価格（売値）]] | N16: =_xlfn.XLOOKUP(tbl_明細[[#This Row],[商品ID]],商品マスタ[商品連番],商品マスタ[税率],"",0,1) | X16: =tbl_明細[[#This Row],[仕入価格]]*tbl_明細[[#This Row],[数量]]+tbl_明細[[#This Row],[仕入価格（M)]]*tbl_明細[[#This Row],[数量（M)]] | Y16: =tbl_明細[[#This Row],[販売価格（売値）]]*tbl_明細[[#This Row],[数量]]+tbl_明細[[#This Row],[販売価格（M)]]*tbl_明細[[#This Row],[数量（M)]] | Z16: =_xlfn.XLOOKUP(tbl_明細[[#This Row],[案件番号]],tbl_案件追跡[案件番号],tbl_案件追跡[受注],"",0,1) | AA16: =tbl_明細[[#This Row],[販売価格（売値）]]+tbl_明細[[#This Row],[販売価格（M)]] | AB16: =tbl_明細[[#This Row],[販売価格（売値）]]*1.08+tbl_明細[[#This Row],[販売価格（M)]]*1.08
A17: 2601-1004-S01 | B17: =IF(ISBLANK(tbl_明細[[#This Row],[案件番号]]),"",COUNTIFS($A$3:A17,tbl_明細[[#This Row],[案件番号]],$AA$3:AA17,">0")) | C17: =COUNTIFS($A$3:A17,tbl_明細[[#This Row],[案件番号]],$F$3:F17,tbl_明細[[#This Row],[仕入先]]) | D17: =_xlfn.XLOOKUP(tbl_明細[[#This Row],[案件番号]],tbl_採番[案件番号],tbl_採番[顧客],"",0,1) | E17: other | F17: =IF(ISBLANK(tbl_明細[[#This Row],[仕入先（M)]]),_xlfn.XLOOKUP(tbl_明細[[#This Row],[商品ID]],商品マスタ[商品連番],商品マスタ[仕入先],"",0,1),tbl_明細[[#This Row],[仕入先（M)]]) | G17: =IF(ISBLANK(tbl_明細[[#This Row],[商品名（M)]]),_xlfn.XLOOKUP(tbl_明細[[#This Row],[商品ID]],商品マスタ[商品連番],商品マスタ[商品名],"",0,),tbl_明細[[#This Row],[商品名（M)]]) | H17: =IF(ISBLANK(tbl_明細[[#This Row],[仕入価格（M)]]),_xlfn.XLOOKUP(tbl_明細[[#This Row],[商品ID]],商品マスタ[商品連番],商品マスタ[仕入 単価],"",0,1),tbl_明細[[#This Row],[仕入価格（M)]]) | I17: =_xlfn.XLOOKUP(tbl_明細[[#This Row],[商品ID]],商品マスタ[商品連番],商品マスタ[国内定価 （15％）],"",0,1) | L17: =_xlfn.XLOOKUP(tbl_明細[[#This Row],[商品ID]],商品マスタ[商品連番],商品マスタ[単位],"",0,1) | M17: =1-tbl_明細[[#This Row],[仕入価格]]/tbl_明細[[#This Row],[販売価格（売値）]] | N17: =_xlfn.XLOOKUP(tbl_明細[[#This Row],[商品ID]],商品マスタ[商品連番],商品マスタ[税率],"",0,1) | O17: あぷかの森 | P17: 送料（大阪） | Q17: 2060 | R17: 2060 | S17: 1 | T17: 式 | U17: 0.1 | X17: =tbl_明細[[#This Row],[仕入価格]]*tbl_明細[[#This Row],[数量]]+tbl_明細[[#This Row],[仕入価格（M)]]*tbl_明細[[#This Row],[数量（M)]] | Y17: =tbl_明細[[#This Row],[販売価格（売値）]]*tbl_明細[[#This Row],[数量]]+tbl_明細[[#This Row],[販売価格（M)]]*tbl_明細[[#This Row],[数量（M)]] | Z17: =_xlfn.XLOOKUP(tbl_明細[[#This Row],[案件番号]],tbl_案件追跡[案件番号],tbl_案件追跡[受注],"",0,1) | AA17: =tbl_明細[[#This Row],[販売価格（売値）]]+tbl_明細[[#This Row],[販売価格（M)]] | AB17: =tbl_明細[[#This Row],[販売価格（売値）]]*1.08+tbl_明細[[#This Row],[販売価格（M)]]*1.08
A18: 2601-1005-S01 | B18: =IF(ISBLANK(tbl_明細[[#This Row],[案件番号]]),"",COUNTIFS($A$3:A18,tbl_明細[[#This Row],[案件番号]],$AA$3:AA18,">0")) | C18: =COUNTIFS($A$3:A18,tbl_明細[[#This Row],[案件番号]],$F$3:F18,tbl_明細[[#This Row],[仕入先]]) | D18: =_xlfn.XLOOKUP(tbl_明細[[#This Row],[案件番号]],tbl_採番[案件番号],tbl_採番[顧客],"",0,1) | E18: PRD_SNJ_KDK_0002_01 | F18: =IF(ISBLANK(tbl_明細[[#This Row],[仕入先（M)]]),_xlfn.XLOOKUP(tbl_明細[[#This Row],[商品ID]],商品マスタ[商品連番],商品マスタ[仕入先],"",0,1),tbl_明細[[#This Row],[仕入先（M)]]) | G18: =IF(ISBLANK(tbl_明細[[#This Row],[商品名（M)]]),_xlfn.XLOOKUP(tbl_明細[[#This Row],[商品ID]],商品マスタ[商品連番],商品マスタ[商品名],"",0,),tbl_明細[[#This Row],[商品名（M)]]) | H18: =IF(ISBLANK(tbl_明細[[#This Row],[仕入価格（M)]]),_xlfn.XLOOKUP(tbl_明細[[#This Row],[商品ID]],商品マスタ[商品連番],商品マスタ[仕入 単価],"",0,1),tbl_明細[[#This Row],[仕入価格（M)]]) | I18: =_xlfn.XLOOKUP(tbl_明細[[#This Row],[商品ID]],商品マスタ[商品連番],商品マスタ[国内定価 （15％）],"",0,1) | J18: 18000 | K18: 1.363 | L18: =_xlfn.XLOOKUP(tbl_明細[[#This Row],[商品ID]],商品マスタ[商品連番],商品マスタ[単位],"",0,1) | M18: =1-tbl_明細[[#This Row],[仕入価格]]/tbl_明細[[#This Row],[販売価格（売値）]] | N18: =_xlfn.XLOOKUP(tbl_明細[[#This Row],[商品ID]],商品マスタ[商品連番],商品マスタ[税率],"",0,1) | X18: =tbl_明細[[#This Row],[仕入価格]]*tbl_明細[[#This Row],[数量]]+tbl_明細[[#This Row],[仕入価格（M)]]*tbl_明細[[#This Row],[数量（M)]] | Y18: =tbl_明細[[#This Row],[販売価格（売値）]]*tbl_明細[[#This Row],[数量]]+tbl_明細[[#This Row],[販売価格（M)]]*tbl_明細[[#This Row],[数量（M)]] | Z18: =_xlfn.XLOOKUP(tbl_明細[[#This Row],[案件番号]],tbl_案件追跡[案件番号],tbl_案件追跡[受注],"",0,1) | AA18: =tbl_明細[[#This Row],[販売価格（売値）]]+tbl_明細[[#This Row],[販売価格（M)]] | AB18: =tbl_明細[[#This Row],[販売価格（売値）]]*1.08+tbl_明細[[#This Row],[販売価格（M)]]*1.08
A19: 2601-1005-S01 | B19: =IF(ISBLANK(tbl_明細[[#This Row],[案件番号]]),"",COUNTIFS($A$3:A19,tbl_明細[[#This Row],[案件番号]],$AA$3:AA19,">0")) | C19: =COUNTIFS($A$3:A19,tbl_明細[[#This Row],[案件番号]],$F$3:F19,tbl_明細[[#This Row],[仕入先]]) | D19: =_xlfn.XLOOKUP(tbl_明細[[#This Row],[案件番号]],tbl_採番[案件番号],tbl_採番[顧客],"",0,1) | E19: PRD_SNJ_KDK_0002_01 | F19: =IF(ISBLANK(tbl_明細[[#This Row],[仕入先（M)]]),_xlfn.XLOOKUP(tbl_明細[[#This Row],[商品ID]],商品マスタ[商品連番],商品マスタ[仕入先],"",0,1),tbl_明細[[#This Row],[仕入先（M)]]) | G19: =IF(ISBLANK(tbl_明細[[#This Row],[商品名（M)]]),_xlfn.XLOOKUP(tbl_明細[[#This Row],[商品ID]],商品マスタ[商品連番],商品マスタ[商品名],"",0,),tbl_明細[[#This Row],[商品名（M)]]) | H19: =IF(ISBLANK(tbl_明細[[#This Row],[仕入価格（M)]]),_xlfn.XLOOKUP(tbl_明細[[#This Row],[商品ID]],商品マスタ[商品連番],商品マスタ[仕入 単価],"",0,1),tbl_明細[[#This Row],[仕入価格（M)]]) | I19: =_xlfn.XLOOKUP(tbl_明細[[#This Row],[商品ID]],商品マスタ[商品連番],商品マスタ[国内定価 （15％）],"",0,1) | J19: 18000 | K19: 1.32 | L19: =_xlfn.XLOOKUP(tbl_明細[[#This Row],[商品ID]],商品マスタ[商品連番],商品マスタ[単位],"",0,1) | M19: =1-tbl_明細[[#This Row],[仕入価格]]/tbl_明細[[#This Row],[販売価格（売値）]] | N19: =_xlfn.XLOOKUP(tbl_明細[[#This Row],[商品ID]],商品マスタ[商品連番],商品マスタ[税率],"",0,1) | X19: =tbl_明細[[#This Row],[仕入価格]]*tbl_明細[[#This Row],[数量]]+tbl_明細[[#This Row],[仕入価格（M)]]*tbl_明細[[#This Row],[数量（M)]] | Y19: =tbl_明細[[#This Row],[販売価格（売値）]]*tbl_明細[[#This Row],[数量]]+tbl_明細[[#This Row],[販売価格（M)]]*tbl_明細[[#This Row],[数量（M)]] | Z19: =_xlfn.XLOOKUP(tbl_明細[[#This Row],[案件番号]],tbl_案件追跡[案件番号],tbl_案件追跡[受注],"",0,1) | AA19: =tbl_明細[[#This Row],[販売価格（売値）]]+tbl_明細[[#This Row],[販売価格（M)]] | AB19: =tbl_明細[[#This Row],[販売価格（売値）]]*1.08+tbl_明細[[#This Row],[販売価格（M)]]*1.08
A20: 2601-1005-S01 | B20: =IF(ISBLANK(tbl_明細[[#This Row],[案件番号]]),"",COUNTIFS($A$3:A20,tbl_明細[[#This Row],[案件番号]],$AA$3:AA20,">0")) | C20: =COUNTIFS($A$3:A20,tbl_明細[[#This Row],[案件番号]],$F$3:F20,tbl_明細[[#This Row],[仕入先]]) | D20: =_xlfn.XLOOKUP(tbl_明細[[#This Row],[案件番号]],tbl_採番[案件番号],tbl_採番[顧客],"",0,1) | E20: other | F20: =IF(ISBLANK(tbl_明細[[#This Row],[仕入先（M)]]),_xlfn.XLOOKUP(tbl_明細[[#This Row],[商品ID]],商品マスタ[商品連番],商品マスタ[仕入先],"",0,1),tbl_明細[[#This Row],[仕入先（M)]]) | G20: =IF(ISBLANK(tbl_明細[[#This Row],[商品名（M)]]),_xlfn.XLOOKUP(tbl_明細[[#This Row],[商品ID]],商品マスタ[商品連番],商品マスタ[商品名],"",0,),tbl_明細[[#This Row],[商品名（M)]]) | H20: =IF(ISBLANK(tbl_明細[[#This Row],[仕入価格（M)]]),_xlfn.XLOOKUP(tbl_明細[[#This Row],[商品ID]],商品マスタ[商品連番],商品マスタ[仕入 単価],"",0,1),tbl_明細[[#This Row],[仕入価格（M)]]) | I20: =_xlfn.XLOOKUP(tbl_明細[[#This Row],[商品ID]],商品マスタ[商品連番],商品マスタ[国内定価 （15％）],"",0,1) | L20: =_xlfn.XLOOKUP(tbl_明細[[#This Row],[商品ID]],商品マスタ[商品連番],商品マスタ[単位],"",0,1) | M20: =1-tbl_明細[[#This Row],[仕入価格]]/tbl_明細[[#This Row],[販売価格（売値）]] | N20: =_xlfn.XLOOKUP(tbl_明細[[#This Row],[商品ID]],商品マスタ[商品連番],商品マスタ[税率],"",0,1) | O20: 狩人の蔵 | P20: 送料（北海道） | Q20: 1050 | R20: 1100 | S20: 1 | T20: 式 | U20: 0.1 | X20: =tbl_明細[[#This Row],[仕入価格]]*tbl_明細[[#This Row],[数量]]+tbl_明細[[#This Row],[仕入価格（M)]]*tbl_明細[[#This Row],[数量（M)]] | Y20: =tbl_明細[[#This Row],[販売価格（売値）]]*tbl_明細[[#This Row],[数量]]+tbl_明細[[#This Row],[販売価格（M)]]*tbl_明細[[#This Row],[数量（M)]] | Z20: =_xlfn.XLOOKUP(tbl_明細[[#This Row],[案件番号]],tbl_案件追跡[案件番号],tbl_案件追跡[受注],"",0,1) | AA20: =tbl_明細[[#This Row],[販売価格（売値）]]+tbl_明細[[#This Row],[販売価格（M)]] | AB20: =tbl_明細[[#This Row],[販売価格（売値）]]*1.08+tbl_明細[[#This Row],[販売価格（M)]]*1.08
A21: 2601-1006-S01 | B21: =IF(ISBLANK(tbl_明細[[#This Row],[案件番号]]),"",COUNTIFS($A$3:A21,tbl_明細[[#This Row],[案件番号]],$AA$3:AA21,">0")) | C21: =COUNTIFS($A$3:A21,tbl_明細[[#This Row],[案件番号]],$F$3:F21,tbl_明細[[#This Row],[仕入先]]) | D21: =_xlfn.XLOOKUP(tbl_明細[[#This Row],[案件番号]],tbl_採番[案件番号],tbl_採番[顧客],"",0,1) | E21: PRD_SNJ_GGM_0097_01 | F21: =IF(ISBLANK(tbl_明細[[#This Row],[仕入先（M)]]),_xlfn.XLOOKUP(tbl_明細[[#This Row],[商品ID]],商品マスタ[商品連番],商品マスタ[仕入先],"",0,1),tbl_明細[[#This Row],[仕入先（M)]]) | G21: =IF(ISBLANK(tbl_明細[[#This Row],[商品名（M)]]),_xlfn.XLOOKUP(tbl_明細[[#This Row],[商品ID]],商品マスタ[商品連番],商品マスタ[商品名],"",0,),tbl_明細[[#This Row],[商品名（M)]]) | H21: =IF(ISBLANK(tbl_明細[[#This Row],[仕入価格（M)]]),_xlfn.XLOOKUP(tbl_明細[[#This Row],[商品ID]],商品マスタ[商品連番],商品マスタ[仕入 単価],"",0,1),tbl_明細[[#This Row],[仕入価格（M)]]) | I21: =_xlfn.XLOOKUP(tbl_明細[[#This Row],[商品ID]],商品マスタ[商品連番],商品マスタ[国内定価 （15％）],"",0,1) | J21: 5000 | K21: 2 | L21: =_xlfn.XLOOKUP(tbl_明細[[#This Row],[商品ID]],商品マスタ[商品連番],商品マスタ[単位],"",0,1) | M21: =1-tbl_明細[[#This Row],[仕入価格]]/tbl_明細[[#This Row],[販売価格（売値）]] | N21: =_xlfn.XLOOKUP(tbl_明細[[#This Row],[商品ID]],商品マスタ[商品連番],商品マスタ[税率],"",0,1) | X21: =tbl_明細[[#This Row],[仕入価格]]*tbl_明細[[#This Row],[数量]]+tbl_明細[[#This Row],[仕入価格（M)]]*tbl_明細[[#This Row],[数量（M)]] | Y21: =tbl_明細[[#This Row],[販売価格（売値）]]*tbl_明細[[#This Row],[数量]]+tbl_明細[[#This Row],[販売価格（M)]]*tbl_明細[[#This Row],[数量（M)]] | Z21: =_xlfn.XLOOKUP(tbl_明細[[#This Row],[案件番号]],tbl_案件追跡[案件番号],tbl_案件追跡[受注],"",0,1) | AA21: =tbl_明細[[#This Row],[販売価格（売値）]]+tbl_明細[[#This Row],[販売価格（M)]] | AB21: =tbl_明細[[#This Row],[販売価格（売値）]]*1.08+tbl_明細[[#This Row],[販売価格（M)]]*1.08
A22: 2601-1007-S01 | B22: =IF(ISBLANK(tbl_明細[[#This Row],[案件番号]]),"",COUNTIFS($A$3:A22,tbl_明細[[#This Row],[案件番号]],$AA$3:AA22,">0")) | C22: =COUNTIFS($A$3:A22,tbl_明細[[#This Row],[案件番号]],$F$3:F22,tbl_明細[[#This Row],[仕入先]]) | D22: =_xlfn.XLOOKUP(tbl_明細[[#This Row],[案件番号]],tbl_採番[案件番号],tbl_採番[顧客],"",0,1) | F22: =IF(ISBLANK(tbl_明細[[#This Row],[仕入先（M)]]),_xlfn.XLOOKUP(tbl_明細[[#This Row],[商品ID]],商品マスタ[商品連番],商品マスタ[仕入先],"",0,1),tbl_明細[[#This Row],[仕入先（M)]]) | G22: =IF(ISBLANK(tbl_明細[[#This Row],[商品名（M)]]),_xlfn.XLOOKUP(tbl_明細[[#This Row],[商品ID]],商品マスタ[商品連番],商品マスタ[商品名],"",0,),tbl_明細[[#This Row],[商品名（M)]]) | H22: =IF(ISBLANK(tbl_明細[[#This Row],[仕入価格（M)]]),_xlfn.XLOOKUP(tbl_明細[[#This Row],[商品ID]],商品マスタ[商品連番],商品マスタ[仕入 単価],"",0,1),tbl_明細[[#This Row],[仕入価格（M)]]) | I22: =_xlfn.XLOOKUP(tbl_明細[[#This Row],[商品ID]],商品マスタ[商品連番],商品マスタ[国内定価 （15％）],"",0,1) | J22: 0 | L22: =_xlfn.XLOOKUP(tbl_明細[[#This Row],[商品ID]],商品マスタ[商品連番],商品マスタ[単位],"",0,1) | M22: =1-tbl_明細[[#This Row],[仕入価格]]/tbl_明細[[#This Row],[販売価格（売値）]] | N22: =_xlfn.XLOOKUP(tbl_明細[[#This Row],[商品ID]],商品マスタ[商品連番],商品マスタ[税率],"",0,1) | O22: あぷかの森 | P22: 鹿肉サンプル（ロース、内もも） | Q22: 0 | R22: 0 | S22: 1 | T22: 式 | U22: 0.1 | X22: =tbl_明細[[#This Row],[仕入価格]]*tbl_明細[[#This Row],[数量]]+tbl_明細[[#This Row],[仕入価格（M)]]*tbl_明細[[#This Row],[数量（M)]] | Y22: =tbl_明細[[#This Row],[販売価格（売値）]]*tbl_明細[[#This Row],[数量]]+tbl_明細[[#This Row],[販売価格（M)]]*tbl_明細[[#This Row],[数量（M)]] | Z22: =_xlfn.XLOOKUP(tbl_明細[[#This Row],[案件番号]],tbl_案件追跡[案件番号],tbl_案件追跡[受注],"",0,1) | AA22: =tbl_明細[[#This Row],[販売価格（売値）]]+tbl_明細[[#This Row],[販売価格（M)]] | AB22: =tbl_明細[[#This Row],[販売価格（売値）]]*1.08+tbl_明細[[#This Row],[販売価格（M)]]*1.08
A23: 2602-1002-K01 | B23: =IF(ISBLANK(tbl_明細[[#This Row],[案件番号]]),"",COUNTIFS($A$3:A23,tbl_明細[[#This Row],[案件番号]],$AA$3:AA23,">0")) | C23: =COUNTIFS($A$3:A23,tbl_明細[[#This Row],[案件番号]],$F$3:F23,tbl_明細[[#This Row],[仕入先]]) | D23: =_xlfn.XLOOKUP(tbl_明細[[#This Row],[案件番号]],tbl_採番[案件番号],tbl_採番[顧客],"",0,1) | F23: =IF(ISBLANK(tbl_明細[[#This Row],[仕入先（M)]]),_xlfn.XLOOKUP(tbl_明細[[#This Row],[商品ID]],商品マスタ[商品連番],商品マスタ[仕入先],"",0,1),tbl_明細[[#This Row],[仕入先（M)]]) | G23: =IF(ISBLANK(tbl_明細[[#This Row],[商品名（M)]]),_xlfn.XLOOKUP(tbl_明細[[#This Row],[商品ID]],商品マスタ[商品連番],商品マスタ[商品名],"",0,),tbl_明細[[#This Row],[商品名（M)]]) | H23: =IF(ISBLANK(tbl_明細[[#This Row],[仕入価格（M)]]),_xlfn.XLOOKUP(tbl_明細[[#This Row],[商品ID]],商品マスタ[商品連番],商品マスタ[仕入 単価],"",0,1),tbl_明細[[#This Row],[仕入価格（M)]]) | I23: =_xlfn.XLOOKUP(tbl_明細[[#This Row],[商品ID]],商品マスタ[商品連番],商品マスタ[国内定価 （15％）],"",0,1) | L23: =_xlfn.XLOOKUP(tbl_明細[[#This Row],[商品ID]],商品マスタ[商品連番],商品マスタ[単位],"",0,1) | M23: =1-tbl_明細[[#This Row],[仕入価格]]/tbl_明細[[#This Row],[販売価格（売値）]] | N23: =_xlfn.XLOOKUP(tbl_明細[[#This Row],[商品ID]],商品マスタ[商品連番],商品マスタ[税率],"",0,1) | O23: ベジタブルワークス | P23: レトルトとうもろこし | Q23: 310 | R23: =396/1.08 | S23: 60 | T23: 本 | U23: 0.08 | X23: =tbl_明細[[#This Row],[仕入価格]]*tbl_明細[[#This Row],[数量]]+tbl_明細[[#This Row],[仕入価格（M)]]*tbl_明細[[#This Row],[数量（M)]] | Y23: =tbl_明細[[#This Row],[販売価格（売値）]]*tbl_明細[[#This Row],[数量]]+tbl_明細[[#This Row],[販売価格（M)]]*tbl_明細[[#This Row],[数量（M)]] | Z23: =_xlfn.XLOOKUP(tbl_明細[[#This Row],[案件番号]],tbl_案件追跡[案件番号],tbl_案件追跡[受注],"",0,1) | AA23: =tbl_明細[[#This Row],[販売価格（売値）]]+tbl_明細[[#This Row],[販売価格（M)]] | AB23: =tbl_明細[[#This Row],[販売価格（売値）]]*1.08+tbl_明細[[#This Row],[販売価格（M)]]*1.08
A24: 2602-1002-K01 | B24: =IF(ISBLANK(tbl_明細[[#This Row],[案件番号]]),"",COUNTIFS($A$3:A24,tbl_明細[[#This Row],[案件番号]],$AA$3:AA24,">0")) | C24: =COUNTIFS($A$3:A24,tbl_明細[[#This Row],[案件番号]],$F$3:F24,tbl_明細[[#This Row],[仕入先]]) | D24: =_xlfn.XLOOKUP(tbl_明細[[#This Row],[案件番号]],tbl_採番[案件番号],tbl_採番[顧客],"",0,1) | F24: =IF(ISBLANK(tbl_明細[[#This Row],[仕入先（M)]]),_xlfn.XLOOKUP(tbl_明細[[#This Row],[商品ID]],商品マスタ[商品連番],商品マスタ[仕入先],"",0,1),tbl_明細[[#This Row],[仕入先（M)]]) | G24: =IF(ISBLANK(tbl_明細[[#This Row],[商品名（M)]]),_xlfn.XLOOKUP(tbl_明細[[#This Row],[商品ID]],商品マスタ[商品連番],商品マスタ[商品名],"",0,),tbl_明細[[#This Row],[商品名（M)]]) | H24: =IF(ISBLANK(tbl_明細[[#This Row],[仕入価格（M)]]),_xlfn.XLOOKUP(tbl_明細[[#This Row],[商品ID]],商品マスタ[商品連番],商品マスタ[仕入 単価],"",0,1),tbl_明細[[#This Row],[仕入価格（M)]]) | I24: =_xlfn.XLOOKUP(tbl_明細[[#This Row],[商品ID]],商品マスタ[商品連番],商品マスタ[国内定価 （15％）],"",0,1) | L24: =_xlfn.XLOOKUP(tbl_明細[[#This Row],[商品ID]],商品マスタ[商品連番],商品マスタ[単位],"",0,1) | M24: =1-tbl_明細[[#This Row],[仕入価格]]/tbl_明細[[#This Row],[販売価格（売値）]] | N24: =_xlfn.XLOOKUP(tbl_明細[[#This Row],[商品ID]],商品マスタ[商品連番],商品マスタ[税率],"",0,1) | O24: ベジタブルワークス | P24: レトルトとうもろこし 関西送料 | Q24: 1300 | R24: 0 | S24: 1 | T24: 式 | U24: 0.1 | X24: =tbl_明細[[#This Row],[仕入価格]]*tbl_明細[[#This Row],[数量]]+tbl_明細[[#This Row],[仕入価格（M)]]*tbl_明細[[#This Row],[数量（M)]] | Y24: =tbl_明細[[#This Row],[販売価格（売値）]]*tbl_明細[[#This Row],[数量]]+tbl_明細[[#This Row],[販売価格（M)]]*tbl_明細[[#This Row],[数量（M)]] | Z24: =_xlfn.XLOOKUP(tbl_明細[[#This Row],[案件番号]],tbl_案件追跡[案件番号],tbl_案件追跡[受注],"",0,1) | AA24: =tbl_明細[[#This Row],[販売価格（売値）]]+tbl_明細[[#This Row],[販売価格（M)]] | AB24: =tbl_明細[[#This Row],[販売価格（売値）]]*1.08+tbl_明細[[#This Row],[販売価格（M)]]*1.08
